Workbook
Name AAA: '[2]28-02-97'!#REF!
Name AAA: '[2]28-02-97'!#REF!
Name ACCRUAL: '[3]Acc&Prep'!$A$1:$J$700
Name ACCRUALS: '[3]Acc&Prep'!$D$701
Name Beg_Bal: #REF!
Name Beg_Bal: #REF!
Name CCY: #REF!
Name CCY: #REF!
Name copy.P_LtoAC: #REF!
Name copy.P_LtoAC: #REF!
Name copyCons_toAA: #REF!
Name copyCons_toAA: #REF!
Name Cum_Int: #REF!
Name Cum_Int: #REF!
Name Data: #REF!
Name Data: #REF!
Name data84: '[4]Purchase Order'!$E$52
Name Def.Income: #REF!
Name Def.Income: #REF!
Name Direct: [3]TB!$42:$124
Name dtrj: DATE(YEAR([5]Payments!Loan_Start),MONTH([5]Payments!Loan_Start)+Payment_Number,DAY([5]Payments!Loan_Start))
Name dtrj: DATE(YEAR([5]Payments!Loan_Start),MONTH([5]Payments!Loan_Start)+Payment_Number,DAY([5]Payments!Loan_Start))
Name dtrj: DATE(YEAR([5]Payments!Loan_Start),MONTH([5]Payments!Loan_Start)+Payment_Number,DAY([5]Payments!Loan_Start))
Name dtrj: DATE(YEAR([5]Payments!Loan_Start),MONTH([5]Payments!Loan_Start)+Payment_Number,DAY([5]Payments!Loan_Start))
Name dtrj: DATE(YEAR([5]Payments!Loan_Start),MONTH([5]Payments!Loan_Start)+Payment_Number,DAY([5]Payments!Loan_Start))
Name dtrj: DATE(YEAR([5]Payments!Loan_Start),MONTH([5]Payments!Loan_Start)+Payment_Number,DAY([5]Payments!Loan_Start))
Name dtrj: DATE(YEAR([5]Payments!Loan_Start),MONTH([5]Payments!Loan_Start)+Payment_Number,DAY([5]Payments!Loan_Start))
Name dtrj: DATE(YEAR([5]Payments!Loan_Start),MONTH([5]Payments!Loan_Start)+Payment_Number,DAY([5]Payments!Loan_Start))
Name End_Bal: #REF!
Name End_Bal: #REF!
Name Extra_Pay: #REF!
Name Extra_Pay: #REF!
Name Full_Print: #REF!
Name Full_Print: #REF!
Name Header_Row: ROW(#REF!)
Name Int: #REF!
Name Int: #REF!
Name Interest_Rate: #REF!
Name Interest_Rate: #REF!
Name Last_Row: IF('اجمالى راس المال'!Values_Entered,[6]!Header_Row+'اجمالى راس المال'!Number_of_Payments,[6]!Header_Row)
Name Last_Row: IF('الايرادات '!Values_Entered,Header_Row+'الايرادات '!Number_of_Payments,Header_Row)
Name Last_Row: IF(Values_Entered,Header_Row+Number_of_Payments,Header_Row)
Name Loan_Amount: #REF!
Name Loan_Amount: #REF!
Name Loan_Start: #REF!
Name Loan_Start: #REF!
Name Loan_Years: #REF!
Name Loan_Years: #REF!
Name MonthEnding: #REF!
Name MonthEnding: #REF!
Name nnn: Scheduled_Payment+Extra_Payment
Name nnn: Scheduled_Payment+Extra_Payment
Name nnn: Scheduled_Payment+Extra_Payment
Name nnn: Scheduled_Payment+Extra_Payment
Name nnn: Scheduled_Payment+Extra_Payment
Name nnn: Scheduled_Payment+Extra_Payment
Name nnn: Scheduled_Payment+Extra_Payment
Name nnn: Scheduled_Payment+Extra_Payment
Name Num_Pmt_Per_Year: #REF!
Name Num_Pmt_Per_Year: #REF!

Sheet قاعدة بيانات  
A2: رقم التسجيل | B2: المورد | C2: العنوان | D2: النوع | F2: القسم | G2: التصنيف | I2: نوع المصروف | K2: الكود | L2: اسم الموظف | M2: رقم البطاقه | N2: الوظيفه | O2: الاداره | P2: القسم | Q2: الفرع | R2: تاريخ التعين | S2: تاريخ الاستقاله | T2: الراتب
A3: 535694423 | B3: مانى فيللوز لتكنولوجيا المعلومات وادارة المشروعات | C3: ق44الحي الاول التجمع الخامس القاهره الجديده | D3: مبيعات | E3: =A3 -> 535694423 | F3: الادراه العليا | G3: قيمه | I3: رصيد اول | K3: 88888888 | L3: زينب عبد الكريم عبد العليم الحفناوى | M3: 2908180100628 | N3: وكيل تحصيل هاتفى | O3: مانى فيللوز | P3: التحصيل | Q3: القاهرة | R3: 45545
A4: 643247289 | B4: سيمبل للحلول والتكنولوجيا المالية | C4: الشيخ زايد | D4: مبيعات | E4: =A4 -> 643247289 | F4: الادراه الماليه | G4: القاهرة | I4: اصول | K4: 8 | L4: امل صبرى | M4: 2908180100628 | N4: وكيل تحصيل هاتفى | O4: ميد تقسيط - ماني فيللوز | P4: التحصيل | Q4: المنصورة
A5: 200196375 | B5: شركه رايه للالكترونيات | C5: قسم أول 6 أكتوبر, الجيزه, EG | D5: مبيعات | E5: =A5 -> 200196375 | F5: اداره الموارد البشريه | G5: المنصورة | I5: ض 14% | K5: 1 | L5: احمد شريف سليمان امين سليمان | M5: 29903040101135 | N5: نائب كبير مشرفى تحصيل | O5: متعدد | P5: التحصيل | Q5: القاهرة | R5: 44896
A6: 200029665 | B6: بنك الإسكندرية | C6: شارع قصر النيل | D6: مبيعات | E6: =A6 -> 200029665 | F6: اداره الخدمات المعاونه | G6: القانونيه | I6: انتقالات | K6: 2 | L6: علاء محمد عوض جاد الله | M6: 28602012105474 | N6: مدير تحصيل | O6: التحصيل | P6: التحصيل | Q6: المنصورة
A7: 204896843 | B7: بنك كريدي اجريكول مصر | C7: قسم التجمع الخامس (أول القاهرة الجديدة ), القاهرة, EG | D7: مبيعات | E7: =A7 -> 204896843 | F7: الاداره القانونيه | G7: الخدمات القانونية | I7: صيانه | K7: 4 | L7: وليد عبد الكريم عبد العليم | M7: 28808250100593 | N7: مدير تحصيل | O7: التحصيل | P7: التحصيل | Q7: القاهرة
A8: 547823509 | B8: فاليو لخدمات البيع والتقسيط | C8: القرية الذكية ك 29 طريق ابورواش | D8: مبيعات | E8: =A8 -> 547823509 | F8: اداري | G8: 25 ج | I8: ايجارات | K8: 5 | L8: باسم صلاح عبد الله قوشتى | M8: 28303120101712 | N8: المستشار القانوني | O8: الشئون القانونية | P8: الادارى | Q8: القاهرة
A9: 204901448 | B9: بنك البركة مصر | E9: =A9 -> 204901448 | F9: شركه رايه - تحصيل | G9: 20 أ | I9: جاري شركاء | K9: 9 | L9: عمرو عصام بدر الدين زكي | M9: 29808080106196 | N9: نائب مدير الإدارة القانونية | O9: الشئون القانونية | P9: الادارى | Q9: القاهرة | R9: 44927
A10: 547768524 | B10: امان لتمويل المشروعات | D10: مبيعات | E10: =A10 -> 547768524 | F10: شركه رايه - قانونيه | G10: الدور 15 | I10: رسوم | K10: 10 | L10: عبد المنعم مجدى عبدربه محمد هلهل | M10: 28609291403433 | N10: المدير العام | O10: التحصيل | P10: التحصيل | Q10: القاهرة
A11: 669384283 | B11: ميد للتقسيط | C11: 21 شارع جامعة الدول المهندسين | D11: مبيعات | E11: =A11 -> 669384283 | F11: شركه فاليو - تحصيل | G11: الصعيد | I11: أدوات نظافة | K11: 19 | L11: سحر اوسامة احمد محمد | M11: 29611110104501 | N11: مشرف تحصيل | O11: شركة فاليو | P11: التحصيل | Q11: القاهرة | R11: 45209
A12: 200196375 | B12: شركه رايه قانونى | C12: قسم أول 6 أكتوبر, الجيزه, EG | D12: مبيعات | E12: =A12 -> 200196375 | F12: شركه فاليو - قانونيه | G12: المقر الجديد | I12: سباكه | K12: 20 | L12: عبد العزيز صلاح عبد العزيز على حسن | M12: 29703150100399 | N12: مشرف قضائى | O12: الشئون القانونية | P12: الادارى | Q12: القاهرة | R12: 45003
A13: 200196375 | B13: شركه رايه كوربت | F13: شركه بلنك - تحصيل | I13: انترنت | K13: 25 | L13: منى احمد طه احمد سعد | M13: 27312250101345 | N13: خدمات معاونة | O13: الخدمات المعاونة | P13: الادارى | Q13: القاهرة | R13: 44959
A14: 757680283 | B14: فورى لتكنولوجيا المعلومات التجارية | C14: قطعه اف 12 على بى 221 القريه الذكيه الحى المالى الجيزه قسم الجيزة, الجيزه, EG | F14: شركه بلنك - قانونيه | I14: بوفيه | K14: 31 | L14: محمود النادى أبو الحسن احمد | M14: 28504108800236 | N14: كبير مشرفى تحصيل | O14: بنك كريدى اجريكول | P14: التحصيل | Q14: القاهرة | R14: 45020
A15: 547823509 | B15: فاليو قانونى | F15: شركه سمبيل - تحصيل | I15: اكراميات | K15: 35 | L15: رحمة مصطفى خلف الله حسانين | M15: 30111210101161 | N15: منسق بيانات | O15: منسقى البيانات | P15: الادارى | Q15: القاهرة | R15: 45285
A16: 623670232 | B16: بلنك قانونى | C16: قسم أول 6 أكتوبر, الجيزه, EG | D16: مبيعات | F16: بنك الاسكندريه - تحصيل | I16: تليفونات | K16: 45 | L16: محمد مجدى ربيع عبد الغنى جاد | M16: 28409261402239 | N16: مشرف تحصيل | O16: شركة فاليو | P16: التحصيل | Q16: القاهرة | R16: 45042
A17: 669384283 | B17: ميد قانونى | F17: بنك كريدي - تحصيل | I17: سلف | K17: 54 | L17: رحاب عبد الهادى احمد بدوى | M17: 28706021401264 | N17: مشرف تحصيل | O17: بنك الإسكندرية / شركة سهولة | P17: التحصيل | Q17: القاهرة | R17: 45053
A18: 720831954 | B18: بى ام للتمويل الاستهلاكى | C18: 118وان قطامية أبراج المرشدى | D18: مبيعات | F18: شركه ماني - تحصيل | I18: ادوات مكتبيه | K18: 60 | L18: مروة مصطفى على جاد | M18: 29912120104665 | N18: مشرف تحصيل | O18: شركة راية | P18: التحصيل | Q18: القاهرة | R18: 45062
A19: 332885968 | B19: شركه مشروعى للتجاره | F19: فيزا المحكمة | K19: 277 | L19: ماجد الالفي | N19: محامي | O19: الشئون القانونية | P19: القانونية
A20: 628786476 | B20: شركه حالا للتمويل الاستهلاكى
A21: 499041712 | B21: شركه تساهيل للتمويل
B22: اور للتمويل الاستهلاكى -وسيلة قانونى | F22: شركه ميد تقسيط - تحصيل | I22: ضيافه | K22: 62 | L22: محمد مجدى السيد عبد الدايم | M22: 29710280100451 | N22: مشرف قضائى | O22: الشئون القانونية | P22: الادارى | Q22: القاهرة | R22: 45066
A23: 578890496 | B23: بلتون للتمويل الاستهلاكى سفن | C23: مجمع جاليريا40وحده304محور كريزي ووتر الشيخ زايد | F23: تشغيل القاهره | I23: كهرباء | K23: 64 | L23: تريز سامى رزق شحاته | M23: 28712200101702 | N23: مدير موارد بشرية | O23: الموارد البشرية | P23: الادارى | Q23: القاهرة | R23: 45081
A24: 313018103 | B24: تنميه لخدمات المشروعات متناهيه الصغر | C24: 0 / 9 شياخه المعادى الجديده قسم البساتين شارع أحمد عبد ا | F24: تشغيل المنصورة | I24: نجارة | K24: 71 | L24: ندى محمد سعد محمد | M24: 30110042101308 | N24: وكيل تحصيل هاتفى | O24: بنك كريدى اجريكول | P24: التحصيل | Q24: القاهرة | R24: 45081
A25: 204892465 | B25: ميد بنك | F25: تشغيل الشركه | I25: مرتبات -اداره التحصيل | K25: 83 | L25: حبيبه احمد سلطان منصور عويس | M25: 30312060105762 | N25: مشرف تحصيل | O25: شركة ماني فيللوز | P25: التحصيل | Q25: القاهرة | R25: 45111
A26: 724133259 | B26: اور للتمويل الاستهلاكى -وسيلة | C26: الوحده رقم A 111 -مبنى اركاديا مول كورنيش النيل بولاق | F26: عقود الإنتاج | I26: مرتبات -الشئون القانونية | K26: 97 | L26: ندى محمد محمود عبد المقصود | M26: 30106051400523 | N26: وكيل تحصيل هاتفى | O26: شركة ميد تقسيط | P26: التحصيل | Q26: القاهرة | R26: 45395
A27: 547823509 | B27: فاليو | F27: شركة بلتون | I27: عمولات | K27: 119 | L27: مصطفى جميل عبد الفتاح محمد شاهين | M27: 30302090103319 | N27: وكيل تحصيل | O27: بنك كريدى اجريكول | P27: التحصيل | Q27: القاهرة | R27: 45326
A28: 578890496 | B28: سفن | F28: إدارة التحصيل | I28: استشارات | K28: 125 | L28: زينب محمود محمد محمود صالح | M28: 30108160102829 | N28: وكيل تحصيل هاتفى | O28: شركة ماني فيللوز | P28: التحصيل | Q28: القاهرة | R28: 45326
A29: 725632186 | B29: شهرى للتمويل الاستهلاكى | F29: المصرية للتمويل العقارى | I29: رصيد | K29: 126 | L29: حبيبة عادل بدرالدين احمد | M29: 30107110104522 | N29: وكيل تحصيل هاتفى | O29: شركة ماني فيللوز | P29: التحصيل | Q29: القاهرة | R29: 45326
B30: سهولة قانونى | F30: منسقى البيانات | I30: تبرعات | K30: 127 | L30: احمد عوض عباس عوض كشك | M30: 29103071200577 | N30: نائب كبير مشرفى تحصيل | P30: التحصيل | Q30: المنصورة | R30: 45139
A31: 694058882 | B31: شركة إرادة لتمويل المشروعات | C31: 13 ج شارع احمد كامل تقسيم اللاسلكي المعادي القاهرة | F31: شركة سهولة | I31: تمويل البنك | K31: 129 | L31: نانسى يوسف عزيز يوسف | M31: 28908081201843 | N31: نائب مدير الإدارة القانونية | O31: الشئون القانونية | P31: الادارى | Q31: المنصورة | R31: 45150
B32: تنميه قانوني | F32: شركه ميد تقسيط - قانونية | I32: تامين | K32: 130 | L32: عبد الرحمن عوض عباس عوض كشك | M32: 29909131202315 | N32: مشرف تحصيل | P32: التحصيل | Q32: المنصورة | R32: 45139
A33: 671968785 | B33: الكان فاينانس للخدمات المالية الحديثة | F33: شركة هيما بلاستيك | I33: سمسره | K33: 131 | L33: امانى طارق إبراهيم عبد الحميد | M33: 29501011262064 | N33: منسق بيانات | O33: منسقى البيانات | P33: الادارى | Q33: المنصورة | R33: 45145
B34: سيجما كوم | F34: شركة وسيلة | I34: تمويل خزينه | K34: 133 | L34: نادين عماد منصور محمد | M34: 30106141202127 | N34: رئيس فريق عمل | P34: التحصيل | Q34: المنصورة | R34: 45146
F35: شركة تنمية | I35: مكافات | K35: 136 | L35: بهاء محمد السيد صالح أبو حسين | M35: 28403211200572 | N35: رئيس فريق عمل | P35: التحصيل | Q35: المنصورة | R35: 45139
F36: شركة جلوبال | I36: مرتبات -الادارة المالية | K36: 137 | L36: محمد وفيق إبراهيم عبد المعطى | M36: 28605211200574 | N36: مشرف تحصيل | P36: التحصيل | Q36: المنصورة | R36: 45139
F37: اى اف اس للتخصيم | I37: مرتبات -اداره الموارد البشرية | K37: 148 | L37: امال كمال عبد الله عبد الحليم | M37: 29805050105684 | N37: منسق بيانات | O37: منسقى البيانات | P37: الادارى | Q37: القاهرة | R37: 45164
F38: بنك البركة | I38: مرتبات -الشئون الإدارية | K38: 150 | L38: هدى حسن السيد على الضوى | M38: 30006102101386 | N38: منسق بيانات | O38: منسقى البيانات | P38: الادارى | Q38: القاهرة | R38: 45167
F39: شركة امان | I39: مرتبات -الخدمات المعاونة | K39: 151 | L39: احمد عبد الباسط عبد السلام محمد | M39: 29805101502713 | N39: محاسب | O39: المالية | P39: الادارى | Q39: القاهرة | R39: 45171
A40: 591872528 | B40: الجارحى للاستيراد والتصدير | C40: الهرم | D40: مشتريات | F40: البنك المصرى لتنمية الصادرات | I40: تامينات اجتماعية | K40: 177 | L40: أسماء إبراهيم السيد عبد الله | M40: 30001011278168 | N40: وكيل تحصيل هاتفى | P40: التحصيل | Q40: المنصورة | R40: 45187
A41: 205354793 | B41: جملة ماركت | C41: العبور | D41: مشتريات | F41: مصر للأصول العقارية | I41: كسب العمل | K41: 197 | L41: احمد مجدى بكر على | M41: 29503120100816 | N41: وكيل تحصيل | O41: شركة فاليو | P41: التحصيل | Q41: القاهرة | R41: 45234
A42: 235071579 | B42: شركه اتصالات مصر | C42: التجمع الخامس | D42: مشتريات | F42: الشمس العقارية | I42: اختام | K42: 209 | L42: ريم رضا سيد احمد إبراهيم المطراوى | M42: 29806231401346 | N42: منسق بيانات | O42: الشئون القانونية | P42: الادارى | Q42: القاهرة | R42: 45239
A43: 212699598 | B43: ديجتال اوفيس للتوريدات | C43: باب الشعريه | D43: مشتريات | F43: شركة فورى | I43: مرتبات -الادارة العليا | K43: 215 | L43: روان عادل محمد عبد الكريم | M43: 30503030106403 | N43: وكيل تحصيل هاتفى | O43: شركة فاليو | P43: التحصيل | Q43: القاهرة | R43: 45259
A44: 672466724 | B44: نيرجان للتجارة | C44: الاسكندريه | D44: مشتريات | F44: شركة شهرى | I44: مصروفات نثرية | K44: 221 | L44: عمرو صابر إبراهيم سيد محمد | M44: 29707060104137 | N44: وكيل تحصيل | O44: شركة فاليو | P44: التحصيل | Q44: القاهرة | R44: 45601
A45: 669904856 | B45: ام اس كيو M S Q للاستيراد والتصدير | C45: مدينة نقادة الزوايدة ,مركز قوص | D45: مشتريات | F45: بنك نكست | I45: غاز | K45: 222 | L45: مريم محمد على سيد خطاب | M45: 30403051401184 | N45: مشرف تحصيل | O45: بنك الاسكندرية | P45: التحصيل | Q45: القاهرة | R45: 45266
A46: 506322335 | B46: البنيان للتوريدات والتجارة العامة تريومف | C46: ترعة الجبل الزيتون | D46: مشتريات | F46: شركة حالا | I46: مياة | K46: 223 | L46: هبة خلف محمد احمد | M46: 28107120200563 | N46: وكيل تحصيل هاتفى | O46: شركة راية | P46: التحصيل | Q46: القاهرة | R46: 45266
A47: 463380096 | B47: ايتوال لصناعة وتجارة الحلوى إبراهيم رافت عبد الصادق وشركاة | C47: ش الحرية الزيتون ,قسم الزيتون | D47: مشتريات | F47: ميد بنك | I47: دعايا وإعلان | K47: 238 | L47: اشرف محمد محروس محمود | M47: 30412130100296 | N47: وكيل تحصيل | O47: بنك الإسكندرية | P47: التحصيل | Q47: القاهرة | R47: 45385
A48: 663208343 | B48: الأمين تك عبد الله امين حسن | C48: قسم عابدين القاهرة | D48: مشتريات | F48: ايجى بنك | I48: مصروفات بنكية | K48: 239 | L48: يوسف كامل عبد الله صبحى غنيم | M48: 30405030105677 | N48: وكيل تحصيل | O48: شركة ميد تقسيط | P48: التحصيل | Q48: القاهرة | R48: 45295
A49: 518665143 | B49: دوبيزل ليمتد | C49: القاهرة | D49: مشتريات | F49: شركة جاست | I49: رسوم غرامات | K49: 258 | L49: منار سيد عثمان احمد | M49: 30005070100726 | N49: مشرف تحصيل | O49: شركة سهولة | P49: التحصيل | Q49: القاهرة | R49: 45330
A50: 756563542 | B50: اتش ام اتش لمستلزمات الحاسبات والأدوات الكهربائية | C50: المعادى القاهرة | D50: مشتريات | F50: شركة هيرمس | I50: عيدية | K50: 262 | L50: يارا رمضان يوسف عبده | M50: 30401011401723 | N50: وكيل تحصيل هاتفى | O50: شركة ماني فيللوز | P50: التحصيل | Q50: القاهرة | R50: 45333
A51: 754717062 | B51: اس واى دى للمقاولات والتجارة والتوريدات العمومية | C51: التجمع الخامس | D51: مشتريات | F51: شركة إرادة | I51: مصاريف علاج | K51: 269 | L51: هاجر شريف محمد عبد الرؤف | M51: 30103260102301 | N51: وكيل تحصيل هاتفي | O51: شركة راية | P51: التحصيل | Q51: القاهرة | R51: 45344
A52: 752235184 | B52: بسام محمود محمد مصطفى | C52: المعادى القاهرة | D52: مشتريات | F52: شركة الكان | I52: مرتبات -عقود الانتاج | K52: 273 | L52: ملك رمضان يوسف عبده | M52: 30602171401202 | N52: وكيل تحصيل هاتفى | O52: شركة فاليو | P52: التحصيل | Q52: القاهرة | R52: 45355
A53: 756449782 | B53: ار يو كى للمقاولات والتوريدات العمومية والحديد | C53: المعادى القاهرة | D53: مشتريات | F53: البنك الوطنى الكويتى | I53: اتعاب مهنية | K53: 278 | L53: هشام فتح الله عبدربه فرج | M53: 26303201400474 | N53: وكيل تحصيل | O53: بنك الإسكندرية / شركة سهولة | P53: التحصيل | Q53: القاهرة | R53: 45358
A54: 755197658 | B54: المتحدة للمقاولات والتوريدات | C54: مكرم عبيد | D54: مشتريات | F54: بنك مصر | I54: مرتبات وعمولات | K54: 283 | L54: طارق عصام فتوح حسن | M54: 29601011735072 | N54: وكيل تحصيل | O54: شركة سهولة | P54: التحصيل | Q54: القاهرة | R54: 45367
A55: 244691665 | B55: إسماعيل محمد على وشركاه | C55: ش كامل صدقى الفجالة الازبكية | D55: مشتريات | F55: بنك ابوظبي | I55: المساهمة التكافلية | K55: 284 | L55: زياد كرم عبد الفضيل عبد المجيد | M55: 30208171403094 | N55: وكيل تحصيل | O55: شركة فاليو | P55: التحصيل | Q55: القاهرة | R55: 45370
A56: 212699598 | B56: مينا أنور عطية بطرس | C56: شارع بركة الرطل باب الشعرية | D56: مشتريات | I56: بريد و دمغة | K56: 289 | L56: صبرى عبد الهادى عبد الهادى | M56: 28509251202635 | N56: خدمات معاونة | P56: الادارى | Q56: المنصورة | R56: 45399
A57: 699480213 | B57: مؤسسة سيد للتوريدات العمومية | C57: الجيزة | D57: مشتريات | I57: ضريبة الخصم والاضافة | K57: 294 | L57: باسم ناجى سعد ابرهيم خلف | M57: 29005011201254 | N57: مسئول ادارى | P57: الادارى | Q57: المنصورة | R57: 45400
A58: 205127088 | B58: المصرية لنقل البيانات وى داتا | C58: القرية الذكية | D58: مشتريات | I58: سداد الجمعية | K58: 302 | L58: مى سيد إبراهيم حنفي عقل | M58: 30207051201769 | N58: وكيل تحصيل هاتفى | P58: التحصيل | Q58: المنصورة | R58: 45416
A59: 504380354 | B59: المؤسسة المصرية لمهمات المكاتب | C59: ش محمد عبد الشافى امتداد شارع جيهان | I59: سداد مديونية | K59: 307 | L59: شيماء حمدى حسن ركابى حامد | M59: 29506012100906 | N59: منسق بيانات | O59: منسقى البيانات | P59: الادارى | Q59: القاهرة | R59: 45424
A60: 212724223 | B60: محمد عبد السلام فرج أبو العلا سراج | C60: برج الشاعر ش جيهان | I60: رسوم فتح حساب | K60: 312 | L60: نيرة محمد يوسف عبد المجيد غزى | M60: 30306261201301 | N60: وكيل تحصيل هاتفى | P60: التحصيل | Q60: المنصورة | R60: 45430
I61: توزيع أرباح | K61: 324 | L61: شوقية محمد عثمان احمد | M61: 29706171200384 | N61: وكيل تحصيل هاتفى | O61: شركة سهولة | P61: التحصيل | Q61: المنصورة | R61: 45448
I62: ضريبة أسر الشهداء | K62: 332 | L62: إسماعيل سلامه إسماعيل بركات | M62: 30601161400333 | N62: وكيل تحصيل | O62: شركة ميد تقسيط | P62: التحصيل | Q62: القاهرة | R62: 45465
K63: 334 | L63: عبد الله كامل عبد الله صبحى غنيم | M63: 30304160102938 | N63: وكيل تحصيل | O63: شركة فاليو | P63: التحصيل | Q63: القاهرة | R63: 45467
K64: 336 | L64: زياد احمد سيد محمد | M64: 30507250100398 | N64: وكيل تحصيل | O64: شركة ماني فيللوز | P64: التحصيل | Q64: القاهرة | R64: 13/11/2024
K65: 340 | L65: اميرة شعراوى ابراهيم حامد على | M65: 29203050102561 | N65: كبير مشرفى تحصيل | O65: شركة فاليو | P65: التحصيل | Q65: القاهرة | R65: 45497
K66: 341 | L66: نرمين شعراوى إبراهيم حامد على | M66: 30203190102583 | N66: رئيس فريق عمل | O66: شركة فاليو | P66: التحصيل | Q66: القاهرة | R66: 45482
K67: 345 | L67: دعاء محمد عثمان احمد | M67: 29002011201905 | N67: وكيل تحصيل هاتفى | P67: التحصيل | Q67: المنصورة | R67: 45477
K68: 347 | L68: يحي هاني نبيل عبد التواب | M68: 30508040103757 | N68: وكيل تحصيل | O68: شركة ميد تقسيط | P68: التحصيل | Q68: القاهرة | R68: 45478
K69: 354 | L69: منه رضا فتحى سيد | M69: 30205300101122 | N69: وكيل تحصيل هاتفى | O69: شركة راية | P69: التحصيل | Q69: القاهرة | R69: 45482
K70: 355 | L70: كرستينا مجدى محروس فؤاد | M70: 29903160102844 | N70: وكيل تحصيل هاتفى | O70: بنك الاسكندرية | P70: التحصيل | Q70: القاهرة | R70: 45486
K71: 356 | L71: عبدالله عماد محمد السيد | M71: 29302041400591 | N71: وكيل تحصيل | P71: التحصيل | Q71: المنصورة | R71: 45487
K72: 362 | L72: احمد محمد محمود احمد أبو الدهب | M72: 30505051403192 | N72: وكيل تحصيل | O72: بنك الاسكندرية | P72: التحصيل | Q72: القاهرة | R72: 45497
K73: 365 | L73: محمد رضا سعد حسن الشرقاوى | M73: 29305020111474 | N73: مسئول ادارى | O73: الموارد البشرية | P73: الادارى | Q73: القاهرة | R73: 45498
K74: 370 | L74: اسراء كمال الدين حسن محمد محمود الشافعى | M74: 29601140103228 | N74: وكيل تحصيل هاتفى | O74: بنك كريدى اجريكول | P74: التحصيل | Q74: القاهرة | R74: 45508
K75: 375 | L75: اسراء خالد محمود عبد الله | M75: 29712102101846 | N75: رئيس فريق عمل | O75: شركة تنمية | P75: التحصيل | Q75: القاهرة | R75: 45508
K76: 378 | L76: عبد الحميد نبوى فهيم محمد | M76: 28102150100511 | N76: رئيس فريق عمل | O76: بنك كريدى اجريكول | P76: التحصيل | Q76: القاهرة | R76: 45508
K77: 379 | L77: حسين محمود حسين حسن | M77: 818198924630900 | N77: مشرف تحصيل | O77: بنك كريدى اجريكول | P77: التحصيل | Q77: القاهرة | R77: 45539
K78: 383 | L78: اية حمدى رجب على غنيمة | M78: 30101201202626 | N78: وكيل تحصيل هاتفى | P78: التحصيل | Q78: المنصورة | R78: 45508
K79: 389 | L79: ادهم رؤوف كمال كامل سعيد | M79: 30407270101515 | N79: وكيل تحصيل | O79: شركة راية | P79: التحصيل | Q79: القاهرة | R79: 45637
K80: 395 | L80: مصطفى احمد عبد الهادى محمود | M80: 29705010106934 | N80: وكيل تحصيل | O80: بنك كريدى اجريكول | P80: التحصيل | Q80: القاهرة | R80: 45511
K81: 400 | L81: عبد الرحمن احمد عبد العليم السيد مرعى | M81: 29810270101519 | N81: وكيل تحصيل | O81: شركة فاليو | P81: التحصيل | Q81: القاهرة | R81: 45517
K82: 401 | L82: سامح ماجد الهجرسى الدسوقى | M82: 27301211204771 | N82: مشرف تحصيل | P82: التحصيل | Q82: المنصورة | R82: 45516
K83: 402 | L83: ياسر عبد الحكيم حمزة أبو النيل | M83: 27309251700756 | N83: وكيل تحصيل | P83: التحصيل | Q83: المنصورة | R83: 45517
K84: 404 | L84: اصالة مهدى محمد احمد | M84: 30109290101804 | N84: وكيل تحصيل هاتفى | O84: بنك الاسكندرية | P84: التحصيل | Q84: القاهرة | R84: 45519
K85: 410 | L85: سيف طارق محمد إسماعيل | M85: 30605100100332 | N85: وكيل تحصيل | O85: بنك كريدى اجريكول | P85: التحصيل | Q85: القاهرة | R85: 45521
K86: 416 | L86: هاني جمعه علي احمد | M86: 27610261201733 | N86: وكيل تحصيل | P86: التحصيل | Q86: المنصورة | R86: 45531
K87: 418 | L87: احمد حمدى محمد سرور | M87: 28302221701951 | N87: وكيل تحصيل | O87: وكيل تحصيل | P87: التحصيل | Q87: المنصورة | R87: 45539
K88: 421 | L88: محمد احمد ناجز سعيد | M88: 30609022100334 | N88: وكيل تحصيل | O88: بنك كريدى اجريكول | P88: التحصيل | Q88: القاهرة | R88: 45539
K89: 425 | L89: احمد رزق طاهر أبو الفتوح | M89: 29403171201019 | N89: وكيل تحصيل | O89: شركة تنمية | P89: التحصيل | Q89: المنصورة | R89: 45566
K90: 426 | L90: هدير رمضان مصطفي عبد العال | M90: 29908201201021 | N90: وكيل تحصيل هاتفى | O90: وكيل تحصيل هاتفى | P90: التحصيل | Q90: المنصورة | R90: 45539
K91: 428 | L91: سحر محمد علي سيد | M91: 29101201401488 | N91: منسق بيانات | O91: منسقى البيانات | P91: الادارى | Q91: القاهرة | R91: 45566
K92: 444 | L92: نورين محمود عبد السلام | M92: 30301181400409 | N92: وكيل تحصيل هاتفى | O92: شركة راية | P92: التحصيل | Q92: القاهرة | R92: 45557
K93: 445 | L93: أسماء عباس عثمان عباس | M93: 29012100105168 | N93: خدمات معاونة | O93: الخدمات المعاونة | P93: الادارى | Q93: القاهرة | R93: 45557
K94: 448 | L94: ياسمين ماهر زيدان محمود عبد الباقي | M94: 30201111402604 | N94: وكيل تحصيل هاتفى | O94: شركة سهولة | P94: التحصيل | Q94: القاهرة | R94: 45561
K95: 456 | L95: مختار محمد محمد مختار | M95: 28705180300154 | N95: وكيل تحصيل | O95: شركة ماني فيللوز | P95: التحصيل | Q95: القاهرة | R95: 45570
K96: 460 | L96: احمد اشرف محمد حسن | M96: 30205240100555 | N96: وكيل تحصيل | O96: شركة وسيله /بنك اسكندرية | P96: التحصيل | Q96: القاهرة | R96: 17/12/2024
K97: 461 | L97: كريم جمال السيد عبد الهادي | M97: 29305041401219 | N97: كبير مشرفى تحصيل | O97: بنك كريدى اجريكول | P97: التحصيل | Q97: القاهرة | R97: 45574
K98: 462 | L98: رنيم إبراهيم محمد احمد مجاهد | M98: 0 | N98: وكيل تحصيل هاتفى | O98: شركة تنمية | P98: التحصيل | Q98: المنصورة | R98: 45574
K99: 466 | L99: فاطمة محمود سلامة إبراهيم | M99: 29309251200181 | N99: وكيل تحصيل هاتفى | O99: شركة تنمية | P99: التحصيل | Q99: المنصورة | R99: 45575
K100: 467 | L100: مى علاء السيد محمد غريب | M100: 30102051204885 | N100: وكيل تحصيل هاتفى | O100: شركة تنمية | P100: التحصيل | Q100: المنصورة | R100: 45575
K101: 468 | L101: حسام حسن محمد حسن | M101: 29405100101555 | N101: وكيل تحصيل | O101: شركة فاليو | P101: التحصيل | Q101: القاهرة | R101: 45578
...

Sheet تحليلات 2024
B1: Jan | O1: Feb | AB1: Mar
A2: الإيرادات -14% | B2: القاهرة | D2: المنصورة | F2: القانونيه | H2: الخدمات القانونية | J2: قيمه | L2: الإجمالي | O2: القاهرة | Q2: المنصورة | S2: القانونيه | U2: الخدمات القانونية | W2: قيمه | Y2: الإجمالي | AB2: القاهرة | AD2: المنصورة | AF2: القانونيه | AH2: الخدمات القانونية | AJ2: قيمه | AL2: الإجمالي | AO2: القاهرة | AQ2: المنصورة | AS2: القانونيه | AU2: الخدمات القانونية | AW2: قيمه | AY2: الإجمالي
A3: شركه رايه - تحصيل | B3: 76955.623 | C3: =IFERROR((B3/$B$18),0) -> 0.11711088 | D3: 11748.009 | E3: =IFERROR((D3/$D$18),0) -> 0.067186484 | G3: =IFERROR((F3/$F$18),0) -> 0 | I3: =IFERROR((H3/$H$18),0) -> 0 | K3: =IFERROR((J3/$H$18),0) -> 0 | L3: =B3+D3+H3+J3 -> 88703.632 | M3: =IFERROR((L3/$L$18),0) -> 0.10576092 | O3: 63271.22 | P3: =IFERROR((O3/$B$18),0) -> 0.096285985 | Q3: 11430.21 | R3: =IFERROR((Q3/$D$18),0) -> 0.065369003 | T3: =IFERROR((S3/$H$18),0) -> 0 | V3: =IFERROR((U3/$H$18),0) -> 0 | X3: =IFERROR((W3/$H$18),0) -> 0 | Y3: =O3+Q3+U3+W3+S3 -> 74701.43 | Z3: =IFERROR((Y3/$L$18),0) -> 0.089066161 | AC3: =IFERROR((AB3/$B$18),0) -> 0 | AE3: =IFERROR((AD3/$D$18),0) -> 0 | AG3: =IFERROR((AF3/$H$18),0) -> 0 | AI3: =IFERROR((AH3/$H$18),0) -> 0 | AK3: =IFERROR((AJ3/$H$18),0) -> 0 | AL3: =AB3+AD3+AH3+AJ3+AF3 -> 0 | AM3: =IFERROR((AL3/$L$18),0) -> 0 | AP3: =IFERROR((AO3/$B$18),0) -> 0 | AR3: =IFERROR((AQ3/$D$18),0) -> 0 | AT3: =IFERROR((AS3/$H$18),0) -> 0 | AV3: =IFERROR((AU3/$H$18),0) -> 0 | AX3: =IFERROR((AW3/$H$18),0) -> 0 | AY3: =AO3+AQ3+AU3+AW3+AS3 -> 0 | AZ3: =IFERROR((AY3/$L$18),0) -> 0
A4: شركه رايه - قانونيه | C4: =IFERROR((B4/$B$18),0) -> 0 | E4: =IFERROR((D4/$D$18),0) -> 0 | F4: 6744.0439 | G4: =IFERROR((F4/$H$18),0) -> 0 | I4: =IFERROR((H4/$H$18),0) -> 0 | K4: =IFERROR((J4/$H$18),0) -> 0 | L4: =B4+D4+H4+J4 -> 0 | M4: =IFERROR((L4/$L$18),0) -> 0 | P4: =IFERROR((O4/$B$18),0) -> 0 | R4: =IFERROR((Q4/$D$18),0) -> 0 | T4: =IFERROR((S4/$H$18),0) -> 0 | V4: =IFERROR((U4/$H$18),0) -> 0 | X4: =IFERROR((W4/$H$18),0) -> 0 | Y4: =O4+Q4+U4+W4+S4 -> 0 | Z4: =IFERROR((Y4/$L$18),0) -> 0 | AC4: =IFERROR((AB4/$B$18),0) -> 0 | AE4: =IFERROR((AD4/$D$18),0) -> 0 | AG4: =IFERROR((AF4/$H$18),0) -> 0 | AI4: =IFERROR((AH4/$H$18),0) -> 0 | AK4: =IFERROR((AJ4/$H$18),0) -> 0 | AL4: =AB4+AD4+AH4+AJ4+AF4 -> 0 | AM4: =IFERROR((AL4/$L$18),0) -> 0 | AP4: =IFERROR((AO4/$B$18),0) -> 0 | AR4: =IFERROR((AQ4/$D$18),0) -> 0 | AT4: =IFERROR((AS4/$H$18),0) -> 0 | AV4: =IFERROR((AU4/$H$18),0) -> 0 | AX4: =IFERROR((AW4/$H$18),0) -> 0 | AY4: =AO4+AQ4+AU4+AW4+AS4 -> 0 | AZ4: =IFERROR((AY4/$L$18),0) -> 0
A5: شركه فاليو - تحصيل | B5: 140893.41 | C5: =IFERROR((B5/$B$18),0) -> 0.21441125 | D5: 6666.7715 | E5: =IFERROR((D5/$D$18),0) -> 0.038127051 | G5: =IFERROR((F5/$H$18),0) -> 0 | I5: =IFERROR((H5/$H$18),0) -> 0 | K5: =IFERROR((J5/$H$18),0) -> 0 | L5: =B5+D5+H5+J5 -> 147560.18 | M5: =IFERROR((L5/$L$18),0) -> 0.17593531 | O5: 54751.84 | P5: =IFERROR((O5/$B$18),0) -> 0.083321214 | Q5: 7112.38 | R5: =IFERROR((Q5/$D$18),0) -> 0.040675472 | T5: =IFERROR((S5/$H$18),0) -> 0 | V5: =IFERROR((U5/$H$18),0) -> 0 | X5: =IFERROR((W5/$H$18),0) -> 0 | Y5: =O5+Q5+U5+W5+S5 -> 61864.22 | Z5: =IFERROR((Y5/$L$18),0) -> 0.073760417 | AC5: =IFERROR((AB5/$B$18),0) -> 0 | AE5: =IFERROR((AD5/$D$18),0) -> 0 | AG5: =IFERROR((AF5/$H$18),0) -> 0 | AI5: =IFERROR((AH5/$H$18),0) -> 0 | AK5: =IFERROR((AJ5/$H$18),0) -> 0 | AL5: =AB5+AD5+AH5+AJ5+AF5 -> 0 | AM5: =IFERROR((AL5/$L$18),0) -> 0 | AP5: =IFERROR((AO5/$B$18),0) -> 0 | AR5: =IFERROR((AQ5/$D$18),0) -> 0 | AT5: =IFERROR((AS5/$H$18),0) -> 0 | AV5: =IFERROR((AU5/$H$18),0) -> 0 | AX5: =IFERROR((AW5/$H$18),0) -> 0 | AY5: =AO5+AQ5+AU5+AW5+AS5 -> 0 | AZ5: =IFERROR((AY5/$L$18),0) -> 0
A6: شركه فاليو - قانونيه | C6: =IFERROR((B6/$B$18),0) -> 0 | E6: =IFERROR((D6/$D$18),0) -> 0 | G6: =IFERROR((F6/$H$18),0) -> 0 | I6: =IFERROR((H6/$H$18),0) -> 0 | K6: =IFERROR((J6/$H$18),0) -> 0 | L6: =B6+D6+H6+J6+F6 -> 0 | M6: =IFERROR((L6/$L$18),0) -> 0 | P6: =IFERROR((O6/$B$18),0) -> 0 | R6: =IFERROR((Q6/$D$18),0) -> 0 | T6: =IFERROR((S6/$H$18),0) -> 0 | V6: =IFERROR((U6/$H$18),0) -> 0 | X6: =IFERROR((W6/$H$18),0) -> 0 | Y6: =O6+Q6+U6+W6+S6 -> 0 | Z6: =IFERROR((Y6/$L$18),0) -> 0 | AC6: =IFERROR((AB6/$B$18),0) -> 0 | AE6: =IFERROR((AD6/$D$18),0) -> 0 | AG6: =IFERROR((AF6/$H$18),0) -> 0 | AI6: =IFERROR((AH6/$H$18),0) -> 0 | AK6: =IFERROR((AJ6/$H$18),0) -> 0 | AL6: =AB6+AD6+AH6+AJ6+AF6 -> 0 | AM6: =IFERROR((AL6/$L$18),0) -> 0 | AP6: =IFERROR((AO6/$B$18),0) -> 0 | AR6: =IFERROR((AQ6/$D$18),0) -> 0 | AT6: =IFERROR((AS6/$H$18),0) -> 0 | AV6: =IFERROR((AU6/$H$18),0) -> 0 | AX6: =IFERROR((AW6/$H$18),0) -> 0 | AY6: =AO6+AQ6+AU6+AW6+AS6 -> 0 | AZ6: =IFERROR((AY6/$L$18),0) -> 0
A7: شركه بلنك - تحصيل | C7: =IFERROR((B7/$B$18),0) -> 0 | E7: =IFERROR((D7/$D$18),0) -> 0 | G7: =IFERROR((F7/$H$18),0) -> 0 | I7: =IFERROR((H7/$H$18),0) -> 0 | K7: =IFERROR((J7/$H$18),0) -> 0 | L7: =B7+D7+H7+J7+F7 -> 0 | M7: =IFERROR((L7/$L$18),0) -> 0 | P7: =IFERROR((O7/$B$18),0) -> 0 | R7: =IFERROR((Q7/$D$18),0) -> 0 | T7: =IFERROR((S7/$H$18),0) -> 0 | V7: =IFERROR((U7/$H$18),0) -> 0 | X7: =IFERROR((W7/$H$18),0) -> 0 | Y7: =O7+Q7+U7+W7+S7 -> 0 | Z7: =IFERROR((Y7/$L$18),0) -> 0 | AC7: =IFERROR((AB7/$B$18),0) -> 0 | AE7: =IFERROR((AD7/$D$18),0) -> 0 | AG7: =IFERROR((AF7/$H$18),0) -> 0 | AI7: =IFERROR((AH7/$H$18),0) -> 0 | AK7: =IFERROR((AJ7/$H$18),0) -> 0 | AL7: =AB7+AD7+AH7+AJ7+AF7 -> 0 | AM7: =IFERROR((AL7/$L$18),0) -> 0 | AP7: =IFERROR((AO7/$B$18),0) -> 0 | AR7: =IFERROR((AQ7/$D$18),0) -> 0 | AT7: =IFERROR((AS7/$H$18),0) -> 0 | AV7: =IFERROR((AU7/$H$18),0) -> 0 | AX7: =IFERROR((AW7/$H$18),0) -> 0 | AY7: =AO7+AQ7+AU7+AW7+AS7 -> 0 | AZ7: =IFERROR((AY7/$L$18),0) -> 0
A8: شركه بلنك - قانونيه | C8: =IFERROR((B8/$B$18),0) -> 0 | E8: =IFERROR((D8/$D$18),0) -> 0 | G8: =IFERROR((F8/$H$18),0) -> 0 | I8: =IFERROR((H8/$H$18),0) -> 0 | K8: =IFERROR((J8/$H$18),0) -> 0 | L8: =B8+D8+H8+J8+F8 -> 0 | M8: =IFERROR((L8/$L$18),0) -> 0 | P8: =IFERROR((O8/$B$18),0) -> 0 | R8: =IFERROR((Q8/$D$18),0) -> 0 | T8: =IFERROR((S8/$H$18),0) -> 0 | V8: =IFERROR((U8/$H$18),0) -> 0 | X8: =IFERROR((W8/$H$18),0) -> 0 | Y8: =O8+Q8+U8+W8+S8 -> 0 | Z8: =IFERROR((Y8/$L$18),0) -> 0 | AC8: =IFERROR((AB8/$B$18),0) -> 0 | AE8: =IFERROR((AD8/$D$18),0) -> 0 | AG8: =IFERROR((AF8/$H$18),0) -> 0 | AI8: =IFERROR((AH8/$H$18),0) -> 0 | AK8: =IFERROR((AJ8/$H$18),0) -> 0 | AL8: =AB8+AD8+AH8+AJ8+AF8 -> 0 | AM8: =IFERROR((AL8/$L$18),0) -> 0 | AP8: =IFERROR((AO8/$B$18),0) -> 0 | AR8: =IFERROR((AQ8/$D$18),0) -> 0 | AT8: =IFERROR((AS8/$H$18),0) -> 0 | AV8: =IFERROR((AU8/$H$18),0) -> 0 | AX8: =IFERROR((AW8/$H$18),0) -> 0 | AY8: =AO8+AQ8+AU8+AW8+AS8 -> 0 | AZ8: =IFERROR((AY8/$L$18),0) -> 0
A9: شركه سمبيل - تحصيل | B9: 1061.02 | C9: =IFERROR((B9/$B$18),0) -> 0.0016146576 | E9: =IFERROR((D9/$D$18),0) -> 0 | G9: =IFERROR((F9/$H$18),0) -> 0 | I9: =IFERROR((H9/$H$18),0) -> 0 | K9: =IFERROR((J9/$H$18),0) -> 0 | L9: =B9+D9+H9+J9+F9 -> 1061.02 | M9: =IFERROR((L9/$L$18),0) -> 0.0012650491 | O9: 344.34211 | P9: =IFERROR((O9/$B$18),0) -> 0.00052401896 | R9: =IFERROR((Q9/$D$18),0) -> 0 | T9: =IFERROR((S9/$H$18),0) -> 0 | V9: =IFERROR((U9/$H$18),0) -> 0 | X9: =IFERROR((W9/$H$18),0) -> 0 | Y9: =O9+Q9+U9+W9+S9 -> 344.34211 | Z9: =IFERROR((Y9/$L$18),0) -> 0.00041055746 | AC9: =IFERROR((AB9/$B$18),0) -> 0 | AE9: =IFERROR((AD9/$D$18),0) -> 0 | AG9: =IFERROR((AF9/$H$18),0) -> 0 | AI9: =IFERROR((AH9/$H$18),0) -> 0 | AK9: =IFERROR((AJ9/$H$18),0) -> 0 | AL9: =AB9+AD9+AH9+AJ9+AF9 -> 0 | AM9: =IFERROR((AL9/$L$18),0) -> 0 | AP9: =IFERROR((AO9/$B$18),0) -> 0 | AR9: =IFERROR((AQ9/$D$18),0) -> 0 | AT9: =IFERROR((AS9/$H$18),0) -> 0 | AV9: =IFERROR((AU9/$H$18),0) -> 0 | AX9: =IFERROR((AW9/$H$18),0) -> 0 | AY9: =AO9+AQ9+AU9+AW9+AS9 -> 0 | AZ9: =IFERROR((AY9/$L$18),0) -> 0
A10: بنك الاسكندريه - تحصيل | B10: 283688.43 | C10: =IFERROR((B10/$B$18),0) -> 0.43171635 | D10: 123009.94 | E10: =IFERROR((D10/$D$18),0) -> 0.7034899 | G10: =IFERROR((F10/$H$18),0) -> 0 | I10: =IFERROR((H10/$H$18),0) -> 0 | K10: =IFERROR((J10/$H$18),0) -> 0 | L10: =B10+D10+H10+J10+F10 -> 406698.38 | M10: =IFERROR((L10/$L$18),0) -> 0.48490455 | O10: 40005.19 | P10: =IFERROR((O10/$B$18),0) -> 0.060879799 | Q10: 81951.65 | R10: =IFERROR((Q10/$D$18),0) -> 0.46867884 | T10: =IFERROR((S10/$H$18),0) -> 0 | V10: =IFERROR((U10/$H$18),0) -> 0 | X10: =IFERROR((W10/$H$18),0) -> 0 | Y10: =O10+Q10+U10+W10+S10 -> 121956.84 | Z10: =IFERROR((Y10/$L$18),0) -> 0.14540856 | AC10: =IFERROR((AB10/$B$18),0) -> 0 | AE10: =IFERROR((AD10/$D$18),0) -> 0 | AG10: =IFERROR((AF10/$H$18),0) -> 0 | AI10: =IFERROR((AH10/$H$18),0) -> 0 | AK10: =IFERROR((AJ10/$H$18),0) -> 0 | AL10: =AB10+AD10+AH10+AJ10+AF10 -> 0 | AM10: =IFERROR((AL10/$L$18),0) -> 0 | AP10: =IFERROR((AO10/$B$18),0) -> 0 | AR10: =IFERROR((AQ10/$D$18),0) -> 0 | AT10: =IFERROR((AS10/$H$18),0) -> 0 | AV10: =IFERROR((AU10/$H$18),0) -> 0 | AX10: =IFERROR((AW10/$H$18),0) -> 0 | AY10: =AO10+AQ10+AU10+AW10+AS10 -> 0 | AZ10: =IFERROR((AY10/$L$18),0) -> 0
A11: بنك كريدي - تحصيل | B11: 81005.25 | C11: =IFERROR((B11/$B$18),0) -> 0.12327359 | D11: 18945.227 | E11: =IFERROR((D11/$D$18),0) -> 0.10834714 | G11: =IFERROR((F11/$H$18),0) -> 0 | I11: =IFERROR((H11/$H$18),0) -> 0 | K11: =IFERROR((J11/$H$18),0) -> 0 | L11: =B11+D11+H11+J11+F11 -> 99950.477 | M11: =IFERROR((L11/$L$18),0) -> 0.11917048 | O11: 20066.756 | P11: =IFERROR((O11/$B$18),0) -> 0.030537539 | Q11: 41885.994 | R11: =IFERROR((Q11/$D$18),0) -> 0.23954465 | T11: =IFERROR((S11/$H$18),0) -> 0 | V11: =IFERROR((U11/$H$18),0) -> 0 | X11: =IFERROR((W11/$H$18),0) -> 0 | Y11: =O11+Q11+U11+W11+S11 -> 61952.75 | Z11: =IFERROR((Y11/$L$18),0) -> 0.073865971 | AC11: =IFERROR((AB11/$B$18),0) -> 0 | AE11: =IFERROR((AD11/$D$18),0) -> 0 | AG11: =IFERROR((AF11/$H$18),0) -> 0 | AI11: =IFERROR((AH11/$H$18),0) -> 0 | AK11: =IFERROR((AJ11/$H$18),0) -> 0 | AL11: =AB11+AD11+AH11+AJ11+AF11 -> 0 | AM11: =IFERROR((AL11/$L$18),0) -> 0 | AP11: =IFERROR((AO11/$B$18),0) -> 0 | AR11: =IFERROR((AQ11/$D$18),0) -> 0 | AT11: =IFERROR((AS11/$H$18),0) -> 0 | AV11: =IFERROR((AU11/$H$18),0) -> 0 | AX11: =IFERROR((AW11/$H$18),0) -> 0 | AY11: =AO11+AQ11+AU11+AW11+AS11 -> 0 | AZ11: =IFERROR((AY11/$L$18),0) -> 0
A12: شركه ماني - تحصيل | B12: 42995.73 | C12: =IFERROR((B12/$B$18),0) -> 0.065430795 | D12: 11737.56 | E12: =IFERROR((D12/$D$18),0) -> 0.067126727 | G12: =IFERROR((F12/$H$18),0) -> 0 | I12: =IFERROR((H12/$H$18),0) -> 0 | K12: =IFERROR((J12/$H$18),0) -> 0 | L12: =B12+D12+H12+J12+F12 -> 54733.29 | M12: =IFERROR((L12/$L$18),0) -> 0.065258243 | O12: 30877.18 | P12: =IFERROR((O12/$B$18),0) -> 0.046988816 | Q12: 7741.34 | R12: =IFERROR((Q12/$D$18),0) -> 0.044272474 | T12: =IFERROR((S12/$H$18),0) -> 0 | V12: =IFERROR((U12/$H$18),0) -> 0 | X12: =IFERROR((W12/$H$18),0) -> 0 | Y12: =O12+Q12+U12+W12+S12 -> 38618.52 | Z12: =IFERROR((Y12/$L$18),0) -> 0.046044679 | AC12: =IFERROR((AB12/$B$18),0) -> 0 | AE12: =IFERROR((AD12/$D$18),0) -> 0 | AG12: =IFERROR((AF12/$H$18),0) -> 0 | AI12: =IFERROR((AH12/$H$18),0) -> 0 | AK12: =IFERROR((AJ12/$H$18),0) -> 0 | AL12: =AB12+AD12+AH12+AJ12+AF12 -> 0 | AM12: =IFERROR((AL12/$L$18),0) -> 0 | AP12: =IFERROR((AO12/$B$18),0) -> 0 | AR12: =IFERROR((AQ12/$D$18),0) -> 0 | AT12: =IFERROR((AS12/$H$18),0) -> 0 | AV12: =IFERROR((AU12/$H$18),0) -> 0 | AX12: =IFERROR((AW12/$H$18),0) -> 0 | AY12: =AO12+AQ12+AU12+AW12+AS12 -> 0 | AZ12: =IFERROR((AY12/$L$18),0) -> 0
A13: شركه ميد تقسيط - تحصيل | B13: 30518.176 | C13: =IFERROR((B13/$B$18),0) -> 0.046442484 | D13: 2749.2192 | E13: =IFERROR((D13/$D$18),0) -> 0.015722696 | G13: =IFERROR((F13/$H$18),0) -> 0 | I13: =IFERROR((H13/$H$18),0) -> 0 | K13: =IFERROR((J13/$H$18),0) -> 0 | L13: =B13+D13+H13+J13+F13 -> 33267.395 | M13: =IFERROR((L13/$L$18),0) -> 0.039664557 | O13: 39834.86 | P13: =IFERROR((O13/$B$18),0) -> 0.060620591 | Q13: 2400.12 | R13: =IFERROR((Q13/$D$18),0) -> 0.013726209 | T13: =IFERROR((S13/$H$18),0) -> 0 | V13: =IFERROR((U13/$H$18),0) -> 0 | X13: =IFERROR((W13/$H$18),0) -> 0 | Y13: =O13+Q13+U13+W13+S13 -> 42234.98 | Z13: =IFERROR((Y13/$L$18),0) -> 0.050356567 | AC13: =IFERROR((AB13/$B$18),0) -> 0 | AE13: =IFERROR((AD13/$D$18),0) -> 0 | AG13: =IFERROR((AF13/$H$18),0) -> 0 | AI13: =IFERROR((AH13/$H$18),0) -> 0 | AK13: =IFERROR((AJ13/$H$18),0) -> 0 | AL13: =AB13+AD13+AH13+AJ13+AF13 -> 0 | AM13: =IFERROR((AL13/$L$18),0) -> 0 | AP13: =IFERROR((AO13/$B$18),0) -> 0 | AR13: =IFERROR((AQ13/$D$18),0) -> 0 | AT13: =IFERROR((AS13/$H$18),0) -> 0 | AV13: =IFERROR((AU13/$H$18),0) -> 0 | AX13: =IFERROR((AW13/$H$18),0) -> 0 | AY13: =AO13+AQ13+AU13+AW13+AS13 -> 0 | AZ13: =IFERROR((AY13/$L$18),0) -> 0
A14: شركه رايه - كوربت | C14: =IFERROR((B14/$B$18),0) -> 0 | E14: =IFERROR((D14/$D$18),0) -> 0 | G14: =IFERROR((F14/$H$18),0) -> 0 | I14: =IFERROR((H14/$H$18),0) -> 0 | K14: =IFERROR((J14/$H$18),0) -> 0 | L14: =B14+D14+H14+J14+F14 -> 0 | M14: =IFERROR((L14/$L$18),0) -> 0 | O14: 3250 | P14: =IFERROR((O14/$B$18),0) -> 0.0049458419 | R14: =IFERROR((Q14/$D$18),0) -> 0 | T14: =IFERROR((S14/$H$18),0) -> 0 | V14: =IFERROR((U14/$H$18),0) -> 0 | X14: =IFERROR((W14/$H$18),0) -> 0 | Y14: =O14+Q14+U14+W14+S14 -> 3250 | Z14: =IFERROR((Y14/$L$18),0) -> 0.0038749596 | AC14: =IFERROR((AB14/$B$18),0) -> 0 | AE14: =IFERROR((AD14/$D$18),0) -> 0 | AG14: =IFERROR((AF14/$H$18),0) -> 0 | AI14: =IFERROR((AH14/$H$18),0) -> 0 | AK14: =IFERROR((AJ14/$H$18),0) -> 0 | AL14: =AB14+AD14+AH14+AJ14+AF14 -> 0 | AM14: =IFERROR((AL14/$L$18),0) -> 0 | AP14: =IFERROR((AO14/$B$18),0) -> 0 | AR14: =IFERROR((AQ14/$D$18),0) -> 0 | AT14: =IFERROR((AS14/$H$18),0) -> 0 | AV14: =IFERROR((AU14/$H$18),0) -> 0 | AX14: =IFERROR((AW14/$H$18),0) -> 0 | AY14: =AO14+AQ14+AU14+AW14+AS14 -> 0 | AZ14: =IFERROR((AY14/$L$18),0) -> 0
A15: الخدمات القانونية | C15: =IFERROR((B15/$B$18),0) -> 0 | E15: =IFERROR((D15/$D$18),0) -> 0 | G15: =IFERROR((F15/$H$18),0) -> 0 | I15: =IFERROR((H15/$H$18),0) -> 0 | K15: =IFERROR((J15/$H$18),0) -> 0 | L15: =B15+D15+H15+J15+F15 -> 0 | M15: =IFERROR((L15/$L$18),0) -> 0 | P15: =IFERROR((O15/$B$18),0) -> 0 | R15: =IFERROR((Q15/$D$18),0) -> 0 | T15: =IFERROR((S15/$H$18),0) -> 0 | U15: 3000 | V15: =IFERROR((U15/$H$18),0) -> 0 | X15: =IFERROR((W15/$H$18),0) -> 0 | Y15: =O15+Q15+U15+W15+S15 -> 3000 | Z15: =IFERROR((Y15/$L$18),0) -> 0.0035768858 | AC15: =IFERROR((AB15/$B$18),0) -> 0 | AE15: =IFERROR((AD15/$D$18),0) -> 0 | AG15: =IFERROR((AF15/$H$18),0) -> 0 | AI15: =IFERROR((AH15/$H$18),0) -> 0 | AK15: =IFERROR((AJ15/$H$18),0) -> 0 | AL15: =AB15+AD15+AH15+AJ15+AF15 -> 0 | AM15: =IFERROR((AL15/$L$18),0) -> 0 | AP15: =IFERROR((AO15/$B$18),0) -> 0 | AR15: =IFERROR((AQ15/$D$18),0) -> 0 | AT15: =IFERROR((AS15/$H$18),0) -> 0 | AV15: =IFERROR((AU15/$H$18),0) -> 0 | AX15: =IFERROR((AW15/$H$18),0) -> 0 | AY15: =AO15+AQ15+AU15+AW15+AS15 -> 0 | AZ15: =IFERROR((AY15/$L$18),0) -> 0
C16: =IFERROR((B16/$B$18),0) -> 0 | E16: =IFERROR((D16/$D$18),0) -> 0 | G16: =IFERROR((F16/$H$18),0) -> 0 | I16: =IFERROR((H16/$H$18),0) -> 0 | K16: =IFERROR((J16/$H$18),0) -> 0 | L16: =B16+D16+H16+J16+F16 -> 0 | M16: =IFERROR((L16/$L$18),0) -> 0 | P16: =IFERROR((O16/$B$18),0) -> 0 | R16: =IFERROR((Q16/$D$18),0) -> 0 | T16: =IFERROR((S16/$H$18),0) -> 0 | V16: =IFERROR((U16/$H$18),0) -> 0 | X16: =IFERROR((W16/$H$18),0) -> 0 | Y16: =O16+Q16+U16+W16+S16 -> 0 | Z16: =IFERROR((Y16/$L$18),0) -> 0 | AC16: =IFERROR((AB16/$B$18),0) -> 0 | AE16: =IFERROR((AD16/$D$18),0) -> 0 | AG16: =IFERROR((AF16/$H$18),0) -> 0 | AI16: =IFERROR((AH16/$H$18),0) -> 0 | AK16: =IFERROR((AJ16/$H$18),0) -> 0 | AL16: =AB16+AD16+AH16+AJ16+AF16 -> 0 | AM16: =IFERROR((AL16/$L$18),0) -> 0 | AP16: =IFERROR((AO16/$B$18),0) -> 0 | AR16: =IFERROR((AQ16/$D$18),0) -> 0 | AT16: =IFERROR((AS16/$H$18),0) -> 0 | AV16: =IFERROR((AU16/$H$18),0) -> 0 | AX16: =IFERROR((AW16/$H$18),0) -> 0 | AY16: =AO16+AQ16+AU16+AW16+AS16 -> 0 | AZ16: =IFERROR((AY16/$L$18),0) -> 0
C17: =IFERROR((B17/$B$18),0) -> 0 | E17: =IFERROR((D17/$D$18),0) -> 0 | G17: =IFERROR((F17/$H$18),0) -> 0 | I17: =IFERROR((H17/$H$18),0) -> 0 | K17: =IFERROR((J17/$H$18),0) -> 0 | L17: =B17+D17+H17+J17+F17 -> 0 | M17: =IFERROR((L17/$L$18),0) -> 0 | P17: =IFERROR((O17/$B$18),0) -> 0 | R17: =IFERROR((Q17/$D$18),0) -> 0 | T17: =IFERROR((S17/$H$18),0) -> 0 | V17: =IFERROR((U17/$H$18),0) -> 0 | X17: =IFERROR((W17/$H$18),0) -> 0 | Y17: =O17+Q17+U17+W17+S17 -> 0 | Z17: =IFERROR((Y17/$L$18),0) -> 0 | AC17: =IFERROR((AB17/$B$18),0) -> 0 | AE17: =IFERROR((AD17/$D$18),0) -> 0 | AG17: =IFERROR((AF17/$H$18),0) -> 0 | AI17: =IFERROR((AH17/$H$18),0) -> 0 | AK17: =IFERROR((AJ17/$H$18),0) -> 0 | AL17: =AB17+AD17+AH17+AJ17+AF17 -> 0 | AM17: =IFERROR((AL17/$L$18),0) -> 0 | AP17: =IFERROR((AO17/$B$18),0) -> 0 | AR17: =IFERROR((AQ17/$D$18),0) -> 0 | AT17: =IFERROR((AS17/$H$18),0) -> 0 | AV17: =IFERROR((AU17/$H$18),0) -> 0 | AX17: =IFERROR((AW17/$H$18),0) -> 0 | AY17: =AO17+AQ17+AU17+AW17+AS17 -> 0 | AZ17: =IFERROR((AY17/$L$18),0) -> 0
A18: الإجمالي | B18: =SUM(B3:B17) -> 657117.64 | C18: =IFERROR((B18/$B$18),0) -> 1 | D18: =SUM(D3:D17) -> 174856.73 | E18: =IFERROR((D18/$D$18),0) -> 1 | F18: =SUM(F3:F17) -> 6744.0439 | G18: =IFERROR((F18/$H$18),0) -> 0 | H18: =SUM(H3:H17) -> 0 | I18: =IFERROR((H18/$H$18),0) -> 0 | J18: =SUM(J3:J17) -> 0 | K18: =IFERROR((J18/$H$18),0) -> 0 | L18: =B18+D18+H18+J18+F18 -> 838718.42 | M18: =IFERROR((L18/$L$18),0) -> 1 | O18: =SUM(O3:O17) -> 252401.39 | P18: =IFERROR((O18/$B$18),0) -> 0.38410381 | Q18: =SUM(Q3:Q17) -> 152521.69 | R18: =IFERROR((Q18/$D$18),0) -> 0.87226665 | S18: =SUM(S3:S17) -> 0 | T18: =IFERROR((S18/$H$18),0) -> 0 | U18: =SUM(U3:U17) -> 3000 | V18: =IFERROR((U18/$H$18),0) -> 0 | W18: =SUM(W3:W17) -> 0 | X18: =IFERROR((W18/$H$18),0) -> 0 | Y18: =O18+Q18+U18+W18+S18 -> 407923.08 | Z18: =IFERROR((Y18/$L$18),0) -> 0.48636476 | AB18: =SUM(AB3:AB17) -> 0 | AC18: =IFERROR((AB18/$B$18),0) -> 0 | AD18: =SUM(AD3:AD17) -> 0 | AE18: =IFERROR((AD18/$D$18),0) -> 0 | AF18: =SUM(AF3:AF17) -> 0 | AG18: =IFERROR((AF18/$H$18),0) -> 0 | AH18: =SUM(AH3:AH17) -> 0 | AI18: =IFERROR((AH18/$H$18),0) -> 0 | AJ18: =SUM(AJ3:AJ17) -> 0 | AK18: =IFERROR((AJ18/$H$18),0) -> 0 | AL18: =AB18+AD18+AH18+AJ18+AF18 -> 0 | AM18: =IFERROR((AL18/$L$18),0) -> 0 | AO18: =SUM(AO3:AO17) -> 0 | AP18: =IFERROR((AO18/$B$18),0) -> 0 | AQ18: =SUM(AQ3:AQ17) -> 0 | AR18: =IFERROR((AQ18/$D$18),0) -> 0 | AS18: =SUM(AS3:AS17) -> 0 | AT18: =IFERROR((AS18/$H$18),0) -> 0 | AU18: =SUM(AU3:AU17) -> 0 | AV18: =IFERROR((AU18/$H$18),0) -> 0 | AW18: =SUM(AW3:AW17) -> 0 | AX18: =IFERROR((AW18/$H$18),0) -> 0 | AY18: =AO18+AQ18+AU18+AW18+AS18 -> 0 | AZ18: =IFERROR((AY18/$L$18),0) -> 0
A20: نوع المصروف | B20: =B2 -> القاهرة | D20: =D2 -> المنصورة | F20: =F2 -> القانونيه | H20: =H2 -> الخدمات القانونية | J20: =J2 -> قيمه | L20: =L2 -> الإجمالي | O20: =O2 -> القاهرة | Q20: =Q2 -> المنصورة | S20: =S2 -> القانونيه | U20: =U2 -> الخدمات القانونية | W20: =W2 -> قيمه | Y20: =Y2 -> الإجمالي | AB20: =AB2 -> القاهرة | AD20: =AD2 -> المنصورة | AF20: =AF2 -> القانونيه | AH20: =AH2 -> الخدمات القانونية | AJ20: =AJ2 -> قيمه | AL20: =AL2 -> الإجمالي | AO20: =AO2 -> القاهرة | AQ20: =AQ2 -> المنصورة | AS20: =AS2 -> القانونيه | AU20: =AU2 -> الخدمات القانونية | AW20: =AW2 -> قيمه | AY20: =AY2 -> الإجمالي
A21: جاري شركاء | B21: =SUMIFS(Table1[[المنصرف ]],Table1[[نوع المصروف ]],$A:$A,Table1[[الشهر ]],$B$1,Table1[الفرع],'تحليلات 2024'!$B$20) -> 0 | C21: =IFERROR((B21/$B$18),0) -> 0 | D21: =SUMIFS(Table1[[المنصرف ]],Table1[[نوع المصروف ]],$A:$A,Table1[[الشهر ]],$B$1,Table1[الفرع],'تحليلات 2024'!$D$20) -> 0 | E21: =IFERROR((D21/$D$18),0) -> 0 | F21: =SUMIFS(Table1[[المنصرف ]],Table1[[نوع المصروف ]],$A:$A,Table1[[الشهر ]],$B$1,Table1[الفرع],'تحليلات 2024'!$F$20) -> 0 | G21: =IFERROR((F21/$F$18),0) -> 0 | H21: =SUMIFS(Table1[[المنصرف ]],Table1[[نوع المصروف ]],$A:$A,Table1[[الشهر ]],$B$1,Table1[الفرع],'تحليلات 2024'!$H$20) -> 0 | I21: =IFERROR((H21/$H$18),0) -> 0 | J21: =SUMIFS(Table1[[المنصرف ]],Table1[[نوع المصروف ]],$A:$A,Table1[[الشهر ]],$B$1,Table1[الفرع],'تحليلات 2024'!$J$20) -> 0 | K21: =IFERROR((J21/$L$18),0) -> 0 | L21: =B21+D21+H21+J21+F21 -> 0 | M21: =IFERROR((L21/$L$18),0) -> 0 | O21: =SUMIFS(Table1[[المنصرف ]],Table1[[نوع المصروف ]],$A:$A,Table1[[الشهر ]],$O$1,Table1[الفرع],'تحليلات 2024'!$B$20) -> 0 | P21: =IFERROR((O21/$B$18),0) -> 0 | Q21: =SUMIFS(Table1[[المنصرف ]],Table1[[نوع المصروف ]],$A:$A,Table1[[الشهر ]],$O$1,Table1[الفرع],'تحليلات 2024'!$D$20) -> 0 | R21: =IFERROR((Q21/$D$18),0) -> 0 | S21: =SUMIFS(Table1[[المنصرف ]],Table1[[نوع المصروف ]],$A:$A,Table1[[الشهر ]],$O$1,Table1[الفرع],'تحليلات 2024'!$F$20) -> 0 | T21: =IFERROR((S21/$F$18),0) -> 0 | U21: =SUMIFS(Table1[[المنصرف ]],Table1[[نوع المصروف ]],$A:$A,Table1[[الشهر ]],$O$1,Table1[الفرع],'تحليلات 2024'!$H$20) -> 0 | V21: =IFERROR((U21/$H$18),0) -> 0 | W21: =SUMIFS(Table1[[المنصرف ]],Table1[[نوع المصروف ]],$A:$A,Table1[[الشهر ]],$O$1,Table1[الفرع],'تحليلات 2024'!$J$20) -> 0 | X21: =IFERROR((W21/$L$18),0) -> 0 | Y21: =O21+Q21+U21+W21+S21 -> 0 | Z21: =IFERROR((Y21/$L$18),0) -> 0 | AB21: =SUMIFS(Table1[[المنصرف ]],Table1[[نوع المصروف ]],$A:$A,Table1[[الشهر ]],$AB$1,Table1[الفرع],'تحليلات 2024'!$B$20) -> 0 | AC21: =IFERROR((AB21/$B$18),0) -> 0 | AD21: =SUMIFS(Table1[[المنصرف ]],Table1[[نوع المصروف ]],$A:$A,Table1[[الشهر ]],$AB$1,Table1[الفرع],'تحليلات 2024'!$D$20) -> 0 | AE21: =IFERROR((AD21/$D$18),0) -> 0 | AF21: =SUMIFS(Table1[[المنصرف ]],Table1[[نوع المصروف ]],$A:$A,Table1[[الشهر ]],$AB$1,Table1[الفرع],'تحليلات 2024'!$F$20) -> 0 | AG21: =IFERROR((AF21/$F$18),0) -> 0 | AH21: =SUMIFS(Table1[[المنصرف ]],Table1[[نوع المصروف ]],$A:$A,Table1[[الشهر ]],$AB$1,Table1[الفرع],'تحليلات 2024'!$H$20) -> 0 | AI21: =IFERROR((AH21/$H$18),0) -> 0 | AJ21: =SUMIFS(Table1[[المنصرف ]],Table1[[نوع المصروف ]],$A:$A,Table1[[الشهر ]],$AB$1,Table1[الفرع],'تحليلات 2024'!$J$20) -> 0 | AK21: =IFERROR((AJ21/$L$18),0) -> 0 | AL21: =AB21+AD21+AH21+AJ21+AF21 -> 0 | AM21: =IFERROR((AL21/$L$18),0) -> 0 | AO21: =SUMIFS(Table1[[المنصرف ]],Table1[[نوع المصروف ]],$A:$A,Table1[[الشهر ]],$AO$1,Table1[الفرع],'تحليلات 2024'!$B$20) -> 0 | AP21: =IFERROR((AO21/$B$18),0) -> 0 | AQ21: =SUMIFS(Table1[[المنصرف ]],Table1[[نوع المصروف ]],$A:$A,Table1[[الشهر ]],$AO$1,Table1[الفرع],'تحليلات 2024'!$D$20) -> 0 | AR21: =IFERROR((AQ21/$D$18),0) -> 0 | AS21: =SUMIFS(Table1[[المنصرف ]],Table1[[نوع المصروف ]],$A:$A,Table1[[الشهر ]],$AO$1,Table1[الفرع],'تحليلات 2024'!$F$20) -> 0 | AT21: =IFERROR((AS21/$F$18),0) -> 0 | AU21: =SUMIFS(Table1[[المنصرف ]],Table1[[نوع المصروف ]],$A:$A,Table1[[الشهر ]],$AO$1,Table1[الفرع],'تحليلات 2024'!$H$20) -> 0 | AV21: =IFERROR((AU21/$H$18),0) -> 0 | AW21: =SUMIFS(Table1[[المنصرف ]],Table1[[نوع المصروف ]],$A:$A,Table1[[الشهر ]],$AO$1,Table1[الفرع],'تحليلات 2024'!$J$20) -> 0 | AX21: =IFERROR((AW21/$L$18),0) -> 0 | AY21: =AO21+AQ21+AU21+AW21+AS21 -> 0 | AZ21: =IFERROR((AY21/$L$18),0) -> 0
A22: مرتبات -الادارة العليا | B22: =SUMIFS(Table1[[المنصرف ]],Table1[[نوع المصروف ]],$A:$A,Table1[[الشهر ]],$B$1,Table1[الفرع],'تحليلات 2024'!$B$20) -> 0 | C22: =IFERROR((B22/$B$18),0) -> 0 | D22: =SUMIFS(Table1[[المنصرف ]],Table1[[نوع المصروف ]],$A:$A,Table1[[الشهر ]],$B$1,Table1[الفرع],'تحليلات 2024'!$D$20) -> 0 | E22: =IFERROR((D22/$D$18),0) -> 0 | F22: =SUMIFS(Table1[[المنصرف ]],Table1[[نوع المصروف ]],$A:$A,Table1[[الشهر ]],$B$1,Table1[الفرع],'تحليلات 2024'!$F$20) -> 0 | G22: =IFERROR((F22/$H$18),0) -> 0 | H22: =SUMIFS(Table1[[المنصرف ]],Table1[[نوع المصروف ]],$A:$A,Table1[[الشهر ]],$B$1,Table1[الفرع],'تحليلات 2024'!$H$20) -> 0 | I22: =IFERROR((H22/$H$18),0) -> 0 | J22: =SUMIFS(Table1[[المنصرف ]],Table1[[نوع المصروف ]],$A:$A,Table1[[الشهر ]],$B$1,Table1[الفرع],'تحليلات 2024'!$J$20) -> 0 | K22: =IFERROR((J22/$L$18),0) -> 0 | L22: =B22+D22+H22+J22+F22 -> 0 | M22: =IFERROR((L22/$L$18),0) -> 0 | O22: =SUMIFS(Table1[[المنصرف ]],Table1[[نوع المصروف ]],$A:$A,Table1[[الشهر ]],$O$1,Table1[الفرع],'تحليلات 2024'!$B$20) -> 0 | P22: =IFERROR((O22/$B$18),0) -> 0 | Q22: =SUMIFS(Table1[[المنصرف ]],Table1[[نوع المصروف ]],$A:$A,Table1[[الشهر ]],$O$1,Table1[الفرع],'تحليلات 2024'!$D$20) -> 0 | R22: =IFERROR((Q22/$D$18),0) -> 0 | S22: =SUMIFS(Table1[[المنصرف ]],Table1[[نوع المصروف ]],$A:$A,Table1[[الشهر ]],$O$1,Table1[الفرع],'تحليلات 2024'!$F$20) -> 0 | T22: =IFERROR((S22/$H$18),0) -> 0 | U22: =SUMIFS(Table1[[المنصرف ]],Table1[[نوع المصروف ]],$A:$A,Table1[[الشهر ]],$O$1,Table1[الفرع],'تحليلات 2024'!$H$20) -> 0 | V22: =IFERROR((U22/$H$18),0) -> 0 | W22: =SUMIFS(Table1[[المنصرف ]],Table1[[نوع المصروف ]],$A:$A,Table1[[الشهر ]],$O$1,Table1[الفرع],'تحليلات 2024'!$J$20) -> 0 | X22: =IFERROR((W22/$L$18),0) -> 0 | Y22: =O22+Q22+U22+W22+S22 -> 0 | Z22: =IFERROR((Y22/$L$18),0) -> 0 | AB22: =SUMIFS(Table1[[المنصرف ]],Table1[[نوع المصروف ]],$A:$A,Table1[[الشهر ]],$AB$1,Table1[الفرع],'تحليلات 2024'!$B$20) -> 0 | AC22: =IFERROR((AB22/$B$18),0) -> 0 | AD22: =SUMIFS(Table1[[المنصرف ]],Table1[[نوع المصروف ]],$A:$A,Table1[[الشهر ]],$AB$1,Table1[الفرع],'تحليلات 2024'!$D$20) -> 0 | AE22: =IFERROR((AD22/$D$18),0) -> 0 | AF22: =SUMIFS(Table1[[المنصرف ]],Table1[[نوع المصروف ]],$A:$A,Table1[[الشهر ]],$AB$1,Table1[الفرع],'تحليلات 2024'!$F$20) -> 0 | AG22: =IFERROR((AF22/$H$18),0) -> 0 | AH22: =SUMIFS(Table1[[المنصرف ]],Table1[[نوع المصروف ]],$A:$A,Table1[[الشهر ]],$AB$1,Table1[الفرع],'تحليلات 2024'!$H$20) -> 0 | AI22: =IFERROR((AH22/$H$18),0) -> 0 | AJ22: =SUMIFS(Table1[[المنصرف ]],Table1[[نوع المصروف ]],$A:$A,Table1[[الشهر ]],$AB$1,Table1[الفرع],'تحليلات 2024'!$J$20) -> 0 | AK22: =IFERROR((AJ22/$L$18),0) -> 0 | AL22: =AB22+AD22+AH22+AJ22+AF22 -> 0 | AM22: =IFERROR((AL22/$L$18),0) -> 0 | AO22: =SUMIFS(Table1[[المنصرف ]],Table1[[نوع المصروف ]],$A:$A,Table1[[الشهر ]],$AO$1,Table1[الفرع],'تحليلات 2024'!$B$20) -> 0 | AP22: =IFERROR((AO22/$B$18),0) -> 0 | AQ22: =SUMIFS(Table1[[المنصرف ]],Table1[[نوع المصروف ]],$A:$A,Table1[[الشهر ]],$AO$1,Table1[الفرع],'تحليلات 2024'!$D$20) -> 0 | AR22: =IFERROR((AQ22/$D$18),0) -> 0 | AS22: =SUMIFS(Table1[[المنصرف ]],Table1[[نوع المصروف ]],$A:$A,Table1[[الشهر ]],$AO$1,Table1[الفرع],'تحليلات 2024'!$F$20) -> 0 | AT22: =IFERROR((AS22/$H$18),0) -> 0 | AU22: =SUMIFS(Table1[[المنصرف ]],Table1[[نوع المصروف ]],$A:$A,Table1[[الشهر ]],$AO$1,Table1[الفرع],'تحليلات 2024'!$H$20) -> 0 | AV22: =IFERROR((AU22/$H$18),0) -> 0 | AW22: =SUMIFS(Table1[[المنصرف ]],Table1[[نوع المصروف ]],$A:$A,Table1[[الشهر ]],$AO$1,Table1[الفرع],'تحليلات 2024'!$J$20) -> 0 | AX22: =IFERROR((AW22/$L$18),0) -> 0 | AY22: =AO22+AQ22+AU22+AW22+AS22 -> 0 | AZ22: =IFERROR((AY22/$L$18),0) -> 0
A23: مرتبات -الادارة المالية | B23: =SUMIFS(Table1[[المنصرف ]],Table1[[نوع المصروف ]],$A:$A,Table1[[الشهر ]],$B$1,Table1[الفرع],'تحليلات 2024'!$B$20) -> 0 | C23: =IFERROR((B23/$B$18),0) -> 0 | D23: =SUMIFS(Table1[[المنصرف ]],Table1[[نوع المصروف ]],$A:$A,Table1[[الشهر ]],$B$1,Table1[الفرع],'تحليلات 2024'!$D$20) -> 4269.21 | E23: =IFERROR((D23/$D$18),0) -> 0.024415474 | F23: =SUMIFS(Table1[[المنصرف ]],Table1[[نوع المصروف ]],$A:$A,Table1[[الشهر ]],$B$1,Table1[الفرع],'تحليلات 2024'!$F$20) -> 0 | G23: =IFERROR((F23/$H$18),0) -> 0 | H23: =SUMIFS(Table1[[المنصرف ]],Table1[[نوع المصروف ]],$A:$A,Table1[[الشهر ]],$B$1,Table1[الفرع],'تحليلات 2024'!$H$20) -> 0 | I23: =IFERROR((H23/$H$18),0) -> 0 | J23: =SUMIFS(Table1[[المنصرف ]],Table1[[نوع المصروف ]],$A:$A,Table1[[الشهر ]],$B$1,Table1[الفرع],'تحليلات 2024'!$J$20) -> 0 | K23: =IFERROR((J23/$L$18),0) -> 0 | L23: =B23+D23+H23+J23+F23 -> 4269.21 | M23: =IFERROR((L23/$L$18),0) -> 0.0050901589 | O23: =SUMIFS(Table1[[المنصرف ]],Table1[[نوع المصروف ]],$A:$A,Table1[[الشهر ]],$O$1,Table1[الفرع],'تحليلات 2024'!$B$20) -> 0 | P23: =IFERROR((O23/$B$18),0) -> 0 | Q23: =SUMIFS(Table1[[المنصرف ]],Table1[[نوع المصروف ]],$A:$A,Table1[[الشهر ]],$O$1,Table1[الفرع],'تحليلات 2024'!$D$20) -> 0 | R23: =IFERROR((Q23/$D$18),0) -> 0 | S23: =SUMIFS(Table1[[المنصرف ]],Table1[[نوع المصروف ]],$A:$A,Table1[[الشهر ]],$O$1,Table1[الفرع],'تحليلات 2024'!$F$20) -> 0 | T23: =IFERROR((S23/$H$18),0) -> 0 | U23: =SUMIFS(Table1[[المنصرف ]],Table1[[نوع المصروف ]],$A:$A,Table1[[الشهر ]],$O$1,Table1[الفرع],'تحليلات 2024'!$H$20) -> 0 | V23: =IFERROR((U23/$H$18),0) -> 0 | W23: =SUMIFS(Table1[[المنصرف ]],Table1[[نوع المصروف ]],$A:$A,Table1[[الشهر ]],$O$1,Table1[الفرع],'تحليلات 2024'!$J$20) -> 0 | X23: =IFERROR((W23/$L$18),0) -> 0 | Y23: =O23+Q23+U23+W23+S23 -> 0 | Z23: =IFERROR((Y23/$L$18),0) -> 0 | AB23: =SUMIFS(Table1[[المنصرف ]],Table1[[نوع المصروف ]],$A:$A,Table1[[الشهر ]],$AB$1,Table1[الفرع],'تحليلات 2024'!$B$20) -> 0 | AC23: =IFERROR((AB23/$B$18),0) -> 0 | AD23: =SUMIFS(Table1[[المنصرف ]],Table1[[نوع المصروف ]],$A:$A,Table1[[الشهر ]],$AB$1,Table1[الفرع],'تحليلات 2024'!$D$20) -> 0 | AE23: =IFERROR((AD23/$D$18),0) -> 0 | AF23: =SUMIFS(Table1[[المنصرف ]],Table1[[نوع المصروف ]],$A:$A,Table1[[الشهر ]],$AB$1,Table1[الفرع],'تحليلات 2024'!$F$20) -> 0 | AG23: =IFERROR((AF23/$H$18),0) -> 0 | AH23: =SUMIFS(Table1[[المنصرف ]],Table1[[نوع المصروف ]],$A:$A,Table1[[الشهر ]],$AB$1,Table1[الفرع],'تحليلات 2024'!$H$20) -> 0 | AI23: =IFERROR((AH23/$H$18),0) -> 0 | AJ23: =SUMIFS(Table1[[المنصرف ]],Table1[[نوع المصروف ]],$A:$A,Table1[[الشهر ]],$AB$1,Table1[الفرع],'تحليلات 2024'!$J$20) -> 0 | AK23: =IFERROR((AJ23/$L$18),0) -> 0 | AL23: =AB23+AD23+AH23+AJ23+AF23 -> 0 | AM23: =IFERROR((AL23/$L$18),0) -> 0 | AO23: =SUMIFS(Table1[[المنصرف ]],Table1[[نوع المصروف ]],$A:$A,Table1[[الشهر ]],$AO$1,Table1[الفرع],'تحليلات 2024'!$B$20) -> 0 | AP23: =IFERROR((AO23/$B$18),0) -> 0 | AQ23: =SUMIFS(Table1[[المنصرف ]],Table1[[نوع المصروف ]],$A:$A,Table1[[الشهر ]],$AO$1,Table1[الفرع],'تحليلات 2024'!$D$20) -> 0 | AR23: =IFERROR((AQ23/$D$18),0) -> 0 | AS23: =SUMIFS(Table1[[المنصرف ]],Table1[[نوع المصروف ]],$A:$A,Table1[[الشهر ]],$AO$1,Table1[الفرع],'تحليلات 2024'!$F$20) -> 0 | AT23: =IFERROR((AS23/$H$18),0) -> 0 | AU23: =SUMIFS(Table1[[المنصرف ]],Table1[[نوع المصروف ]],$A:$A,Table1[[الشهر ]],$AO$1,Table1[الفرع],'تحليلات 2024'!$H$20) -> 0 | AV23: =IFERROR((AU23/$H$18),0) -> 0 | AW23: =SUMIFS(Table1[[المنصرف ]],Table1[[نوع المصروف ]],$A:$A,Table1[[الشهر ]],$AO$1,Table1[الفرع],'تحليلات 2024'!$J$20) -> 0 | AX23: =IFERROR((AW23/$L$18),0) -> 0 | AY23: =AO23+AQ23+AU23+AW23+AS23 -> 0 | AZ23: =IFERROR((AY23/$L$18),0) -> 0
A24: مرتبات -اداره الموارد البشرية | B24: =SUMIFS(Table1[[المنصرف ]],Table1[[نوع المصروف ]],$A:$A,Table1[[الشهر ]],$B$1,Table1[الفرع],'تحليلات 2024'!$B$20) -> 0 | C24: =IFERROR((B24/$B$18),0) -> 0 | D24: =SUMIFS(Table1[[المنصرف ]],Table1[[نوع المصروف ]],$A:$A,Table1[[الشهر ]],$B$1,Table1[الفرع],'تحليلات 2024'!$D$20) -> 0 | E24: =IFERROR((D24/$D$18),0) -> 0 | F24: =SUMIFS(Table1[[المنصرف ]],Table1[[نوع المصروف ]],$A:$A,Table1[[الشهر ]],$B$1,Table1[الفرع],'تحليلات 2024'!$F$20) -> 0 | G24: =IFERROR((F24/$H$18),0) -> 0 | H24: =SUMIFS(Table1[[المنصرف ]],Table1[[نوع المصروف ]],$A:$A,Table1[[الشهر ]],$B$1,Table1[الفرع],'تحليلات 2024'!$H$20) -> 0 | I24: =IFERROR((H24/$H$18),0) -> 0 | J24: =SUMIFS(Table1[[المنصرف ]],Table1[[نوع المصروف ]],$A:$A,Table1[[الشهر ]],$B$1,Table1[الفرع],'تحليلات 2024'!$J$20) -> 0 | K24: =IFERROR((J24/$L$18),0) -> 0 | L24: =B24+D24+H24+J24+F24 -> 0 | M24: =IFERROR((L24/$L$18),0) -> 0 | O24: =SUMIFS(Table1[[المنصرف ]],Table1[[نوع المصروف ]],$A:$A,Table1[[الشهر ]],$O$1,Table1[الفرع],'تحليلات 2024'!$B$20) -> 0 | P24: =IFERROR((O24/$B$18),0) -> 0 | Q24: =SUMIFS(Table1[[المنصرف ]],Table1[[نوع المصروف ]],$A:$A,Table1[[الشهر ]],$O$1,Table1[الفرع],'تحليلات 2024'!$D$20) -> 0 | R24: =IFERROR((Q24/$D$18),0) -> 0 | S24: =SUMIFS(Table1[[المنصرف ]],Table1[[نوع المصروف ]],$A:$A,Table1[[الشهر ]],$O$1,Table1[الفرع],'تحليلات 2024'!$F$20) -> 0 | T24: =IFERROR((S24/$H$18),0) -> 0 | U24: =SUMIFS(Table1[[المنصرف ]],Table1[[نوع المصروف ]],$A:$A,Table1[[الشهر ]],$O$1,Table1[الفرع],'تحليلات 2024'!$H$20) -> 0 | V24: =IFERROR((U24/$H$18),0) -> 0 | W24: =SUMIFS(Table1[[المنصرف ]],Table1[[نوع المصروف ]],$A:$A,Table1[[الشهر ]],$O$1,Table1[الفرع],'تحليلات 2024'!$J$20) -> 0 | X24: =IFERROR((W24/$L$18),0) -> 0 | Y24: =O24+Q24+U24+W24+S24 -> 0 | Z24: =IFERROR((Y24/$L$18),0) -> 0 | AB24: =SUMIFS(Table1[[المنصرف ]],Table1[[نوع المصروف ]],$A:$A,Table1[[الشهر ]],$AB$1,Table1[الفرع],'تحليلات 2024'!$B$20) -> 0 | AC24: =IFERROR((AB24/$B$18),0) -> 0 | AD24: =SUMIFS(Table1[[المنصرف ]],Table1[[نوع المصروف ]],$A:$A,Table1[[الشهر ]],$AB$1,Table1[الفرع],'تحليلات 2024'!$D$20) -> 0 | AE24: =IFERROR((AD24/$D$18),0) -> 0 | AF24: =SUMIFS(Table1[[المنصرف ]],Table1[[نوع المصروف ]],$A:$A,Table1[[الشهر ]],$AB$1,Table1[الفرع],'تحليلات 2024'!$F$20) -> 0 | AG24: =IFERROR((AF24/$H$18),0) -> 0 | AH24: =SUMIFS(Table1[[المنصرف ]],Table1[[نوع المصروف ]],$A:$A,Table1[[الشهر ]],$AB$1,Table1[الفرع],'تحليلات 2024'!$H$20) -> 0 | AI24: =IFERROR((AH24/$H$18),0) -> 0 | AJ24: =SUMIFS(Table1[[المنصرف ]],Table1[[نوع المصروف ]],$A:$A,Table1[[الشهر ]],$AB$1,Table1[الفرع],'تحليلات 2024'!$J$20) -> 0 | AK24: =IFERROR((AJ24/$L$18),0) -> 0 | AL24: =AB24+AD24+AH24+AJ24+AF24 -> 0 | AM24: =IFERROR((AL24/$L$18),0) -> 0 | AO24: =SUMIFS(Table1[[المنصرف ]],Table1[[نوع المصروف ]],$A:$A,Table1[[الشهر ]],$AO$1,Table1[الفرع],'تحليلات 2024'!$B$20) -> 0 | AP24: =IFERROR((AO24/$B$18),0) -> 0 | AQ24: =SUMIFS(Table1[[المنصرف ]],Table1[[نوع المصروف ]],$A:$A,Table1[[الشهر ]],$AO$1,Table1[الفرع],'تحليلات 2024'!$D$20) -> 0 | AR24: =IFERROR((AQ24/$D$18),0) -> 0 | AS24: =SUMIFS(Table1[[المنصرف ]],Table1[[نوع المصروف ]],$A:$A,Table1[[الشهر ]],$AO$1,Table1[الفرع],'تحليلات 2024'!$F$20) -> 0 | AT24: =IFERROR((AS24/$H$18),0) -> 0 | AU24: =SUMIFS(Table1[[المنصرف ]],Table1[[نوع المصروف ]],$A:$A,Table1[[الشهر ]],$AO$1,Table1[الفرع],'تحليلات 2024'!$H$20) -> 0 | AV24: =IFERROR((AU24/$H$18),0) -> 0 | AW24: =SUMIFS(Table1[[المنصرف ]],Table1[[نوع المصروف ]],$A:$A,Table1[[الشهر ]],$AO$1,Table1[الفرع],'تحليلات 2024'!$J$20) -> 0 | AX24: =IFERROR((AW24/$L$18),0) -> 0 | AY24: =AO24+AQ24+AU24+AW24+AS24 -> 0 | AZ24: =IFERROR((AY24/$L$18),0) -> 0
A25: مرتبات -الشئون الإدارية | B25: =SUMIFS(Table1[[المنصرف ]],Table1[[نوع المصروف ]],$A:$A,Table1[[الشهر ]],$B$1,Table1[الفرع],'تحليلات 2024'!$B$20) -> 0 | C25: =IFERROR((B25/$B$18),0) -> 0 | D25: =SUMIFS(Table1[[المنصرف ]],Table1[[نوع المصروف ]],$A:$A,Table1[[الشهر ]],$B$1,Table1[الفرع],'تحليلات 2024'!$D$20) -> 0 | E25: =IFERROR((D25/$D$18),0) -> 0 | F25: =SUMIFS(Table1[[المنصرف ]],Table1[[نوع المصروف ]],$A:$A,Table1[[الشهر ]],$B$1,Table1[الفرع],'تحليلات 2024'!$F$20) -> 0 | G25: =IFERROR((F25/$H$18),0) -> 0 | H25: =SUMIFS(Table1[[المنصرف ]],Table1[[نوع المصروف ]],$A:$A,Table1[[الشهر ]],$B$1,Table1[الفرع],'تحليلات 2024'!$H$20) -> 0 | I25: =IFERROR((H25/$H$18),0) -> 0 | J25: =SUMIFS(Table1[[المنصرف ]],Table1[[نوع المصروف ]],$A:$A,Table1[[الشهر ]],$B$1,Table1[الفرع],'تحليلات 2024'!$J$20) -> 0 | K25: =IFERROR((J25/$L$18),0) -> 0 | L25: =B25+D25+H25+J25+F25 -> 0 | M25: =IFERROR((L25/$L$18),0) -> 0 | O25: =SUMIFS(Table1[[المنصرف ]],Table1[[نوع المصروف ]],$A:$A,Table1[[الشهر ]],$O$1,Table1[الفرع],'تحليلات 2024'!$B$20) -> 0 | P25: =IFERROR((O25/$B$18),0) -> 0 | Q25: =SUMIFS(Table1[[المنصرف ]],Table1[[نوع المصروف ]],$A:$A,Table1[[الشهر ]],$O$1,Table1[الفرع],'تحليلات 2024'!$D$20) -> 0 | R25: =IFERROR((Q25/$D$18),0) -> 0 | S25: =SUMIFS(Table1[[المنصرف ]],Table1[[نوع المصروف ]],$A:$A,Table1[[الشهر ]],$O$1,Table1[الفرع],'تحليلات 2024'!$F$20) -> 0 | T25: =IFERROR((S25/$H$18),0) -> 0 | U25: =SUMIFS(Table1[[المنصرف ]],Table1[[نوع المصروف ]],$A:$A,Table1[[الشهر ]],$O$1,Table1[الفرع],'تحليلات 2024'!$H$20) -> 0 | V25: =IFERROR((U25/$H$18),0) -> 0 | W25: =SUMIFS(Table1[[المنصرف ]],Table1[[نوع المصروف ]],$A:$A,Table1[[الشهر ]],$O$1,Table1[الفرع],'تحليلات 2024'!$J$20) -> 0 | X25: =IFERROR((W25/$L$18),0) -> 0 | Y25: =O25+Q25+U25+W25+S25 -> 0 | Z25: =IFERROR((Y25/$L$18),0) -> 0 | AB25: =SUMIFS(Table1[[المنصرف ]],Table1[[نوع المصروف ]],$A:$A,Table1[[الشهر ]],$AB$1,Table1[الفرع],'تحليلات 2024'!$B$20) -> 0 | AC25: =IFERROR((AB25/$B$18),0) -> 0 | AD25: =SUMIFS(Table1[[المنصرف ]],Table1[[نوع المصروف ]],$A:$A,Table1[[الشهر ]],$AB$1,Table1[الفرع],'تحليلات 2024'!$D$20) -> 0 | AE25: =IFERROR((AD25/$D$18),0) -> 0 | AF25: =SUMIFS(Table1[[المنصرف ]],Table1[[نوع المصروف ]],$A:$A,Table1[[الشهر ]],$AB$1,Table1[الفرع],'تحليلات 2024'!$F$20) -> 0 | AG25: =IFERROR((AF25/$H$18),0) -> 0 | AH25: =SUMIFS(Table1[[المنصرف ]],Table1[[نوع المصروف ]],$A:$A,Table1[[الشهر ]],$AB$1,Table1[الفرع],'تحليلات 2024'!$H$20) -> 0 | AI25: =IFERROR((AH25/$H$18),0) -> 0 | AJ25: =SUMIFS(Table1[[المنصرف ]],Table1[[نوع المصروف ]],$A:$A,Table1[[الشهر ]],$AB$1,Table1[الفرع],'تحليلات 2024'!$J$20) -> 0 | AK25: =IFERROR((AJ25/$L$18),0) -> 0 | AL25: =AB25+AD25+AH25+AJ25+AF25 -> 0 | AM25: =IFERROR((AL25/$L$18),0) -> 0 | AO25: =SUMIFS(Table1[[المنصرف ]],Table1[[نوع المصروف ]],$A:$A,Table1[[الشهر ]],$AO$1,Table1[الفرع],'تحليلات 2024'!$B$20) -> 0 | AP25: =IFERROR((AO25/$B$18),0) -> 0 | AQ25: =SUMIFS(Table1[[المنصرف ]],Table1[[نوع المصروف ]],$A:$A,Table1[[الشهر ]],$AO$1,Table1[الفرع],'تحليلات 2024'!$D$20) -> 0 | AR25: =IFERROR((AQ25/$D$18),0) -> 0 | AS25: =SUMIFS(Table1[[المنصرف ]],Table1[[نوع المصروف ]],$A:$A,Table1[[الشهر ]],$AO$1,Table1[الفرع],'تحليلات 2024'!$F$20) -> 0 | AT25: =IFERROR((AS25/$H$18),0) -> 0 | AU25: =SUMIFS(Table1[[المنصرف ]],Table1[[نوع المصروف ]],$A:$A,Table1[[الشهر ]],$AO$1,Table1[الفرع],'تحليلات 2024'!$H$20) -> 0 | AV25: =IFERROR((AU25/$H$18),0) -> 0 | AW25: =SUMIFS(Table1[[المنصرف ]],Table1[[نوع المصروف ]],$A:$A,Table1[[الشهر ]],$AO$1,Table1[الفرع],'تحليلات 2024'!$J$20) -> 0 | AX25: =IFERROR((AW25/$L$18),0) -> 0 | AY25: =AO25+AQ25+AU25+AW25+AS25 -> 0 | AZ25: =IFERROR((AY25/$L$18),0) -> 0
A26: مرتبات -الخدمات المعاونة | B26: =SUMIFS(Table1[[المنصرف ]],Table1[[نوع المصروف ]],$A:$A,Table1[[الشهر ]],$B$1,Table1[الفرع],'تحليلات 2024'!$B$20) -> 0 | C26: =IFERROR((B26/$B$18),0) -> 0 | D26: =SUMIFS(Table1[[المنصرف ]],Table1[[نوع المصروف ]],$A:$A,Table1[[الشهر ]],$B$1,Table1[الفرع],'تحليلات 2024'!$D$20) -> 0 | E26: =IFERROR((D26/$D$18),0) -> 0 | F26: =SUMIFS(Table1[[المنصرف ]],Table1[[نوع المصروف ]],$A:$A,Table1[[الشهر ]],$B$1,Table1[الفرع],'تحليلات 2024'!$F$20) -> 0 | G26: =IFERROR((F26/$H$18),0) -> 0 | H26: =SUMIFS(Table1[[المنصرف ]],Table1[[نوع المصروف ]],$A:$A,Table1[[الشهر ]],$B$1,Table1[الفرع],'تحليلات 2024'!$H$20) -> 0 | I26: =IFERROR((H26/$H$18),0) -> 0 | J26: =SUMIFS(Table1[[المنصرف ]],Table1[[نوع المصروف ]],$A:$A,Table1[[الشهر ]],$B$1,Table1[الفرع],'تحليلات 2024'!$J$20) -> 0 | K26: =IFERROR((J26/$L$18),0) -> 0 | L26: =B26+D26+H26+J26+F26 -> 0 | M26: =IFERROR((L26/$L$18),0) -> 0 | O26: =SUMIFS(Table1[[المنصرف ]],Table1[[نوع المصروف ]],$A:$A,Table1[[الشهر ]],$O$1,Table1[الفرع],'تحليلات 2024'!$B$20) -> 0 | P26: =IFERROR((O26/$B$18),0) -> 0 | Q26: =SUMIFS(Table1[[المنصرف ]],Table1[[نوع المصروف ]],$A:$A,Table1[[الشهر ]],$O$1,Table1[الفرع],'تحليلات 2024'!$D$20) -> 0 | R26: =IFERROR((Q26/$D$18),0) -> 0 | S26: =SUMIFS(Table1[[المنصرف ]],Table1[[نوع المصروف ]],$A:$A,Table1[[الشهر ]],$O$1,Table1[الفرع],'تحليلات 2024'!$F$20) -> 0 | T26: =IFERROR((S26/$H$18),0) -> 0 | U26: =SUMIFS(Table1[[المنصرف ]],Table1[[نوع المصروف ]],$A:$A,Table1[[الشهر ]],$O$1,Table1[الفرع],'تحليلات 2024'!$H$20) -> 0 | V26: =IFERROR((U26/$H$18),0) -> 0 | W26: =SUMIFS(Table1[[المنصرف ]],Table1[[نوع المصروف ]],$A:$A,Table1[[الشهر ]],$O$1,Table1[الفرع],'تحليلات 2024'!$J$20) -> 0 | X26: =IFERROR((W26/$L$18),0) -> 0 | Y26: =O26+Q26+U26+W26+S26 -> 0 | Z26: =IFERROR((Y26/$L$18),0) -> 0 | AB26: =SUMIFS(Table1[[المنصرف ]],Table1[[نوع المصروف ]],$A:$A,Table1[[الشهر ]],$AB$1,Table1[الفرع],'تحليلات 2024'!$B$20) -> 0 | AC26: =IFERROR((AB26/$B$18),0) -> 0 | AD26: =SUMIFS(Table1[[المنصرف ]],Table1[[نوع المصروف ]],$A:$A,Table1[[الشهر ]],$AB$1,Table1[الفرع],'تحليلات 2024'!$D$20) -> 0 | AE26: =IFERROR((AD26/$D$18),0) -> 0 | AF26: =SUMIFS(Table1[[المنصرف ]],Table1[[نوع المصروف ]],$A:$A,Table1[[الشهر ]],$AB$1,Table1[الفرع],'تحليلات 2024'!$F$20) -> 0 | AG26: =IFERROR((AF26/$H$18),0) -> 0 | AH26: =SUMIFS(Table1[[المنصرف ]],Table1[[نوع المصروف ]],$A:$A,Table1[[الشهر ]],$AB$1,Table1[الفرع],'تحليلات 2024'!$H$20) -> 0 | AI26: =IFERROR((AH26/$H$18),0) -> 0 | AJ26: =SUMIFS(Table1[[المنصرف ]],Table1[[نوع المصروف ]],$A:$A,Table1[[الشهر ]],$AB$1,Table1[الفرع],'تحليلات 2024'!$J$20) -> 0 | AK26: =IFERROR((AJ26/$L$18),0) -> 0 | AL26: =AB26+AD26+AH26+AJ26+AF26 -> 0 | AM26: =IFERROR((AL26/$L$18),0) -> 0 | AO26: =SUMIFS(Table1[[المنصرف ]],Table1[[نوع المصروف ]],$A:$A,Table1[[الشهر ]],$AO$1,Table1[الفرع],'تحليلات 2024'!$B$20) -> 0 | AP26: =IFERROR((AO26/$B$18),0) -> 0 | AQ26: =SUMIFS(Table1[[المنصرف ]],Table1[[نوع المصروف ]],$A:$A,Table1[[الشهر ]],$AO$1,Table1[الفرع],'تحليلات 2024'!$D$20) -> 0 | AR26: =IFERROR((AQ26/$D$18),0) -> 0 | AS26: =SUMIFS(Table1[[المنصرف ]],Table1[[نوع المصروف ]],$A:$A,Table1[[الشهر ]],$AO$1,Table1[الفرع],'تحليلات 2024'!$F$20) -> 0 | AT26: =IFERROR((AS26/$H$18),0) -> 0 | AU26: =SUMIFS(Table1[[المنصرف ]],Table1[[نوع المصروف ]],$A:$A,Table1[[الشهر ]],$AO$1,Table1[الفرع],'تحليلات 2024'!$H$20) -> 0 | AV26: =IFERROR((AU26/$H$18),0) -> 0 | AW26: =SUMIFS(Table1[[المنصرف ]],Table1[[نوع المصروف ]],$A:$A,Table1[[الشهر ]],$AO$1,Table1[الفرع],'تحليلات 2024'!$J$20) -> 0 | AX26: =IFERROR((AW26/$L$18),0) -> 0 | AY26: =AO26+AQ26+AU26+AW26+AS26 -> 0 | AZ26: =IFERROR((AY26/$L$18),0) -> 0
A27: مرتبات -الشئون القانونية | B27: =SUMIFS(Table1[[المنصرف ]],Table1[[نوع المصروف ]],$A:$A,Table1[[الشهر ]],$B$1,Table1[الفرع],'تحليلات 2024'!$B$20) -> 0 | C27: =IFERROR((B27/$B$18),0) -> 0 | D27: =SUMIFS(Table1[[المنصرف ]],Table1[[نوع المصروف ]],$A:$A,Table1[[الشهر ]],$B$1,Table1[الفرع],'تحليلات 2024'!$D$20) -> 0 | E27: =IFERROR((D27/$D$18),0) -> 0 | F27: =SUMIFS(Table1[[المنصرف ]],Table1[[نوع المصروف ]],$A:$A,Table1[[الشهر ]],$B$1,Table1[الفرع],'تحليلات 2024'!$F$20) -> 0 | G27: =IFERROR((F27/$H$18),0) -> 0 | H27: =SUMIFS(Table1[[المنصرف ]],Table1[[نوع المصروف ]],$A:$A,Table1[[الشهر ]],$B$1,Table1[الفرع],'تحليلات 2024'!$H$20) -> 0 | I27: =IFERROR((H27/$H$18),0) -> 0 | J27: =SUMIFS(Table1[[المنصرف ]],Table1[[نوع المصروف ]],$A:$A,Table1[[الشهر ]],$B$1,Table1[الفرع],'تحليلات 2024'!$J$20) -> 0 | K27: =IFERROR((J27/$L$18),0) -> 0 | L27: =B27+D27+H27+J27+F27 -> 0 | M27: =IFERROR((L27/$L$18),0) -> 0 | O27: =SUMIFS(Table1[[المنصرف ]],Table1[[نوع المصروف ]],$A:$A,Table1[[الشهر ]],$O$1,Table1[الفرع],'تحليلات 2024'!$B$20) -> 0 | P27: =IFERROR((O27/$B$18),0) -> 0 | Q27: =SUMIFS(Table1[[المنصرف ]],Table1[[نوع المصروف ]],$A:$A,Table1[[الشهر ]],$O$1,Table1[الفرع],'تحليلات 2024'!$D$20) -> 0 | R27: =IFERROR((Q27/$D$18),0) -> 0 | S27: =SUMIFS(Table1[[المنصرف ]],Table1[[نوع المصروف ]],$A:$A,Table1[[الشهر ]],$O$1,Table1[الفرع],'تحليلات 2024'!$F$20) -> 0 | T27: =IFERROR((S27/$H$18),0) -> 0 | U27: =SUMIFS(Table1[[المنصرف ]],Table1[[نوع المصروف ]],$A:$A,Table1[[الشهر ]],$O$1,Table1[الفرع],'تحليلات 2024'!$H$20) -> 0 | V27: =IFERROR((U27/$H$18),0) -> 0 | W27: =SUMIFS(Table1[[المنصرف ]],Table1[[نوع المصروف ]],$A:$A,Table1[[الشهر ]],$O$1,Table1[الفرع],'تحليلات 2024'!$J$20) -> 0 | X27: =IFERROR((W27/$L$18),0) -> 0 | Y27: =O27+Q27+U27+W27+S27 -> 0 | Z27: =IFERROR((Y27/$L$18),0) -> 0 | AB27: =SUMIFS(Table1[[المنصرف ]],Table1[[نوع المصروف ]],$A:$A,Table1[[الشهر ]],$AB$1,Table1[الفرع],'تحليلات 2024'!$B$20) -> 0 | AC27: =IFERROR((AB27/$B$18),0) -> 0 | AD27: =SUMIFS(Table1[[المنصرف ]],Table1[[نوع المصروف ]],$A:$A,Table1[[الشهر ]],$AB$1,Table1[الفرع],'تحليلات 2024'!$D$20) -> 0 | AE27: =IFERROR((AD27/$D$18),0) -> 0 | AF27: =SUMIFS(Table1[[المنصرف ]],Table1[[نوع المصروف ]],$A:$A,Table1[[الشهر ]],$AB$1,Table1[الفرع],'تحليلات 2024'!$F$20) -> 0 | AG27: =IFERROR((AF27/$H$18),0) -> 0 | AH27: =SUMIFS(Table1[[المنصرف ]],Table1[[نوع المصروف ]],$A:$A,Table1[[الشهر ]],$AB$1,Table1[الفرع],'تحليلات 2024'!$H$20) -> 0 | AI27: =IFERROR((AH27/$H$18),0) -> 0 | AJ27: =SUMIFS(Table1[[المنصرف ]],Table1[[نوع المصروف ]],$A:$A,Table1[[الشهر ]],$AB$1,Table1[الفرع],'تحليلات 2024'!$J$20) -> 0 | AK27: =IFERROR((AJ27/$L$18),0) -> 0 | AL27: =AB27+AD27+AH27+AJ27+AF27 -> 0 | AM27: =IFERROR((AL27/$L$18),0) -> 0 | AO27: =SUMIFS(Table1[[المنصرف ]],Table1[[نوع المصروف ]],$A:$A,Table1[[الشهر ]],$AO$1,Table1[الفرع],'تحليلات 2024'!$B$20) -> 0 | AP27: =IFERROR((AO27/$B$18),0) -> 0 | AQ27: =SUMIFS(Table1[[المنصرف ]],Table1[[نوع المصروف ]],$A:$A,Table1[[الشهر ]],$AO$1,Table1[الفرع],'تحليلات 2024'!$D$20) -> 0 | AR27: =IFERROR((AQ27/$D$18),0) -> 0 | AS27: =SUMIFS(Table1[[المنصرف ]],Table1[[نوع المصروف ]],$A:$A,Table1[[الشهر ]],$AO$1,Table1[الفرع],'تحليلات 2024'!$F$20) -> 0 | AT27: =IFERROR((AS27/$H$18),0) -> 0 | AU27: =SUMIFS(Table1[[المنصرف ]],Table1[[نوع المصروف ]],$A:$A,Table1[[الشهر ]],$AO$1,Table1[الفرع],'تحليلات 2024'!$H$20) -> 0 | AV27: =IFERROR((AU27/$H$18),0) -> 0 | AW27: =SUMIFS(Table1[[المنصرف ]],Table1[[نوع المصروف ]],$A:$A,Table1[[الشهر ]],$AO$1,Table1[الفرع],'تحليلات 2024'!$J$20) -> 0 | AX27: =IFERROR((AW27/$L$18),0) -> 0 | AY27: =AO27+AQ27+AU27+AW27+AS27 -> 0 | AZ27: =IFERROR((AY27/$L$18),0) -> 0
A28: مرتبات -اداره التحصيل | B28: =SUMIFS(Table1[[المنصرف ]],Table1[[نوع المصروف ]],$A:$A,Table1[[الشهر ]],$B$1,Table1[الفرع],'تحليلات 2024'!$B$20) -> 0 | C28: =IFERROR((B28/$B$18),0) -> 0 | D28: =SUMIFS(Table1[[المنصرف ]],Table1[[نوع المصروف ]],$A:$A,Table1[[الشهر ]],$B$1,Table1[الفرع],'تحليلات 2024'!$D$20) -> 105273.5 | E28: =IFERROR((D28/$D$18),0) -> 0.60205575 | F28: =SUMIFS(Table1[[المنصرف ]],Table1[[نوع المصروف ]],$A:$A,Table1[[الشهر ]],$B$1,Table1[الفرع],'تحليلات 2024'!$F$20) -> 0 | G28: =IFERROR((F28/$H$18),0) -> 0 | H28: =SUMIFS(Table1[[المنصرف ]],Table1[[نوع المصروف ]],$A:$A,Table1[[الشهر ]],$B$1,Table1[الفرع],'تحليلات 2024'!$H$20) -> 0 | I28: =IFERROR((H28/$H$18),0) -> 0 | J28: =SUMIFS(Table1[[المنصرف ]],Table1[[نوع المصروف ]],$A:$A,Table1[[الشهر ]],$B$1,Table1[الفرع],'تحليلات 2024'!$J$20) -> 0 | K28: =IFERROR((J28/$L$18),0) -> 0 | L28: =B28+D28+H28+J28+F28 -> 105273.5 | M28: =IFERROR((L28/$L$18),0) -> 0.1255171 | O28: =SUMIFS(Table1[[المنصرف ]],Table1[[نوع المصروف ]],$A:$A,Table1[[الشهر ]],$O$1,Table1[الفرع],'تحليلات 2024'!$B$20) -> 0 | P28: =IFERROR((O28/$B$18),0) -> 0 | Q28: =SUMIFS(Table1[[المنصرف ]],Table1[[نوع المصروف ]],$A:$A,Table1[[الشهر ]],$O$1,Table1[الفرع],'تحليلات 2024'!$D$20) -> 0 | R28: =IFERROR((Q28/$D$18),0) -> 0 | S28: =SUMIFS(Table1[[المنصرف ]],Table1[[نوع المصروف ]],$A:$A,Table1[[الشهر ]],$O$1,Table1[الفرع],'تحليلات 2024'!$F$20) -> 0 | T28: =IFERROR((S28/$H$18),0) -> 0 | U28: =SUMIFS(Table1[[المنصرف ]],Table1[[نوع المصروف ]],$A:$A,Table1[[الشهر ]],$O$1,Table1[الفرع],'تحليلات 2024'!$H$20) -> 0 | V28: =IFERROR((U28/$H$18),0) -> 0 | W28: =SUMIFS(Table1[[المنصرف ]],Table1[[نوع المصروف ]],$A:$A,Table1[[الشهر ]],$O$1,Table1[الفرع],'تحليلات 2024'!$J$20) -> 0 | X28: =IFERROR((W28/$L$18),0) -> 0 | Y28: =O28+Q28+U28+W28+S28 -> 0 | Z28: =IFERROR((Y28/$L$18),0) -> 0 | AB28: =SUMIFS(Table1[[المنصرف ]],Table1[[نوع المصروف ]],$A:$A,Table1[[الشهر ]],$AB$1,Table1[الفرع],'تحليلات 2024'!$B$20) -> 0 | AC28: =IFERROR((AB28/$B$18),0) -> 0 | AD28: =SUMIFS(Table1[[المنصرف ]],Table1[[نوع المصروف ]],$A:$A,Table1[[الشهر ]],$AB$1,Table1[الفرع],'تحليلات 2024'!$D$20) -> 0 | AE28: =IFERROR((AD28/$D$18),0) -> 0 | AF28: =SUMIFS(Table1[[المنصرف ]],Table1[[نوع المصروف ]],$A:$A,Table1[[الشهر ]],$AB$1,Table1[الفرع],'تحليلات 2024'!$F$20) -> 0 | AG28: =IFERROR((AF28/$H$18),0) -> 0 | AH28: =SUMIFS(Table1[[المنصرف ]],Table1[[نوع المصروف ]],$A:$A,Table1[[الشهر ]],$AB$1,Table1[الفرع],'تحليلات 2024'!$H$20) -> 0 | AI28: =IFERROR((AH28/$H$18),0) -> 0 | AJ28: =SUMIFS(Table1[[المنصرف ]],Table1[[نوع المصروف ]],$A:$A,Table1[[الشهر ]],$AB$1,Table1[الفرع],'تحليلات 2024'!$J$20) -> 0 | AK28: =IFERROR((AJ28/$L$18),0) -> 0 | AL28: =AB28+AD28+AH28+AJ28+AF28 -> 0 | AM28: =IFERROR((AL28/$L$18),0) -> 0 | AO28: =SUMIFS(Table1[[المنصرف ]],Table1[[نوع المصروف ]],$A:$A,Table1[[الشهر ]],$AO$1,Table1[الفرع],'تحليلات 2024'!$B$20) -> 0 | AP28: =IFERROR((AO28/$B$18),0) -> 0 | AQ28: =SUMIFS(Table1[[المنصرف ]],Table1[[نوع المصروف ]],$A:$A,Table1[[الشهر ]],$AO$1,Table1[الفرع],'تحليلات 2024'!$D$20) -> 0 | AR28: =IFERROR((AQ28/$D$18),0) -> 0 | AS28: =SUMIFS(Table1[[المنصرف ]],Table1[[نوع المصروف ]],$A:$A,Table1[[الشهر ]],$AO$1,Table1[الفرع],'تحليلات 2024'!$F$20) -> 0 | AT28: =IFERROR((AS28/$H$18),0) -> 0 | AU28: =SUMIFS(Table1[[المنصرف ]],Table1[[نوع المصروف ]],$A:$A,Table1[[الشهر ]],$AO$1,Table1[الفرع],'تحليلات 2024'!$H$20) -> 0 | AV28: =IFERROR((AU28/$H$18),0) -> 0 | AW28: =SUMIFS(Table1[[المنصرف ]],Table1[[نوع المصروف ]],$A:$A,Table1[[الشهر ]],$AO$1,Table1[الفرع],'تحليلات 2024'!$J$20) -> 0 | AX28: =IFERROR((AW28/$L$18),0) -> 0 | AY28: =AO28+AQ28+AU28+AW28+AS28 -> 0 | AZ28: =IFERROR((AY28/$L$18),0) -> 0
A29: عمولات | B29: =SUMIFS(Table1[[المنصرف ]],Table1[[نوع المصروف ]],$A:$A,Table1[[الشهر ]],$B$1,Table1[الفرع],'تحليلات 2024'!$B$20) -> 0 | C29: =IFERROR((B29/$B$18),0) -> 0 | D29: =SUMIFS(Table1[[المنصرف ]],Table1[[نوع المصروف ]],$A:$A,Table1[[الشهر ]],$B$1,Table1[الفرع],'تحليلات 2024'!$D$20) -> 36928.39 | E29: =IFERROR((D29/$D$18),0) -> 0.21119227 | F29: =SUMIFS(Table1[[المنصرف ]],Table1[[نوع المصروف ]],$A:$A,Table1[[الشهر ]],$B$1,Table1[الفرع],'تحليلات 2024'!$F$20) -> 0 | G29: =IFERROR((F29/$H$18),0) -> 0 | H29: =SUMIFS(Table1[[المنصرف ]],Table1[[نوع المصروف ]],$A:$A,Table1[[الشهر ]],$B$1,Table1[الفرع],'تحليلات 2024'!$H$20) -> 0 | I29: =IFERROR((H29/$H$18),0) -> 0 | J29: =SUMIFS(Table1[[المنصرف ]],Table1[[نوع المصروف ]],$A:$A,Table1[[الشهر ]],$B$1,Table1[الفرع],'تحليلات 2024'!$J$20) -> 75026 | K29: =IFERROR((J29/$L$18),0) -> 0.089453145 | L29: =B29+D29+H29+J29+F29 -> 111954.39 | M29: =IFERROR((L29/$L$18),0) -> 0.13348269 | O29: =SUMIFS(Table1[[المنصرف ]],Table1[[نوع المصروف ]],$A:$A,Table1[[الشهر ]],$O$1,Table1[الفرع],'تحليلات 2024'!$B$20) -> 0 | P29: =IFERROR((O29/$B$18),0) -> 0 | Q29: =SUMIFS(Table1[[المنصرف ]],Table1[[نوع المصروف ]],$A:$A,Table1[[الشهر ]],$O$1,Table1[الفرع],'تحليلات 2024'!$D$20) -> 0 | R29: =IFERROR((Q29/$D$18),0) -> 0 | S29: =SUMIFS(Table1[[المنصرف ]],Table1[[نوع المصروف ]],$A:$A,Table1[[الشهر ]],$O$1,Table1[الفرع],'تحليلات 2024'!$F$20) -> 0 | T29: =IFERROR((S29/$H$18),0) -> 0 | U29: =SUMIFS(Table1[[المنصرف ]],Table1[[نوع المصروف ]],$A:$A,Table1[[الشهر ]],$O$1,Table1[الفرع],'تحليلات 2024'!$H$20) -> 0 | V29: =IFERROR((U29/$H$18),0) -> 0 | W29: =SUMIFS(Table1[[المنصرف ]],Table1[[نوع المصروف ]],$A:$A,Table1[[الشهر ]],$O$1,Table1[الفرع],'تحليلات 2024'!$J$20) -> 102088.85 | X29: =IFERROR((W29/$L$18),0) -> 0.12172005 | Y29: =O29+Q29+U29+W29+S29 -> 102088.85 | Z29: =IFERROR((Y29/$L$18),0) -> 0.12172005 | AB29: =SUMIFS(Table1[[المنصرف ]],Table1[[نوع المصروف ]],$A:$A,Table1[[الشهر ]],$AB$1,Table1[الفرع],'تحليلات 2024'!$B$20) -> 0 | AC29: =IFERROR((AB29/$B$18),0) -> 0 | AD29: =SUMIFS(Table1[[المنصرف ]],Table1[[نوع المصروف ]],$A:$A,Table1[[الشهر ]],$AB$1,Table1[الفرع],'تحليلات 2024'!$D$20) -> 0 | AE29: =IFERROR((AD29/$D$18),0) -> 0 | AF29: =SUMIFS(Table1[[المنصرف ]],Table1[[نوع المصروف ]],$A:$A,Table1[[الشهر ]],$AB$1,Table1[الفرع],'تحليلات 2024'!$F$20) -> 0 | AG29: =IFERROR((AF29/$H$18),0) -> 0 | AH29: =SUMIFS(Table1[[المنصرف ]],Table1[[نوع المصروف ]],$A:$A,Table1[[الشهر ]],$AB$1,Table1[الفرع],'تحليلات 2024'!$H$20) -> 0 | AI29: =IFERROR((AH29/$H$18),0) -> 0 | AJ29: =SUMIFS(Table1[[المنصرف ]],Table1[[نوع المصروف ]],$A:$A,Table1[[الشهر ]],$AB$1,Table1[الفرع],'تحليلات 2024'!$J$20) -> 0 | AK29: =IFERROR((AJ29/$L$18),0) -> 0 | AL29: =AB29+AD29+AH29+AJ29+AF29 -> 0 | AM29: =IFERROR((AL29/$L$18),0) -> 0 | AO29: =SUMIFS(Table1[[المنصرف ]],Table1[[نوع المصروف ]],$A:$A,Table1[[الشهر ]],$AO$1,Table1[الفرع],'تحليلات 2024'!$B$20) -> 0 | AP29: =IFERROR((AO29/$B$18),0) -> 0 | AQ29: =SUMIFS(Table1[[المنصرف ]],Table1[[نوع المصروف ]],$A:$A,Table1[[الشهر ]],$AO$1,Table1[الفرع],'تحليلات 2024'!$D$20) -> 0 | AR29: =IFERROR((AQ29/$D$18),0) -> 0 | AS29: =SUMIFS(Table1[[المنصرف ]],Table1[[نوع المصروف ]],$A:$A,Table1[[الشهر ]],$AO$1,Table1[الفرع],'تحليلات 2024'!$F$20) -> 0 | AT29: =IFERROR((AS29/$H$18),0) -> 0 | AU29: =SUMIFS(Table1[[المنصرف ]],Table1[[نوع المصروف ]],$A:$A,Table1[[الشهر ]],$AO$1,Table1[الفرع],'تحليلات 2024'!$H$20) -> 0 | AV29: =IFERROR((AU29/$H$18),0) -> 0 | AW29: =SUMIFS(Table1[[المنصرف ]],Table1[[نوع المصروف ]],$A:$A,Table1[[الشهر ]],$AO$1,Table1[الفرع],'تحليلات 2024'!$J$20) -> 0 | AX29: =IFERROR((AW29/$L$18),0) -> 0 | AY29: =AO29+AQ29+AU29+AW29+AS29 -> 0 | AZ29: =IFERROR((AY29/$L$18),0) -> 0
A30: مكافات | B30: =SUMIFS(Table1[[المنصرف ]],Table1[[نوع المصروف ]],$A:$A,Table1[[الشهر ]],$B$1,Table1[الفرع],'تحليلات 2024'!$B$20) -> 0 | C30: =IFERROR((B30/$B$18),0) -> 0 | D30: =SUMIFS(Table1[[المنصرف ]],Table1[[نوع المصروف ]],$A:$A,Table1[[الشهر ]],$B$1,Table1[الفرع],'تحليلات 2024'!$D$20) -> 600 | E30: =IFERROR((D30/$D$18),0) -> 0.0034313807 | F30: =SUMIFS(Table1[[المنصرف ]],Table1[[نوع المصروف ]],$A:$A,Table1[[الشهر ]],$B$1,Table1[الفرع],'تحليلات 2024'!$F$20) -> 1200 | G30: =IFERROR((F30/$H$18),0) -> 0 | H30: =SUMIFS(Table1[[المنصرف ]],Table1[[نوع المصروف ]],$A:$A,Table1[[الشهر ]],$B$1,Table1[الفرع],'تحليلات 2024'!$H$20) -> 0 | I30: =IFERROR((H30/$H$18),0) -> 0 | J30: =SUMIFS(Table1[[المنصرف ]],Table1[[نوع المصروف ]],$A:$A,Table1[[الشهر ]],$B$1,Table1[الفرع],'تحليلات 2024'!$J$20) -> 50 | K30: =IFERROR((J30/$L$18),0) -> 5.9614763e-05 | L30: =B30+D30+H30+J30+F30 -> 1850 | M30: =IFERROR((L30/$L$18),0) -> 0.0022057462 | O30: =SUMIFS(Table1[[المنصرف ]],Table1[[نوع المصروف ]],$A:$A,Table1[[الشهر ]],$O$1,Table1[الفرع],'تحليلات 2024'!$B$20) -> 0 | P30: =IFERROR((O30/$B$18),0) -> 0 | Q30: =SUMIFS(Table1[[المنصرف ]],Table1[[نوع المصروف ]],$A:$A,Table1[[الشهر ]],$O$1,Table1[الفرع],'تحليلات 2024'!$D$20) -> 0 | R30: =IFERROR((Q30/$D$18),0) -> 0 | S30: =SUMIFS(Table1[[المنصرف ]],Table1[[نوع المصروف ]],$A:$A,Table1[[الشهر ]],$O$1,Table1[الفرع],'تحليلات 2024'!$F$20) -> 0 | T30: =IFERROR((S30/$H$18),0) -> 0 | U30: =SUMIFS(Table1[[المنصرف ]],Table1[[نوع المصروف ]],$A:$A,Table1[[الشهر ]],$O$1,Table1[الفرع],'تحليلات 2024'!$H$20) -> 0 | V30: =IFERROR((U30/$H$18),0) -> 0 | W30: =SUMIFS(Table1[[المنصرف ]],Table1[[نوع المصروف ]],$A:$A,Table1[[الشهر ]],$O$1,Table1[الفرع],'تحليلات 2024'!$J$20) -> 0 | X30: =IFERROR((W30/$L$18),0) -> 0 | Y30: =O30+Q30+U30+W30+S30 -> 0 | Z30: =IFERROR((Y30/$L$18),0) -> 0 | AB30: =SUMIFS(Table1[[المنصرف ]],Table1[[نوع المصروف ]],$A:$A,Table1[[الشهر ]],$AB$1,Table1[الفرع],'تحليلات 2024'!$B$20) -> 0 | AC30: =IFERROR((AB30/$B$18),0) -> 0 | AD30: =SUMIFS(Table1[[المنصرف ]],Table1[[نوع المصروف ]],$A:$A,Table1[[الشهر ]],$AB$1,Table1[الفرع],'تحليلات 2024'!$D$20) -> 0 | AE30: =IFERROR((AD30/$D$18),0) -> 0 | AF30: =SUMIFS(Table1[[المنصرف ]],Table1[[نوع المصروف ]],$A:$A,Table1[[الشهر ]],$AB$1,Table1[الفرع],'تحليلات 2024'!$F$20) -> 0 | AG30: =IFERROR((AF30/$H$18),0) -> 0 | AH30: =SUMIFS(Table1[[المنصرف ]],Table1[[نوع المصروف ]],$A:$A,Table1[[الشهر ]],$AB$1,Table1[الفرع],'تحليلات 2024'!$H$20) -> 0 | AI30: =IFERROR((AH30/$H$18),0) -> 0 | AJ30: =SUMIFS(Table1[[المنصرف ]],Table1[[نوع المصروف ]],$A:$A,Table1[[الشهر ]],$AB$1,Table1[الفرع],'تحليلات 2024'!$J$20) -> 0 | AK30: =IFERROR((AJ30/$L$18),0) -> 0 | AL30: =AB30+AD30+AH30+AJ30+AF30 -> 0 | AM30: =IFERROR((AL30/$L$18),0) -> 0 | AO30: =SUMIFS(Table1[[المنصرف ]],Table1[[نوع المصروف ]],$A:$A,Table1[[الشهر ]],$AO$1,Table1[الفرع],'تحليلات 2024'!$B$20) -> 0 | AP30: =IFERROR((AO30/$B$18),0) -> 0 | AQ30: =SUMIFS(Table1[[المنصرف ]],Table1[[نوع المصروف ]],$A:$A,Table1[[الشهر ]],$AO$1,Table1[الفرع],'تحليلات 2024'!$D$20) -> 0 | AR30: =IFERROR((AQ30/$D$18),0) -> 0 | AS30: =SUMIFS(Table1[[المنصرف ]],Table1[[نوع المصروف ]],$A:$A,Table1[[الشهر ]],$AO$1,Table1[الفرع],'تحليلات 2024'!$F$20) -> 0 | AT30: =IFERROR((AS30/$H$18),0) -> 0 | AU30: =SUMIFS(Table1[[المنصرف ]],Table1[[نوع المصروف ]],$A:$A,Table1[[الشهر ]],$AO$1,Table1[الفرع],'تحليلات 2024'!$H$20) -> 0 | AV30: =IFERROR((AU30/$H$18),0) -> 0 | AW30: =SUMIFS(Table1[[المنصرف ]],Table1[[نوع المصروف ]],$A:$A,Table1[[الشهر ]],$AO$1,Table1[الفرع],'تحليلات 2024'!$J$20) -> 0 | AX30: =IFERROR((AW30/$L$18),0) -> 0 | AY30: =AO30+AQ30+AU30+AW30+AS30 -> 0 | AZ30: =IFERROR((AY30/$L$18),0) -> 0
A31: استشارات | B31: =SUMIFS(Table1[[المنصرف ]],Table1[[نوع المصروف ]],$A:$A,Table1[[الشهر ]],$B$1,Table1[الفرع],'تحليلات 2024'!$B$20) -> 0 | C31: =IFERROR((B31/$B$18),0) -> 0 | D31: =SUMIFS(Table1[[المنصرف ]],Table1[[نوع المصروف ]],$A:$A,Table1[[الشهر ]],$B$1,Table1[الفرع],'تحليلات 2024'!$D$20) -> 0 | E31: =IFERROR((D31/$D$18),0) -> 0 | F31: =SUMIFS(Table1[[المنصرف ]],Table1[[نوع المصروف ]],$A:$A,Table1[[الشهر ]],$B$1,Table1[الفرع],'تحليلات 2024'!$F$20) -> 0 | G31: =IFERROR((F31/$H$18),0) -> 0 | H31: =SUMIFS(Table1[[المنصرف ]],Table1[[نوع المصروف ]],$A:$A,Table1[[الشهر ]],$B$1,Table1[الفرع],'تحليلات 2024'!$H$20) -> 0 | I31: =IFERROR((H31/$H$18),0) -> 0 | J31: =SUMIFS(Table1[[المنصرف ]],Table1[[نوع المصروف ]],$A:$A,Table1[[الشهر ]],$B$1,Table1[الفرع],'تحليلات 2024'!$J$20) -> 6500 | K31: =IFERROR((J31/$L$18),0) -> 0.0077499192 | L31: =B31+D31+H31+J31+F31 -> 6500 | M31: =IFERROR((L31/$L$18),0) -> 0.0077499192 | O31: =SUMIFS(Table1[[المنصرف ]],Table1[[نوع المصروف ]],$A:$A,Table1[[الشهر ]],$O$1,Table1[الفرع],'تحليلات 2024'!$B$20) -> 0 | P31: =IFERROR((O31/$B$18),0) -> 0 | Q31: =SUMIFS(Table1[[المنصرف ]],Table1[[نوع المصروف ]],$A:$A,Table1[[الشهر ]],$O$1,Table1[الفرع],'تحليلات 2024'!$D$20) -> 0 | R31: =IFERROR((Q31/$D$18),0) -> 0 | S31: =SUMIFS(Table1[[المنصرف ]],Table1[[نوع المصروف ]],$A:$A,Table1[[الشهر ]],$O$1,Table1[الفرع],'تحليلات 2024'!$F$20) -> 0 | T31: =IFERROR((S31/$H$18),0) -> 0 | U31: =SUMIFS(Table1[[المنصرف ]],Table1[[نوع المصروف ]],$A:$A,Table1[[الشهر ]],$O$1,Table1[الفرع],'تحليلات 2024'!$H$20) -> 0 | V31: =IFERROR((U31/$H$18),0) -> 0 | W31: =SUMIFS(Table1[[المنصرف ]],Table1[[نوع المصروف ]],$A:$A,Table1[[الشهر ]],$O$1,Table1[الفرع],'تحليلات 2024'!$J$20) -> 6500 | X31: =IFERROR((W31/$L$18),0) -> 0.0077499192 | Y31: =O31+Q31+U31+W31+S31 -> 6500 | Z31: =IFERROR((Y31/$L$18),0) -> 0.0077499192 | AB31: =SUMIFS(Table1[[المنصرف ]],Table1[[نوع المصروف ]],$A:$A,Table1[[الشهر ]],$AB$1,Table1[الفرع],'تحليلات 2024'!$B$20) -> 0 | AC31: =IFERROR((AB31/$B$18),0) -> 0 | AD31: =SUMIFS(Table1[[المنصرف ]],Table1[[نوع المصروف ]],$A:$A,Table1[[الشهر ]],$AB$1,Table1[الفرع],'تحليلات 2024'!$D$20) -> 0 | AE31: =IFERROR((AD31/$D$18),0) -> 0 | AF31: =SUMIFS(Table1[[المنصرف ]],Table1[[نوع المصروف ]],$A:$A,Table1[[الشهر ]],$AB$1,Table1[الفرع],'تحليلات 2024'!$F$20) -> 0 | AG31: =IFERROR((AF31/$H$18),0) -> 0 | AH31: =SUMIFS(Table1[[المنصرف ]],Table1[[نوع المصروف ]],$A:$A,Table1[[الشهر ]],$AB$1,Table1[الفرع],'تحليلات 2024'!$H$20) -> 0 | AI31: =IFERROR((AH31/$H$18),0) -> 0 | AJ31: =SUMIFS(Table1[[المنصرف ]],Table1[[نوع المصروف ]],$A:$A,Table1[[الشهر ]],$AB$1,Table1[الفرع],'تحليلات 2024'!$J$20) -> 0 | AK31: =IFERROR((AJ31/$L$18),0) -> 0 | AL31: =AB31+AD31+AH31+AJ31+AF31 -> 0 | AM31: =IFERROR((AL31/$L$18),0) -> 0 | AO31: =SUMIFS(Table1[[المنصرف ]],Table1[[نوع المصروف ]],$A:$A,Table1[[الشهر ]],$AO$1,Table1[الفرع],'تحليلات 2024'!$B$20) -> 0 | AP31: =IFERROR((AO31/$B$18),0) -> 0 | AQ31: =SUMIFS(Table1[[المنصرف ]],Table1[[نوع المصروف ]],$A:$A,Table1[[الشهر ]],$AO$1,Table1[الفرع],'تحليلات 2024'!$D$20) -> 0 | AR31: =IFERROR((AQ31/$D$18),0) -> 0 | AS31: =SUMIFS(Table1[[المنصرف ]],Table1[[نوع المصروف ]],$A:$A,Table1[[الشهر ]],$AO$1,Table1[الفرع],'تحليلات 2024'!$F$20) -> 0 | AT31: =IFERROR((AS31/$H$18),0) -> 0 | AU31: =SUMIFS(Table1[[المنصرف ]],Table1[[نوع المصروف ]],$A:$A,Table1[[الشهر ]],$AO$1,Table1[الفرع],'تحليلات 2024'!$H$20) -> 0 | AV31: =IFERROR((AU31/$H$18),0) -> 0 | AW31: =SUMIFS(Table1[[المنصرف ]],Table1[[نوع المصروف ]],$A:$A,Table1[[الشهر ]],$AO$1,Table1[الفرع],'تحليلات 2024'!$J$20) -> 0 | AX31: =IFERROR((AW31/$L$18),0) -> 0 | AY31: =AO31+AQ31+AU31+AW31+AS31 -> 0 | AZ31: =IFERROR((AY31/$L$18),0) -> 0
A32: كسب العمل | B32: =SUMIFS(Table1[[المنصرف ]],Table1[[نوع المصروف ]],$A:$A,Table1[[الشهر ]],$B$1,Table1[الفرع],'تحليلات 2024'!$B$20) -> 0 | C32: =IFERROR((B32/$B$18),0) -> 0 | D32: =SUMIFS(Table1[[المنصرف ]],Table1[[نوع المصروف ]],$A:$A,Table1[[الشهر ]],$B$1,Table1[الفرع],'تحليلات 2024'!$D$20) -> 0 | E32: =IFERROR((D32/$D$18),0) -> 0 | F32: =SUMIFS(Table1[[المنصرف ]],Table1[[نوع المصروف ]],$A:$A,Table1[[الشهر ]],$B$1,Table1[الفرع],'تحليلات 2024'!$F$20) -> 0 | G32: =IFERROR((F32/$H$18),0) -> 0 | H32: =SUMIFS(Table1[[المنصرف ]],Table1[[نوع المصروف ]],$A:$A,Table1[[الشهر ]],$B$1,Table1[الفرع],'تحليلات 2024'!$H$20) -> 0 | I32: =IFERROR((H32/$H$18),0) -> 0 | J32: =SUMIFS(Table1[[المنصرف ]],Table1[[نوع المصروف ]],$A:$A,Table1[[الشهر ]],$B$1,Table1[الفرع],'تحليلات 2024'!$J$20) -> 1500 | K32: =IFERROR((J32/$L$18),0) -> 0.0017884429 | L32: =B32+D32+H32+J32+F32 -> 1500 | M32: =IFERROR((L32/$L$18),0) -> 0.0017884429 | O32: =SUMIFS(Table1[[المنصرف ]],Table1[[نوع المصروف ]],$A:$A,Table1[[الشهر ]],$O$1,Table1[الفرع],'تحليلات 2024'!$B$20) -> 0 | P32: =IFERROR((O32/$B$18),0) -> 0 | Q32: =SUMIFS(Table1[[المنصرف ]],Table1[[نوع المصروف ]],$A:$A,Table1[[الشهر ]],$O$1,Table1[الفرع],'تحليلات 2024'!$D$20) -> 0 | R32: =IFERROR((Q32/$D$18),0) -> 0 | S32: =SUMIFS(Table1[[المنصرف ]],Table1[[نوع المصروف ]],$A:$A,Table1[[الشهر ]],$O$1,Table1[الفرع],'تحليلات 2024'!$F$20) -> 0 | T32: =IFERROR((S32/$H$18),0) -> 0 | U32: =SUMIFS(Table1[[المنصرف ]],Table1[[نوع المصروف ]],$A:$A,Table1[[الشهر ]],$O$1,Table1[الفرع],'تحليلات 2024'!$H$20) -> 0 | V32: =IFERROR((U32/$H$18),0) -> 0 | W32: =SUMIFS(Table1[[المنصرف ]],Table1[[نوع المصروف ]],$A:$A,Table1[[الشهر ]],$O$1,Table1[الفرع],'تحليلات 2024'!$J$20) -> 0 | X32: =IFERROR((W32/$L$18),0) -> 0 | Y32: =O32+Q32+U32+W32+S32 -> 0 | Z32: =IFERROR((Y32/$L$18),0) -> 0 | AB32: =SUMIFS(Table1[[المنصرف ]],Table1[[نوع المصروف ]],$A:$A,Table1[[الشهر ]],$AB$1,Table1[الفرع],'تحليلات 2024'!$B$20) -> 0 | AC32: =IFERROR((AB32/$B$18),0) -> 0 | AD32: =SUMIFS(Table1[[المنصرف ]],Table1[[نوع المصروف ]],$A:$A,Table1[[الشهر ]],$AB$1,Table1[الفرع],'تحليلات 2024'!$D$20) -> 0 | AE32: =IFERROR((AD32/$D$18),0) -> 0 | AF32: =SUMIFS(Table1[[المنصرف ]],Table1[[نوع المصروف ]],$A:$A,Table1[[الشهر ]],$AB$1,Table1[الفرع],'تحليلات 2024'!$F$20) -> 0 | AG32: =IFERROR((AF32/$H$18),0) -> 0 | AH32: =SUMIFS(Table1[[المنصرف ]],Table1[[نوع المصروف ]],$A:$A,Table1[[الشهر ]],$AB$1,Table1[الفرع],'تحليلات 2024'!$H$20) -> 0 | AI32: =IFERROR((AH32/$H$18),0) -> 0 | AJ32: =SUMIFS(Table1[[المنصرف ]],Table1[[نوع المصروف ]],$A:$A,Table1[[الشهر ]],$AB$1,Table1[الفرع],'تحليلات 2024'!$J$20) -> 0 | AK32: =IFERROR((AJ32/$L$18),0) -> 0 | AL32: =AB32+AD32+AH32+AJ32+AF32 -> 0 | AM32: =IFERROR((AL32/$L$18),0) -> 0 | AO32: =SUMIFS(Table1[[المنصرف ]],Table1[[نوع المصروف ]],$A:$A,Table1[[الشهر ]],$AO$1,Table1[الفرع],'تحليلات 2024'!$B$20) -> 0 | AP32: =IFERROR((AO32/$B$18),0) -> 0 | AQ32: =SUMIFS(Table1[[المنصرف ]],Table1[[نوع المصروف ]],$A:$A,Table1[[الشهر ]],$AO$1,Table1[الفرع],'تحليلات 2024'!$D$20) -> 0 | AR32: =IFERROR((AQ32/$D$18),0) -> 0 | AS32: =SUMIFS(Table1[[المنصرف ]],Table1[[نوع المصروف ]],$A:$A,Table1[[الشهر ]],$AO$1,Table1[الفرع],'تحليلات 2024'!$F$20) -> 0 | AT32: =IFERROR((AS32/$H$18),0) -> 0 | AU32: =SUMIFS(Table1[[المنصرف ]],Table1[[نوع المصروف ]],$A:$A,Table1[[الشهر ]],$AO$1,Table1[الفرع],'تحليلات 2024'!$H$20) -> 0 | AV32: =IFERROR((AU32/$H$18),0) -> 0 | AW32: =SUMIFS(Table1[[المنصرف ]],Table1[[نوع المصروف ]],$A:$A,Table1[[الشهر ]],$AO$1,Table1[الفرع],'تحليلات 2024'!$J$20) -> 0 | AX32: =IFERROR((AW32/$L$18),0) -> 0 | AY32: =AO32+AQ32+AU32+AW32+AS32 -> 0 | AZ32: =IFERROR((AY32/$L$18),0) -> 0
A33: ض 14% | B33: =SUMIFS(Table1[[المنصرف ]],Table1[[نوع المصروف ]],$A:$A,Table1[[الشهر ]],$B$1,Table1[الفرع],'تحليلات 2024'!$B$20) -> 0 | C33: =IFERROR((B33/$B$18),0) -> 0 | D33: =SUMIFS(Table1[[المنصرف ]],Table1[[نوع المصروف ]],$A:$A,Table1[[الشهر ]],$B$1,Table1[الفرع],'تحليلات 2024'!$D$20) -> 36.7193 | E33: =IFERROR((D33/$D$18),0) -> 0.00020999649 | F33: =SUMIFS(Table1[[المنصرف ]],Table1[[نوع المصروف ]],$A:$A,Table1[[الشهر ]],$B$1,Table1[الفرع],'تحليلات 2024'!$F$20) -> 0 | G33: =IFERROR((F33/$H$18),0) -> 0 | H33: =SUMIFS(Table1[[المنصرف ]],Table1[[نوع المصروف ]],$A:$A,Table1[[الشهر ]],$B$1,Table1[الفرع],'تحليلات 2024'!$H$20) -> 0 | I33: =IFERROR((H33/$H$18),0) -> 0 | J33: =SUMIFS(Table1[[المنصرف ]],Table1[[نوع المصروف ]],$A:$A,Table1[[الشهر ]],$B$1,Table1[الفرع],'تحليلات 2024'!$J$20) -> 209693.54 | K33: =IFERROR((J33/$L$18),0) -> 0.25001662 | L33: =B33+D33+H33+J33+F33 -> 209730.26 | M33: =IFERROR((L33/$L$18),0) -> 0.2500604 | O33: =SUMIFS(Table1[[المنصرف ]],Table1[[نوع المصروف ]],$A:$A,Table1[[الشهر ]],$O$1,Table1[الفرع],'تحليلات 2024'!$B$20) -> 0 | P33: =IFERROR((O33/$B$18),0) -> 0 | Q33: =SUMIFS(Table1[[المنصرف ]],Table1[[نوع المصروف ]],$A:$A,Table1[[الشهر ]],$O$1,Table1[الفرع],'تحليلات 2024'!$D$20) -> 0 | R33: =IFERROR((Q33/$D$18),0) -> 0 | S33: =SUMIFS(Table1[[المنصرف ]],Table1[[نوع المصروف ]],$A:$A,Table1[[الشهر ]],$O$1,Table1[الفرع],'تحليلات 2024'!$F$20) -> 0 | T33: =IFERROR((S33/$H$18),0) -> 0 | U33: =SUMIFS(Table1[[المنصرف ]],Table1[[نوع المصروف ]],$A:$A,Table1[[الشهر ]],$O$1,Table1[الفرع],'تحليلات 2024'!$H$20) -> 0 | V33: =IFERROR((U33/$H$18),0) -> 0 | W33: =SUMIFS(Table1[[المنصرف ]],Table1[[نوع المصروف ]],$A:$A,Table1[[الشهر ]],$O$1,Table1[الفرع],'تحليلات 2024'!$J$20) -> 667.1 | X33: =IFERROR((W33/$L$18),0) -> 0.00079538017 | Y33: =O33+Q33+U33+W33+S33 -> 667.1 | Z33: =IFERROR((Y33/$L$18),0) -> 0.00079538017 | AB33: =SUMIFS(Table1[[المنصرف ]],Table1[[نوع المصروف ]],$A:$A,Table1[[الشهر ]],$AB$1,Table1[الفرع],'تحليلات 2024'!$B$20) -> 0 | AC33: =IFERROR((AB33/$B$18),0) -> 0 | AD33: =SUMIFS(Table1[[المنصرف ]],Table1[[نوع المصروف ]],$A:$A,Table1[[الشهر ]],$AB$1,Table1[الفرع],'تحليلات 2024'!$D$20) -> 0 | AE33: =IFERROR((AD33/$D$18),0) -> 0 | AF33: =SUMIFS(Table1[[المنصرف ]],Table1[[نوع المصروف ]],$A:$A,Table1[[الشهر ]],$AB$1,Table1[الفرع],'تحليلات 2024'!$F$20) -> 0 | AG33: =IFERROR((AF33/$H$18),0) -> 0 | AH33: =SUMIFS(Table1[[المنصرف ]],Table1[[نوع المصروف ]],$A:$A,Table1[[الشهر ]],$AB$1,Table1[الفرع],'تحليلات 2024'!$H$20) -> 0 | AI33: =IFERROR((AH33/$H$18),0) -> 0 | AJ33: =SUMIFS(Table1[[المنصرف ]],Table1[[نوع المصروف ]],$A:$A,Table1[[الشهر ]],$AB$1,Table1[الفرع],'تحليلات 2024'!$J$20) -> 0 | AK33: =IFERROR((AJ33/$L$18),0) -> 0 | AL33: =AB33+AD33+AH33+AJ33+AF33 -> 0 | AM33: =IFERROR((AL33/$L$18),0) -> 0 | AO33: =SUMIFS(Table1[[المنصرف ]],Table1[[نوع المصروف ]],$A:$A,Table1[[الشهر ]],$AO$1,Table1[الفرع],'تحليلات 2024'!$B$20) -> 0 | AP33: =IFERROR((AO33/$B$18),0) -> 0 | AQ33: =SUMIFS(Table1[[المنصرف ]],Table1[[نوع المصروف ]],$A:$A,Table1[[الشهر ]],$AO$1,Table1[الفرع],'تحليلات 2024'!$D$20) -> 0 | AR33: =IFERROR((AQ33/$D$18),0) -> 0 | AS33: =SUMIFS(Table1[[المنصرف ]],Table1[[نوع المصروف ]],$A:$A,Table1[[الشهر ]],$AO$1,Table1[الفرع],'تحليلات 2024'!$F$20) -> 0 | AT33: =IFERROR((AS33/$H$18),0) -> 0 | AU33: =SUMIFS(Table1[[المنصرف ]],Table1[[نوع المصروف ]],$A:$A,Table1[[الشهر ]],$AO$1,Table1[الفرع],'تحليلات 2024'!$H$20) -> 0 | AV33: =IFERROR((AU33/$H$18),0) -> 0 | AW33: =SUMIFS(Table1[[المنصرف ]],Table1[[نوع المصروف ]],$A:$A,Table1[[الشهر ]],$AO$1,Table1[الفرع],'تحليلات 2024'!$J$20) -> 0 | AX33: =IFERROR((AW33/$L$18),0) -> 0 | AY33: =AO33+AQ33+AU33+AW33+AS33 -> 0 | AZ33: =IFERROR((AY33/$L$18),0) -> 0
... A59: دعايا وإعلان | B59: =SUMIFS(Table1[[المنصرف ]],Table1[[نوع المصروف ]],$A:$A,Table1[[الشهر ]],$B$1,Table1[الفرع],'تحليلات 2024'!$B$20) -> 0 | C59: =IFERROR((B59/$B$18),0) -> 0 | D59: =SUMIFS(Table1[[المنصرف ]],Table1[[نوع المصروف ]],$A:$A,Table1[[الشهر ]],$B$1,Table1[الفرع],'تحليلات 2024'!$D$20) -> 0 | E59: =IFERROR((D59/$D$18),0) -> 0 | F59: =SUMIFS(Table1[[المنصرف ]],Table1[[نوع المصروف ]],$A:$A,Table1[[الشهر ]],$B$1,Table1[الفرع],'تحليلات 2024'!$F$20) -> 0 | G59: =IFERROR((F59/$H$18),0) -> 0 | H59: =SUMIFS(Table1[[المنصرف ]],Table1[[نوع المصروف ]],$A:$A,Table1[[الشهر ]],$B$1,Table1[الفرع],'تحليلات 2024'!$H$20) -> 0 | I59: =IFERROR((H59/$H$18),0) -> 0 | J59: =SUMIFS(Table1[[المنصرف ]],Table1[[نوع المصروف ]],$A:$A,Table1[[الشهر ]],$B$1,Table1[الفرع],'تحليلات 2024'!$J$20) -> 0 | K59: =IFERROR((J59/$L$18),0) -> 0 | L59: =B59+D59+H59+J59+F59 -> 0 | M59: =IFERROR((L59/$L$18),0) -> 0 | O59: =SUMIFS(Table1[[المنصرف ]],Table1[[نوع المصروف ]],$A:$A,Table1[[الشهر ]],$O$1,Table1[الفرع],'تحليلات 2024'!$B$20) -> 0 | P59: =IFERROR((O59/$B$18),0) -> 0 | Q59: =SUMIFS(Table1[[المنصرف ]],Table1[[نوع المصروف ]],$A:$A,Table1[[الشهر ]],$O$1,Table1[الفرع],'تحليلات 2024'!$D$20) -> 0 | R59: =IFERROR((Q59/$D$18),0) -> 0 | S59: =SUMIFS(Table1[[المنصرف ]],Table1[[نوع المصروف ]],$A:$A,Table1[[الشهر ]],$O$1,Table1[الفرع],'تحليلات 2024'!$F$20) -> 0 | T59: =IFERROR((S59/$H$18),0) -> 0 | U59: =SUMIFS(Table1[[المنصرف ]],Table1[[نوع المصروف ]],$A:$A,Table1[[الشهر ]],$O$1,Table1[الفرع],'تحليلات 2024'!$H$20) -> 0 | V59: =IFERROR((U59/$H$18),0) -> 0 | W59: =SUMIFS(Table1[[المنصرف ]],Table1[[نوع المصروف ]],$A:$A,Table1[[الشهر ]],$O$1,Table1[الفرع],'تحليلات 2024'!$J$20) -> 0 | X59: =IFERROR((W59/$L$18),0) -> 0 | Y59: =O59+Q59+U59+W59+S59 -> 0 | Z59: =IFERROR((Y59/$L$18),0) -> 0 | AB59: =SUMIFS(Table1[[المنصرف ]],Table1[[نوع المصروف ]],$A:$A,Table1[[الشهر ]],$AB$1,Table1[الفرع],'تحليلات 2024'!$B$20) -> 0 | AC59: =IFERROR((AB59/$B$18),0) -> 0 | AD59: =SUMIFS(Table1[[المنصرف ]],Table1[[نوع المصروف ]],$A:$A,Table1[[الشهر ]],$AB$1,Table1[الفرع],'تحليلات 2024'!$D$20) -> 0 | AE59: =IFERROR((AD59/$D$18),0) -> 0 | AF59: =SUMIFS(Table1[[المنصرف ]],Table1[[نوع المصروف ]],$A:$A,Table1[[الشهر ]],$AB$1,Table1[الفرع],'تحليلات 2024'!$F$20) -> 0 | AG59: =IFERROR((AF59/$H$18),0) -> 0 | AH59: =SUMIFS(Table1[[المنصرف ]],Table1[[نوع المصروف ]],$A:$A,Table1[[الشهر ]],$AB$1,Table1[الفرع],'تحليلات 2024'!$H$20) -> 0 | AI59: =IFERROR((AH59/$H$18),0) -> 0 | AJ59: =SUMIFS(Table1[[المنصرف ]],Table1[[نوع المصروف ]],$A:$A,Table1[[الشهر ]],$AB$1,Table1[الفرع],'تحليلات 2024'!$J$20) -> 0 | AK59: =IFERROR((AJ59/$L$18),0) -> 0 | AL59: =AB59+AD59+AH59+AJ59+AF59 -> 0 | AM59: =IFERROR((AL59/$L$18),0) -> 0 | AO59: =SUMIFS(Table1[[المنصرف ]],Table1[[نوع المصروف ]],$A:$A,Table1[[الشهر ]],$AO$1,Table1[الفرع],'تحليلات 2024'!$B$20) -> 0 | AP59: =IFERROR((AO59/$B$18),0) -> 0 | AQ59: =SUMIFS(Table1[[المنصرف ]],Table1[[نوع المصروف ]],$A:$A,Table1[[الشهر ]],$AO$1,Table1[الفرع],'تحليلات 2024'!$D$20) -> 0 | AR59: =IFERROR((AQ59/$D$18),0) -> 0 | AS59: =SUMIFS(Table1[[المنصرف ]],Table1[[نوع المصروف ]],$A:$A,Table1[[الشهر ]],$AO$1,Table1[الفرع],'تحليلات 2024'!$F$20) -> 0 | AT59: =IFERROR((AS59/$H$18),0) -> 0 | AU59: =SUMIFS(Table1[[المنصرف ]],Table1[[نوع المصروف ]],$A:$A,Table1[[الشهر ]],$AO$1,Table1[الفرع],'تحليلات 2024'!$H$20) -> 0 | AV59: =IFERROR((AU59/$H$18),0) -> 0 | AW59: =SUMIFS(Table1[[المنصرف ]],Table1[[نوع المصروف ]],$A:$A,Table1[[الشهر ]],$AO$1,Table1[الفرع],'تحليلات 2024'!$J$20) -> 0 | AX59: =IFERROR((AW59/$L$18),0) -> 0 | AY59: =AO59+AQ59+AU59+AW59+AS59 -> 0 | AZ59: =IFERROR((AY59/$L$18),0) -> 0
B60: =SUMIFS(Table1[[المنصرف ]],Table1[[نوع المصروف ]],$A:$A,Table1[[الشهر ]],$B$1,Table1[الفرع],'تحليلات 2024'!$B$20) -> 0 | C60: =IFERROR((B60/$B$18),0) -> 0 | D60: =SUMIFS(Table1[[المنصرف ]],Table1[[نوع المصروف ]],$A:$A,Table1[[الشهر ]],$B$1,Table1[الفرع],'تحليلات 2024'!$D$20) -> 0 | E60: =IFERROR((D60/$D$18),0) -> 0 | F60: =SUMIFS(Table1[[المنصرف ]],Table1[[نوع المصروف ]],$A:$A,Table1[[الشهر ]],$B$1,Table1[الفرع],'تحليلات 2024'!$F$20) -> 0 | G60: =IFERROR((F60/$H$18),0) -> 0 | H60: =SUMIFS(Table1[[المنصرف ]],Table1[[نوع المصروف ]],$A:$A,Table1[[الشهر ]],$B$1,Table1[الفرع],'تحليلات 2024'!$H$20) -> 0 | I60: =IFERROR((H60/$H$18),0) -> 0 | J60: =SUMIFS(Table1[[المنصرف ]],Table1[[نوع المصروف ]],$A:$A,Table1[[الشهر ]],$B$1,Table1[الفرع],'تحليلات 2024'!$J$20) -> 0 | K60: =IFERROR((J60/$L$18),0) -> 0 | L60: =B60+D60+H60+J60+F60 -> 0 | M60: =IFERROR((L60/$L$18),0) -> 0 | O60: =SUMIFS(Table1[[المنصرف ]],Table1[[نوع المصروف ]],$A:$A,Table1[[الشهر ]],$O$1,Table1[الفرع],'تحليلات 2024'!$B$20) -> 0 | P60: =IFERROR((O60/$B$18),0) -> 0 | Q60: =SUMIFS(Table1[[المنصرف ]],Table1[[نوع المصروف ]],$A:$A,Table1[[الشهر ]],$O$1,Table1[الفرع],'تحليلات 2024'!$D$20) -> 0 | R60: =IFERROR((Q60/$D$18),0) -> 0 | S60: =SUMIFS(Table1[[المنصرف ]],Table1[[نوع المصروف ]],$A:$A,Table1[[الشهر ]],$O$1,Table1[الفرع],'تحليلات 2024'!$F$20) -> 0 | T60: =IFERROR((S60/$H$18),0) -> 0 | U60: =SUMIFS(Table1[[المنصرف ]],Table1[[نوع المصروف ]],$A:$A,Table1[[الشهر ]],$O$1,Table1[الفرع],'تحليلات 2024'!$H$20) -> 0 | V60: =IFERROR((U60/$H$18),0) -> 0 | W60: =SUMIFS(Table1[[المنصرف ]],Table1[[نوع المصروف ]],$A:$A,Table1[[الشهر ]],$O$1,Table1[الفرع],'تحليلات 2024'!$J$20) -> 0 | X60: =IFERROR((W60/$L$18),0) -> 0 | Y60: =O60+Q60+U60+W60+S60 -> 0 | Z60: =IFERROR((Y60/$L$18),0) -> 0 | AB60: =SUMIFS(Table1[[المنصرف ]],Table1[[نوع المصروف ]],$A:$A,Table1[[الشهر ]],$AB$1,Table1[الفرع],'تحليلات 2024'!$B$20) -> 0 | AC60: =IFERROR((AB60/$B$18),0) -> 0 | AD60: =SUMIFS(Table1[[المنصرف ]],Table1[[نوع المصروف ]],$A:$A,Table1[[الشهر ]],$AB$1,Table1[الفرع],'تحليلات 2024'!$D$20) -> 0 | AE60: =IFERROR((AD60/$D$18),0) -> 0 | AF60: =SUMIFS(Table1[[المنصرف ]],Table1[[نوع المصروف ]],$A:$A,Table1[[الشهر ]],$AB$1,Table1[الفرع],'تحليلات 2024'!$F$20) -> 0 | AG60: =IFERROR((AF60/$H$18),0) -> 0 | AH60: =SUMIFS(Table1[[المنصرف ]],Table1[[نوع المصروف ]],$A:$A,Table1[[الشهر ]],$AB$1,Table1[الفرع],'تحليلات 2024'!$H$20) -> 0 | AI60: =IFERROR((AH60/$H$18),0) -> 0 | AJ60: =SUMIFS(Table1[[المنصرف ]],Table1[[نوع المصروف ]],$A:$A,Table1[[الشهر ]],$AB$1,Table1[الفرع],'تحليلات 2024'!$J$20) -> 0 | AK60: =IFERROR((AJ60/$L$18),0) -> 0 | AL60: =AB60+AD60+AH60+AJ60+AF60 -> 0 | AM60: =IFERROR((AL60/$L$18),0) -> 0 | AO60: =SUMIFS(Table1[[المنصرف ]],Table1[[نوع المصروف ]],$A:$A,Table1[[الشهر ]],$AO$1,Table1[الفرع],'تحليلات 2024'!$B$20) -> 0 | AP60: =IFERROR((AO60/$B$18),0) -> 0 | AQ60: =SUMIFS(Table1[[المنصرف ]],Table1[[نوع المصروف ]],$A:$A,Table1[[الشهر ]],$AO$1,Table1[الفرع],'تحليلات 2024'!$D$20) -> 0 | AR60: =IFERROR((AQ60/$D$18),0) -> 0 | AS60: =SUMIFS(Table1[[المنصرف ]],Table1[[نوع المصروف ]],$A:$A,Table1[[الشهر ]],$AO$1,Table1[الفرع],'تحليلات 2024'!$F$20) -> 0 | AT60: =IFERROR((AS60/$H$18),0) -> 0 | AU60: =SUMIFS(Table1[[المنصرف ]],Table1[[نوع المصروف ]],$A:$A,Table1[[الشهر ]],$AO$1,Table1[الفرع],'تحليلات 2024'!$H$20) -> 0 | AV60: =IFERROR((AU60/$H$18),0) -> 0 | AW60: =SUMIFS(Table1[[المنصرف ]],Table1[[نوع المصروف ]],$A:$A,Table1[[الشهر ]],$AO$1,Table1[الفرع],'تحليلات 2024'!$J$20) -> 0 | AX60: =IFERROR((AW60/$L$18),0) -> 0 | AY60: =AO60+AQ60+AU60+AW60+AS60 -> 0 | AZ60: =IFERROR((AY60/$L$18),0) -> 0
B61: =SUMIFS(Table1[[المنصرف ]],Table1[[نوع المصروف ]],$A:$A,Table1[[الشهر ]],$B$1,Table1[الفرع],'تحليلات 2024'!$B$20) -> 0 | C61: =IFERROR((B61/$B$18),0) -> 0 | D61: =SUMIFS(Table1[[المنصرف ]],Table1[[نوع المصروف ]],$A:$A,Table1[[الشهر ]],$B$1,Table1[الفرع],'تحليلات 2024'!$D$20) -> 0 | E61: =IFERROR((D61/$D$18),0) -> 0 | F61: =SUMIFS(Table1[[المنصرف ]],Table1[[نوع المصروف ]],$A:$A,Table1[[الشهر ]],$B$1,Table1[الفرع],'تحليلات 2024'!$F$20) -> 0 | G61: =IFERROR((F61/$H$18),0) -> 0 | H61: =SUMIFS(Table1[[المنصرف ]],Table1[[نوع المصروف ]],$A:$A,Table1[[الشهر ]],$B$1,Table1[الفرع],'تحليلات 2024'!$H$20) -> 0 | I61: =IFERROR((H61/$H$18),0) -> 0 | J61: =SUMIFS(Table1[[المنصرف ]],Table1[[نوع المصروف ]],$A:$A,Table1[[الشهر ]],$B$1,Table1[الفرع],'تحليلات 2024'!$J$20) -> 0 | K61: =IFERROR((J61/$L$18),0) -> 0 | L61: =B61+D61+H61+J61+F61 -> 0 | M61: =IFERROR((L61/$L$18),0) -> 0 | O61: =SUMIFS(Table1[[المنصرف ]],Table1[[نوع المصروف ]],$A:$A,Table1[[الشهر ]],$O$1,Table1[الفرع],'تحليلات 2024'!$B$20) -> 0 | P61: =IFERROR((O61/$B$18),0) -> 0 | Q61: =SUMIFS(Table1[[المنصرف ]],Table1[[نوع المصروف ]],$A:$A,Table1[[الشهر ]],$O$1,Table1[الفرع],'تحليلات 2024'!$D$20) -> 0 | R61: =IFERROR((Q61/$D$18),0) -> 0 | S61: =SUMIFS(Table1[[المنصرف ]],Table1[[نوع المصروف ]],$A:$A,Table1[[الشهر ]],$O$1,Table1[الفرع],'تحليلات 2024'!$F$20) -> 0 | T61: =IFERROR((S61/$H$18),0) -> 0 | U61: =SUMIFS(Table1[[المنصرف ]],Table1[[نوع المصروف ]],$A:$A,Table1[[الشهر ]],$O$1,Table1[الفرع],'تحليلات 2024'!$H$20) -> 0 | V61: =IFERROR((U61/$H$18),0) -> 0 | W61: =SUMIFS(Table1[[المنصرف ]],Table1[[نوع المصروف ]],$A:$A,Table1[[الشهر ]],$O$1,Table1[الفرع],'تحليلات 2024'!$J$20) -> 0 | X61: =IFERROR((W61/$L$18),0) -> 0 | Y61: =O61+Q61+U61+W61+S61 -> 0 | Z61: =IFERROR((Y61/$L$18),0) -> 0 | AB61: =SUMIFS(Table1[[المنصرف ]],Table1[[نوع المصروف ]],$A:$A,Table1[[الشهر ]],$AB$1,Table1[الفرع],'تحليلات 2024'!$B$20) -> 0 | AC61: =IFERROR((AB61/$B$18),0) -> 0 | AD61: =SUMIFS(Table1[[المنصرف ]],Table1[[نوع المصروف ]],$A:$A,Table1[[الشهر ]],$AB$1,Table1[الفرع],'تحليلات 2024'!$D$20) -> 0 | AE61: =IFERROR((AD61/$D$18),0) -> 0 | AF61: =SUMIFS(Table1[[المنصرف ]],Table1[[نوع المصروف ]],$A:$A,Table1[[الشهر ]],$AB$1,Table1[الفرع],'تحليلات 2024'!$F$20) -> 0 | AG61: =IFERROR((AF61/$H$18),0) -> 0 | AH61: =SUMIFS(Table1[[المنصرف ]],Table1[[نوع المصروف ]],$A:$A,Table1[[الشهر ]],$AB$1,Table1[الفرع],'تحليلات 2024'!$H$20) -> 0 | AI61: =IFERROR((AH61/$H$18),0) -> 0 | AJ61: =SUMIFS(Table1[[المنصرف ]],Table1[[نوع المصروف ]],$A:$A,Table1[[الشهر ]],$AB$1,Table1[الفرع],'تحليلات 2024'!$J$20) -> 0 | AK61: =IFERROR((AJ61/$L$18),0) -> 0 | AL61: =AB61+AD61+AH61+AJ61+AF61 -> 0 | AM61: =IFERROR((AL61/$L$18),0) -> 0 | AO61: =SUMIFS(Table1[[المنصرف ]],Table1[[نوع المصروف ]],$A:$A,Table1[[الشهر ]],$AO$1,Table1[الفرع],'تحليلات 2024'!$B$20) -> 0 | AP61: =IFERROR((AO61/$B$18),0) -> 0 | AQ61: =SUMIFS(Table1[[المنصرف ]],Table1[[نوع المصروف ]],$A:$A,Table1[[الشهر ]],$AO$1,Table1[الفرع],'تحليلات 2024'!$D$20) -> 0 | AR61: =IFERROR((AQ61/$D$18),0) -> 0 | AS61: =SUMIFS(Table1[[المنصرف ]],Table1[[نوع المصروف ]],$A:$A,Table1[[الشهر ]],$AO$1,Table1[الفرع],'تحليلات 2024'!$F$20) -> 0 | AT61: =IFERROR((AS61/$H$18),0) -> 0 | AU61: =SUMIFS(Table1[[المنصرف ]],Table1[[نوع المصروف ]],$A:$A,Table1[[الشهر ]],$AO$1,Table1[الفرع],'تحليلات 2024'!$H$20) -> 0 | AV61: =IFERROR((AU61/$H$18),0) -> 0 | AW61: =SUMIFS(Table1[[المنصرف ]],Table1[[نوع المصروف ]],$A:$A,Table1[[الشهر ]],$AO$1,Table1[الفرع],'تحليلات 2024'!$J$20) -> 0 | AX61: =IFERROR((AW61/$L$18),0) -> 0 | AY61: =AO61+AQ61+AU61+AW61+AS61 -> 0 | AZ61: =IFERROR((AY61/$L$18),0) -> 0
B62: =SUMIFS(Table1[[المنصرف ]],Table1[[نوع المصروف ]],$A:$A,Table1[[الشهر ]],$B$1,Table1[الفرع],'تحليلات 2024'!$B$20) -> 0 | C62: =IFERROR((B62/$B$18),0) -> 0 | D62: =SUMIFS(Table1[[المنصرف ]],Table1[[نوع المصروف ]],$A:$A,Table1[[الشهر ]],$B$1,Table1[الفرع],'تحليلات 2024'!$D$20) -> 0 | E62: =IFERROR((D62/$D$18),0) -> 0 | F62: =SUMIFS(Table1[[المنصرف ]],Table1[[نوع المصروف ]],$A:$A,Table1[[الشهر ]],$B$1,Table1[الفرع],'تحليلات 2024'!$F$20) -> 0 | G62: =IFERROR((F62/$H$18),0) -> 0 | H62: =SUMIFS(Table1[[المنصرف ]],Table1[[نوع المصروف ]],$A:$A,Table1[[الشهر ]],$B$1,Table1[الفرع],'تحليلات 2024'!$H$20) -> 0 | I62: =IFERROR((H62/$H$18),0) -> 0 | J62: =SUMIFS(Table1[[المنصرف ]],Table1[[نوع المصروف ]],$A:$A,Table1[[الشهر ]],$B$1,Table1[الفرع],'تحليلات 2024'!$J$20) -> 0 | K62: =IFERROR((J62/$L$18),0) -> 0 | L62: =B62+D62+H62+J62+F62 -> 0 | M62: =IFERROR((L62/$L$18),0) -> 0 | O62: =SUMIFS(Table1[[المنصرف ]],Table1[[نوع المصروف ]],$A:$A,Table1[[الشهر ]],$O$1,Table1[الفرع],'تحليلات 2024'!$B$20) -> 0 | P62: =IFERROR((O62/$B$18),0) -> 0 | Q62: =SUMIFS(Table1[[المنصرف ]],Table1[[نوع المصروف ]],$A:$A,Table1[[الشهر ]],$O$1,Table1[الفرع],'تحليلات 2024'!$D$20) -> 0 | R62: =IFERROR((Q62/$D$18),0) -> 0 | S62: =SUMIFS(Table1[[المنصرف ]],Table1[[نوع المصروف ]],$A:$A,Table1[[الشهر ]],$O$1,Table1[الفرع],'تحليلات 2024'!$F$20) -> 0 | T62: =IFERROR((S62/$H$18),0) -> 0 | U62: =SUMIFS(Table1[[المنصرف ]],Table1[[نوع المصروف ]],$A:$A,Table1[[الشهر ]],$O$1,Table1[الفرع],'تحليلات 2024'!$H$20) -> 0 | V62: =IFERROR((U62/$H$18),0) -> 0 | W62: =SUMIFS(Table1[[المنصرف ]],Table1[[نوع المصروف ]],$A:$A,Table1[[الشهر ]],$O$1,Table1[الفرع],'تحليلات 2024'!$J$20) -> 0 | X62: =IFERROR((W62/$L$18),0) -> 0 | Y62: =O62+Q62+U62+W62+S62 -> 0 | Z62: =IFERROR((Y62/$L$18),0) -> 0 | AB62: =SUMIFS(Table1[[المنصرف ]],Table1[[نوع المصروف ]],$A:$A,Table1[[الشهر ]],$AB$1,Table1[الفرع],'تحليلات 2024'!$B$20) -> 0 | AC62: =IFERROR((AB62/$B$18),0) -> 0 | AD62: =SUMIFS(Table1[[المنصرف ]],Table1[[نوع المصروف ]],$A:$A,Table1[[الشهر ]],$AB$1,Table1[الفرع],'تحليلات 2024'!$D$20) -> 0 | AE62: =IFERROR((AD62/$D$18),0) -> 0 | AF62: =SUMIFS(Table1[[المنصرف ]],Table1[[نوع المصروف ]],$A:$A,Table1[[الشهر ]],$AB$1,Table1[الفرع],'تحليلات 2024'!$F$20) -> 0 | AG62: =IFERROR((AF62/$H$18),0) -> 0 | AH62: =SUMIFS(Table1[[المنصرف ]],Table1[[نوع المصروف ]],$A:$A,Table1[[الشهر ]],$AB$1,Table1[الفرع],'تحليلات 2024'!$H$20) -> 0 | AI62: =IFERROR((AH62/$H$18),0) -> 0 | AJ62: =SUMIFS(Table1[[المنصرف ]],Table1[[نوع المصروف ]],$A:$A,Table1[[الشهر ]],$AB$1,Table1[الفرع],'تحليلات 2024'!$J$20) -> 0 | AK62: =IFERROR((AJ62/$L$18),0) -> 0 | AL62: =AB62+AD62+AH62+AJ62+AF62 -> 0 | AM62: =IFERROR((AL62/$L$18),0) -> 0 | AO62: =SUMIFS(Table1[[المنصرف ]],Table1[[نوع المصروف ]],$A:$A,Table1[[الشهر ]],$AO$1,Table1[الفرع],'تحليلات 2024'!$B$20) -> 0 | AP62: =IFERROR((AO62/$B$18),0) -> 0 | AQ62: =SUMIFS(Table1[[المنصرف ]],Table1[[نوع المصروف ]],$A:$A,Table1[[الشهر ]],$AO$1,Table1[الفرع],'تحليلات 2024'!$D$20) -> 0 | AR62: =IFERROR((AQ62/$D$18),0) -> 0 | AS62: =SUMIFS(Table1[[المنصرف ]],Table1[[نوع المصروف ]],$A:$A,Table1[[الشهر ]],$AO$1,Table1[الفرع],'تحليلات 2024'!$F$20) -> 0 | AT62: =IFERROR((AS62/$H$18),0) -> 0 | AU62: =SUMIFS(Table1[[المنصرف ]],Table1[[نوع المصروف ]],$A:$A,Table1[[الشهر ]],$AO$1,Table1[الفرع],'تحليلات 2024'!$H$20) -> 0 | AV62: =IFERROR((AU62/$H$18),0) -> 0 | AW62: =SUMIFS(Table1[[المنصرف ]],Table1[[نوع المصروف ]],$A:$A,Table1[[الشهر ]],$AO$1,Table1[الفرع],'تحليلات 2024'!$J$20) -> 0 | AX62: =IFERROR((AW62/$L$18),0) -> 0 | AY62: =AO62+AQ62+AU62+AW62+AS62 -> 0 | AZ62: =IFERROR((AY62/$L$18),0) -> 0
B63: =SUMIFS(Table1[[المنصرف ]],Table1[[نوع المصروف ]],$A:$A,Table1[[الشهر ]],$B$1,Table1[الفرع],'تحليلات 2024'!$B$20) -> 0 | C63: =IFERROR((B63/$B$18),0) -> 0 | D63: =SUMIFS(Table1[[المنصرف ]],Table1[[نوع المصروف ]],$A:$A,Table1[[الشهر ]],$B$1,Table1[الفرع],'تحليلات 2024'!$D$20) -> 0 | E63: =IFERROR((D63/$D$18),0) -> 0 | F63: =SUMIFS(Table1[[المنصرف ]],Table1[[نوع المصروف ]],$A:$A,Table1[[الشهر ]],$B$1,Table1[الفرع],'تحليلات 2024'!$F$20) -> 0 | G63: =IFERROR((F63/$H$18),0) -> 0 | H63: =SUMIFS(Table1[[المنصرف ]],Table1[[نوع المصروف ]],$A:$A,Table1[[الشهر ]],$B$1,Table1[الفرع],'تحليلات 2024'!$H$20) -> 0 | I63: =IFERROR((H63/$H$18),0) -> 0 | J63: =SUMIFS(Table1[[المنصرف ]],Table1[[نوع المصروف ]],$A:$A,Table1[[الشهر ]],$B$1,Table1[الفرع],'تحليلات 2024'!$J$20) -> 0 | K63: =IFERROR((J63/$L$18),0) -> 0 | L63: =B63+D63+H63+J63+F63 -> 0 | M63: =IFERROR((L63/$L$18),0) -> 0 | O63: =SUMIFS(Table1[[المنصرف ]],Table1[[نوع المصروف ]],$A:$A,Table1[[الشهر ]],$O$1,Table1[الفرع],'تحليلات 2024'!$B$20) -> 0 | P63: =IFERROR((O63/$B$18),0) -> 0 | Q63: =SUMIFS(Table1[[المنصرف ]],Table1[[نوع المصروف ]],$A:$A,Table1[[الشهر ]],$O$1,Table1[الفرع],'تحليلات 2024'!$D$20) -> 0 | R63: =IFERROR((Q63/$D$18),0) -> 0 | S63: =SUMIFS(Table1[[المنصرف ]],Table1[[نوع المصروف ]],$A:$A,Table1[[الشهر ]],$O$1,Table1[الفرع],'تحليلات 2024'!$F$20) -> 0 | T63: =IFERROR((S63/$H$18),0) -> 0 | U63: =SUMIFS(Table1[[المنصرف ]],Table1[[نوع المصروف ]],$A:$A,Table1[[الشهر ]],$O$1,Table1[الفرع],'تحليلات 2024'!$H$20) -> 0 | V63: =IFERROR((U63/$H$18),0) -> 0 | W63: =SUMIFS(Table1[[المنصرف ]],Table1[[نوع المصروف ]],$A:$A,Table1[[الشهر ]],$O$1,Table1[الفرع],'تحليلات 2024'!$J$20) -> 0 | X63: =IFERROR((W63/$L$18),0) -> 0 | Y63: =O63+Q63+U63+W63+S63 -> 0 | Z63: =IFERROR((Y63/$L$18),0) -> 0 | AB63: =SUMIFS(Table1[[المنصرف ]],Table1[[نوع المصروف ]],$A:$A,Table1[[الشهر ]],$AB$1,Table1[الفرع],'تحليلات 2024'!$B$20) -> 0 | AC63: =IFERROR((AB63/$B$18),0) -> 0 | AD63: =SUMIFS(Table1[[المنصرف ]],Table1[[نوع المصروف ]],$A:$A,Table1[[الشهر ]],$AB$1,Table1[الفرع],'تحليلات 2024'!$D$20) -> 0 | AE63: =IFERROR((AD63/$D$18),0) -> 0 | AF63: =SUMIFS(Table1[[المنصرف ]],Table1[[نوع المصروف ]],$A:$A,Table1[[الشهر ]],$AB$1,Table1[الفرع],'تحليلات 2024'!$F$20) -> 0 | AG63: =IFERROR((AF63/$H$18),0) -> 0 | AH63: =SUMIFS(Table1[[المنصرف ]],Table1[[نوع المصروف ]],$A:$A,Table1[[الشهر ]],$AB$1,Table1[الفرع],'تحليلات 2024'!$H$20) -> 0 | AI63: =IFERROR((AH63/$H$18),0) -> 0 | AJ63: =SUMIFS(Table1[[المنصرف ]],Table1[[نوع المصروف ]],$A:$A,Table1[[الشهر ]],$AB$1,Table1[الفرع],'تحليلات 2024'!$J$20) -> 0 | AK63: =IFERROR((AJ63/$L$18),0) -> 0 | AL63: =AB63+AD63+AH63+AJ63+AF63 -> 0 | AM63: =IFERROR((AL63/$L$18),0) -> 0 | AO63: =SUMIFS(Table1[[المنصرف ]],Table1[[نوع المصروف ]],$A:$A,Table1[[الشهر ]],$AO$1,Table1[الفرع],'تحليلات 2024'!$B$20) -> 0 | AP63: =IFERROR((AO63/$B$18),0) -> 0 | AQ63: =SUMIFS(Table1[[المنصرف ]],Table1[[نوع المصروف ]],$A:$A,Table1[[الشهر ]],$AO$1,Table1[الفرع],'تحليلات 2024'!$D$20) -> 0 | AR63: =IFERROR((AQ63/$D$18),0) -> 0 | AS63: =SUMIFS(Table1[[المنصرف ]],Table1[[نوع المصروف ]],$A:$A,Table1[[الشهر ]],$AO$1,Table1[الفرع],'تحليلات 2024'!$F$20) -> 0 | AT63: =IFERROR((AS63/$H$18),0) -> 0 | AU63: =SUMIFS(Table1[[المنصرف ]],Table1[[نوع المصروف ]],$A:$A,Table1[[الشهر ]],$AO$1,Table1[الفرع],'تحليلات 2024'!$H$20) -> 0 | AV63: =IFERROR((AU63/$H$18),0) -> 0 | AW63: =SUMIFS(Table1[[المنصرف ]],Table1[[نوع المصروف ]],$A:$A,Table1[[الشهر ]],$AO$1,Table1[الفرع],'تحليلات 2024'!$J$20) -> 0 | AX63: =IFERROR((AW63/$L$18),0) -> 0 | AY63: =AO63+AQ63+AU63+AW63+AS63 -> 0 | AZ63: =IFERROR((AY63/$L$18),0) -> 0
B64: =SUMIFS(Table1[[المنصرف ]],Table1[[نوع المصروف ]],$A:$A,Table1[[الشهر ]],$B$1,Table1[الفرع],'تحليلات 2024'!$B$20) -> 0 | C64: =IFERROR((B64/$B$18),0) -> 0 | D64: =SUMIFS(Table1[[المنصرف ]],Table1[[نوع المصروف ]],$A:$A,Table1[[الشهر ]],$B$1,Table1[الفرع],'تحليلات 2024'!$D$20) -> 0 | E64: =IFERROR((D64/$D$18),0) -> 0 | F64: =SUMIFS(Table1[[المنصرف ]],Table1[[نوع المصروف ]],$A:$A,Table1[[الشهر ]],$B$1,Table1[الفرع],'تحليلات 2024'!$F$20) -> 0 | G64: =IFERROR((F64/$H$18),0) -> 0 | H64: =SUMIFS(Table1[[المنصرف ]],Table1[[نوع المصروف ]],$A:$A,Table1[[الشهر ]],$B$1,Table1[الفرع],'تحليلات 2024'!$H$20) -> 0 | I64: =IFERROR((H64/$H$18),0) -> 0 | J64: =SUMIFS(Table1[[المنصرف ]],Table1[[نوع المصروف ]],$A:$A,Table1[[الشهر ]],$B$1,Table1[الفرع],'تحليلات 2024'!$J$20) -> 0 | K64: =IFERROR((J64/$L$18),0) -> 0 | L64: =B64+D64+H64+J64+F64 -> 0 | M64: =IFERROR((L64/$L$18),0) -> 0 | O64: =SUMIFS(Table1[[المنصرف ]],Table1[[نوع المصروف ]],$A:$A,Table1[[الشهر ]],$O$1,Table1[الفرع],'تحليلات 2024'!$B$20) -> 0 | P64: =IFERROR((O64/$B$18),0) -> 0 | Q64: =SUMIFS(Table1[[المنصرف ]],Table1[[نوع المصروف ]],$A:$A,Table1[[الشهر ]],$O$1,Table1[الفرع],'تحليلات 2024'!$D$20) -> 0 | R64: =IFERROR((Q64/$D$18),0) -> 0 | S64: =SUMIFS(Table1[[المنصرف ]],Table1[[نوع المصروف ]],$A:$A,Table1[[الشهر ]],$O$1,Table1[الفرع],'تحليلات 2024'!$F$20) -> 0 | T64: =IFERROR((S64/$H$18),0) -> 0 | U64: =SUMIFS(Table1[[المنصرف ]],Table1[[نوع المصروف ]],$A:$A,Table1[[الشهر ]],$O$1,Table1[الفرع],'تحليلات 2024'!$H$20) -> 0 | V64: =IFERROR((U64/$H$18),0) -> 0 | W64: =SUMIFS(Table1[[المنصرف ]],Table1[[نوع المصروف ]],$A:$A,Table1[[الشهر ]],$O$1,Table1[الفرع],'تحليلات 2024'!$J$20) -> 0 | X64: =IFERROR((W64/$L$18),0) -> 0 | Y64: =O64+Q64+U64+W64+S64 -> 0 | Z64: =IFERROR((Y64/$L$18),0) -> 0 | AB64: =SUMIFS(Table1[[المنصرف ]],Table1[[نوع المصروف ]],$A:$A,Table1[[الشهر ]],$AB$1,Table1[الفرع],'تحليلات 2024'!$B$20) -> 0 | AC64: =IFERROR((AB64/$B$18),0) -> 0 | AD64: =SUMIFS(Table1[[المنصرف ]],Table1[[نوع المصروف ]],$A:$A,Table1[[الشهر ]],$AB$1,Table1[الفرع],'تحليلات 2024'!$D$20) -> 0 | AE64: =IFERROR((AD64/$D$18),0) -> 0 | AF64: =SUMIFS(Table1[[المنصرف ]],Table1[[نوع المصروف ]],$A:$A,Table1[[الشهر ]],$AB$1,Table1[الفرع],'تحليلات 2024'!$F$20) -> 0 | AG64: =IFERROR((AF64/$H$18),0) -> 0 | AH64: =SUMIFS(Table1[[المنصرف ]],Table1[[نوع المصروف ]],$A:$A,Table1[[الشهر ]],$AB$1,Table1[الفرع],'تحليلات 2024'!$H$20) -> 0 | AI64: =IFERROR((AH64/$H$18),0) -> 0 | AJ64: =SUMIFS(Table1[[المنصرف ]],Table1[[نوع المصروف ]],$A:$A,Table1[[الشهر ]],$AB$1,Table1[الفرع],'تحليلات 2024'!$J$20) -> 0 | AK64: =IFERROR((AJ64/$L$18),0) -> 0 | AL64: =AB64+AD64+AH64+AJ64+AF64 -> 0 | AM64: =IFERROR((AL64/$L$18),0) -> 0 | AO64: =SUMIFS(Table1[[المنصرف ]],Table1[[نوع المصروف ]],$A:$A,Table1[[الشهر ]],$AO$1,Table1[الفرع],'تحليلات 2024'!$B$20) -> 0 | AP64: =IFERROR((AO64/$B$18),0) -> 0 | AQ64: =SUMIFS(Table1[[المنصرف ]],Table1[[نوع المصروف ]],$A:$A,Table1[[الشهر ]],$AO$1,Table1[الفرع],'تحليلات 2024'!$D$20) -> 0 | AR64: =IFERROR((AQ64/$D$18),0) -> 0 | AS64: =SUMIFS(Table1[[المنصرف ]],Table1[[نوع المصروف ]],$A:$A,Table1[[الشهر ]],$AO$1,Table1[الفرع],'تحليلات 2024'!$F$20) -> 0 | AT64: =IFERROR((AS64/$H$18),0) -> 0 | AU64: =SUMIFS(Table1[[المنصرف ]],Table1[[نوع المصروف ]],$A:$A,Table1[[الشهر ]],$AO$1,Table1[الفرع],'تحليلات 2024'!$H$20) -> 0 | AV64: =IFERROR((AU64/$H$18),0) -> 0 | AW64: =SUMIFS(Table1[[المنصرف ]],Table1[[نوع المصروف ]],$A:$A,Table1[[الشهر ]],$AO$1,Table1[الفرع],'تحليلات 2024'!$J$20) -> 0 | AX64: =IFERROR((AW64/$L$18),0) -> 0 | AY64: =AO64+AQ64+AU64+AW64+AS64 -> 0 | AZ64: =IFERROR((AY64/$L$18),0) -> 0
B65: =SUMIFS(Table1[[المنصرف ]],Table1[[نوع المصروف ]],$A:$A,Table1[[الشهر ]],$B$1,Table1[الفرع],'تحليلات 2024'!$B$20) -> 0 | C65: =IFERROR((B65/$B$18),0) -> 0 | D65: =SUMIFS(Table1[[المنصرف ]],Table1[[نوع المصروف ]],$A:$A,Table1[[الشهر ]],$B$1,Table1[الفرع],'تحليلات 2024'!$D$20) -> 0 | E65: =IFERROR((D65/$D$18),0) -> 0 | F65: =SUMIFS(Table1[[المنصرف ]],Table1[[نوع المصروف ]],$A:$A,Table1[[الشهر ]],$B$1,Table1[الفرع],'تحليلات 2024'!$F$20) -> 0 | G65: =IFERROR((F65/$H$18),0) -> 0 | H65: =SUMIFS(Table1[[المنصرف ]],Table1[[نوع المصروف ]],$A:$A,Table1[[الشهر ]],$B$1,Table1[الفرع],'تحليلات 2024'!$H$20) -> 0 | I65: =IFERROR((H65/$H$18),0) -> 0 | J65: =SUMIFS(Table1[[المنصرف ]],Table1[[نوع المصروف ]],$A:$A,Table1[[الشهر ]],$B$1,Table1[الفرع],'تحليلات 2024'!$J$20) -> 0 | K65: =IFERROR((J65/$L$18),0) -> 0 | L65: =B65+D65+H65+J65+F65 -> 0 | M65: =IFERROR((L65/$L$18),0) -> 0 | O65: =SUMIFS(Table1[[المنصرف ]],Table1[[نوع المصروف ]],$A:$A,Table1[[الشهر ]],$O$1,Table1[الفرع],'تحليلات 2024'!$B$20) -> 0 | P65: =IFERROR((O65/$B$18),0) -> 0 | Q65: =SUMIFS(Table1[[المنصرف ]],Table1[[نوع المصروف ]],$A:$A,Table1[[الشهر ]],$O$1,Table1[الفرع],'تحليلات 2024'!$D$20) -> 0 | R65: =IFERROR((Q65/$D$18),0) -> 0 | S65: =SUMIFS(Table1[[المنصرف ]],Table1[[نوع المصروف ]],$A:$A,Table1[[الشهر ]],$O$1,Table1[الفرع],'تحليلات 2024'!$F$20) -> 0 | T65: =IFERROR((S65/$H$18),0) -> 0 | U65: =SUMIFS(Table1[[المنصرف ]],Table1[[نوع المصروف ]],$A:$A,Table1[[الشهر ]],$O$1,Table1[الفرع],'تحليلات 2024'!$H$20) -> 0 | V65: =IFERROR((U65/$H$18),0) -> 0 | W65: =SUMIFS(Table1[[المنصرف ]],Table1[[نوع المصروف ]],$A:$A,Table1[[الشهر ]],$O$1,Table1[الفرع],'تحليلات 2024'!$J$20) -> 0 | X65: =IFERROR((W65/$L$18),0) -> 0 | Y65: =O65+Q65+U65+W65+S65 -> 0 | Z65: =IFERROR((Y65/$L$18),0) -> 0 | AB65: =SUMIFS(Table1[[المنصرف ]],Table1[[نوع المصروف ]],$A:$A,Table1[[الشهر ]],$AB$1,Table1[الفرع],'تحليلات 2024'!$B$20) -> 0 | AC65: =IFERROR((AB65/$B$18),0) -> 0 | AD65: =SUMIFS(Table1[[المنصرف ]],Table1[[نوع المصروف ]],$A:$A,Table1[[الشهر ]],$AB$1,Table1[الفرع],'تحليلات 2024'!$D$20) -> 0 | AE65: =IFERROR((AD65/$D$18),0) -> 0 | AF65: =SUMIFS(Table1[[المنصرف ]],Table1[[نوع المصروف ]],$A:$A,Table1[[الشهر ]],$AB$1,Table1[الفرع],'تحليلات 2024'!$F$20) -> 0 | AG65: =IFERROR((AF65/$H$18),0) -> 0 | AH65: =SUMIFS(Table1[[المنصرف ]],Table1[[نوع المصروف ]],$A:$A,Table1[[الشهر ]],$AB$1,Table1[الفرع],'تحليلات 2024'!$H$20) -> 0 | AI65: =IFERROR((AH65/$H$18),0) -> 0 | AJ65: =SUMIFS(Table1[[المنصرف ]],Table1[[نوع المصروف ]],$A:$A,Table1[[الشهر ]],$AB$1,Table1[الفرع],'تحليلات 2024'!$J$20) -> 0 | AK65: =IFERROR((AJ65/$L$18),0) -> 0 | AL65: =AB65+AD65+AH65+AJ65+AF65 -> 0 | AM65: =IFERROR((AL65/$L$18),0) -> 0 | AO65: =SUMIFS(Table1[[المنصرف ]],Table1[[نوع المصروف ]],$A:$A,Table1[[الشهر ]],$AO$1,Table1[الفرع],'تحليلات 2024'!$B$20) -> 0 | AP65: =IFERROR((AO65/$B$18),0) -> 0 | AQ65: =SUMIFS(Table1[[المنصرف ]],Table1[[نوع المصروف ]],$A:$A,Table1[[الشهر ]],$AO$1,Table1[الفرع],'تحليلات 2024'!$D$20) -> 0 | AR65: =IFERROR((AQ65/$D$18),0) -> 0 | AS65: =SUMIFS(Table1[[المنصرف ]],Table1[[نوع المصروف ]],$A:$A,Table1[[الشهر ]],$AO$1,Table1[الفرع],'تحليلات 2024'!$F$20) -> 0 | AT65: =IFERROR((AS65/$H$18),0) -> 0 | AU65: =SUMIFS(Table1[[المنصرف ]],Table1[[نوع المصروف ]],$A:$A,Table1[[الشهر ]],$AO$1,Table1[الفرع],'تحليلات 2024'!$H$20) -> 0 | AV65: =IFERROR((AU65/$H$18),0) -> 0 | AW65: =SUMIFS(Table1[[المنصرف ]],Table1[[نوع المصروف ]],$A:$A,Table1[[الشهر ]],$AO$1,Table1[الفرع],'تحليلات 2024'!$J$20) -> 0 | AX65: =IFERROR((AW65/$L$18),0) -> 0 | AY65: =AO65+AQ65+AU65+AW65+AS65 -> 0 | AZ65: =IFERROR((AY65/$L$18),0) -> 0
A66: اجمالي المصروفات | B66: =SUM(B21:B65) -> 4323.96 | C66: =IFERROR((B66/$B$18),0) -> 0.0065801916 | D66: =SUM(D21:D65) -> 169019.6 | E66: =IFERROR((D66/$D$18),0) -> 0.96661764 | F66: =SUM(F21:F65) -> 15266.03 | G66: =IFERROR((F66/$H$18),0) -> 0 | H66: =SUM(H21:H65) -> 26 | I66: =IFERROR((H66/$H$18),0) -> 0 | J66: =SUM(J21:J65) -> 391729.58 | K66: =IFERROR((J66/$H$18),0) -> 0 | L66: =B66+D66+H66+J66+F66 -> 580365.17 | M66: =IFERROR((L66/$L$18),0) -> 0.69196665 | O66: =SUM(O21:O65) -> 69 | P66: =IFERROR((O66/$B$18),0) -> 0.00010500403 | Q66: =SUM(Q21:Q65) -> 0 | R66: =IFERROR((Q66/$D$18),0) -> 0 | S66: =SUM(S21:S65) -> 6175 | T66: =IFERROR((S66/$H$18),0) -> 0 | U66: =SUM(U21:U65) -> 0 | V66: =IFERROR((U66/$H$18),0) -> 0 | W66: =SUM(W21:W65) -> 194895.19 | X66: =IFERROR((W66/$H$18),0) -> 0 | Y66: =O66+Q66+U66+W66+S66 -> 201139.19 | Z66: =IFERROR((Y66/$L$18),0) -> 0.2398173 | AB66: =SUM(AB21:AB65) -> 0 | AC66: =IFERROR((AB66/$B$18),0) -> 0 | AD66: =SUM(AD21:AD65) -> 0 | AE66: =IFERROR((AD66/$D$18),0) -> 0 | AF66: =SUM(AF21:AF65) -> 0 | AG66: =IFERROR((AF66/$H$18),0) -> 0 | AH66: =SUM(AH21:AH65) -> 0 | AI66: =IFERROR((AH66/$H$18),0) -> 0 | AJ66: =SUM(AJ21:AJ65) -> 0 | AK66: =IFERROR((AJ66/$H$18),0) -> 0 | AL66: =AB66+AD66+AH66+AJ66+AF66 -> 0 | AM66: =IFERROR((AL66/$L$18),0) -> 0 | AO66: =SUM(AO21:AO65) -> 0 | AP66: =IFERROR((AO66/$B$18),0) -> 0 | AQ66: =SUM(AQ21:AQ65) -> 0 | AR66: =IFERROR((AQ66/$D$18),0) -> 0 | AS66: =SUM(AS21:AS65) -> 0 | AT66: =IFERROR((AS66/$H$18),0) -> 0 | AU66: =SUM(AU21:AU65) -> 0 | AV66: =IFERROR((AU66/$H$18),0) -> 0 | AW66: =SUM(AW21:AW65) -> 0 | AX66: =IFERROR((AW66/$H$18),0) -> 0 | AY66: =AO66+AQ66+AU66+AW66+AS66 -> 0 | AZ66: =IFERROR((AY66/$L$18),0) -> 0
A69: الربح | B69: =B18-B66 -> 652793.68 | C69: =IFERROR((B69/B18),0) -> 0.99341981 | D69: =D18-D66 -> 5837.1295 | E69: =IFERROR((D69/D18),0) -> 0.033382356 | F69: =F18-F66 -> -8521.9861 | G69: =IFERROR((F69/F18),0) -> -1.2636315 | H69: =H18-H66 -> -26 | I69: =IFERROR((H69/H18),0) -> 0 | J69: =J18-J66 -> -391729.58 | K69: =IFERROR((J69/J18),0) -> 0 | L69: =L18-L66 -> 258353.24 | M69: =IFERROR((L69/L18),0) -> 0.30803335 | O69: =O18-O66 -> 252332.39 | P69: =IFERROR((O69/O18),0) -> 0.99972663 | Q69: =Q18-Q66 -> 152521.69 | R69: =IFERROR((Q69/Q18),0) -> 1 | S69: =S18-S66 -> -6175 | T69: =IFERROR((S69/S18),0) -> 0 | U69: =U18-U66 -> 3000 | V69: =IFERROR((U69/U18),0) -> 1 | W69: =W18-W66 -> -194895.19 | X69: =IFERROR((W69/W18),0) -> 0 | Y69: =Y18-Y66 -> 206783.89 | Z69: =IFERROR((Y69/Y18),0) -> 0.50691883 | AB69: =AB18-AB66 -> 0 | AC69: =IFERROR((AB69/AB18),0) -> 0 | AD69: =AD18-AD66 -> 0 | AE69: =IFERROR((AD69/AD18),0) -> 0 | AF69: =AF18-AF66 -> 0 | AG69: =IFERROR((AF69/AF18),0) -> 0 | AH69: =AH18-AH66 -> 0 | AI69: =IFERROR((AH69/AH18),0) -> 0 | AJ69: =AJ18-AJ66 -> 0 | AK69: =IFERROR((AJ69/AJ18),0) -> 0 | AL69: =AL18-AL66 -> 0 | AM69: =IFERROR((AL69/AL18),0) -> 0 | AO69: =AO18-AO66 -> 0 | AP69: =IFERROR((AO69/AO18),0) -> 0 | AQ69: =AQ18-AQ66 -> 0 | AR69: =IFERROR((AQ69/AQ18),0) -> 0 | AS69: =AS18-AS66 -> 0 | AT69: =IFERROR((AS69/AS18),0) -> 0 | AU69: =AU18-AU66 -> 0 | AV69: =IFERROR((AU69/AU18),0) -> 0 | AW69: =AW18-AW66 -> 0 | AX69: =IFERROR((AW69/AW18),0) -> 0 | AY69: =AY18-AY66 -> 0 | AZ69: =IFERROR((AY69/AY18),0) -> 0

Sheet Report 
A1: =TODAY() -> 46006 | C1: =TEXT(A1,"dddd") -> Monday | E1: =TEXT(A1,"mmmm") -> December
H2: الإيرادات
A3: رصيد البنك | D3: رصيد الخزينه
A4: القاهرة | B4: مصر | C4: كريدي | D4: الرصيد | E4: ='الخزينه '!A545 -> 12065 | H4: الشهر | I4: العميل | J4: المطلوب تحويله | K4: المبلغ المسدد | L4: المستحق | M4: 14%
B5: ='بنك مصر '!A1 -> 290342.53 | C5: ='بنك كريدي '!A1 -> 384822.19 | D5: ='الخزينه '!C546 -> اجمالي السلف | E5: ='الخزينه '!A546 -> 26600 | H5: 45778 | I5: بنك الإسكندرية | J5: 186066.52 | K5: 186066.52 | L5: 0 | M5: 23467.849
B6: الاهلى الكويتى | C6: ايجي بنك | D6: ='الخزينه '!C547 -> اجمالي العهد | E6: ='الخزينه '!A547-E7-E8 -> 522197.06 | I6: شركه رايه للالكترونيات | J6: 71470.573 | K6: 70182.815 | L6: 4.7748472e-12 | M6: 9014.3065
B7: =+'الاهلى الكويتى'!A1 -> 153740 | C7: 2000 | D7: الإدارة الرقمية | E7: =+'العهد '!K5 -> 49667.985 | I7: شركه رايه قانونى | J7: 243090 | K7: 243090 | L7: 0 | M7: 30660
A8: المنصورة | B8: مصر | D8: الإدارة الرقميةالمنصورة | E8: =+'العهد '!K6 -> 20000 | I8: بنك كريدي اجريكول مصر | J8: 250067.87 | K8: 245562.14 | L8: -1.3642421e-11 | M8: 31540.092
B9: 167.95 | I9: ميد للتقسيط | J9: 145397.71 | K9: 114793 | L9: -30604.712 | M9: 18338.45
I10: مانى فيللوز لتكنولوجيا المعلومات وادارة المشروعات | J10: 133793.64 | K10: 133793.64 | L10: 0 | M10: 16874.873
I11: تنميه لخدمات المشروعات متناهيه الصغر | J11: 138007.19 | K11: 138007.19 | L11: 0 | M11: 17406.312
A12: اجمالي | B12: =SUM(B5:C11) -> 831072.67 | D12: اجمالي | E12: =SUM(E4:E11) -> 630530.05 | I12: سفن | J12: 58417.781 | K12: 58417.781 | L12: 0 | M12: 7368.0084
A13: المصروفات الشهريه | B13: المبلغ | C13: المدفوع | D13: الباقي | E13: ملاحظات | I13: اور للتمويل الاستهلاكى -وسيلة | J13: 77191.708 | K13: 77191.708 | L13: 0 | M13: 9735.8911
A14: المرتبات | B14: 397467.51 | C14: =365217.56+1044+9187.5 -> 375449.06 | D14: =Table9[[#This Row],[المبلغ]]-Table9[[#This Row],[المدفوع]] -> 22018.45 | E14: نوفمبر | F14: =Table9[[#This Row],[الباقي ]]+D15+D16+D17 -> 23018.446 | G14: =F18+F14 -> 23018.446 | I14: اور للتمويل الاستهلاكى -وسيلة قانونى | J14: 228030.57 | K14: 228030.57 | L14: -0.0015789474 | M14: 28760.613
A15: الاستشارات | B15: 8000 | C15: 8000 | D15: =Table9[[#This Row],[المبلغ]]-Table9[[#This Row],[المدفوع]] -> 0 | E15: نوفمبر | I15: امان لتمويل المشروعات | J15: 3012.54 | K15: 3012.54 | L15: 0 | M15: 379.96
A16: بدلات | B16: 7651 | C16: 7651 | D16: =Table9[[#This Row],[المبلغ]]-Table9[[#This Row],[المدفوع]] -> 0 | E16: نوفمبر | I16: فورى لتكنولوجيا المعلومات التجارية | J16: 76970.418 | K16: 76970.418 | L16: 0 | M16: 9707.9807
A17: مكافات | B17: 21867.136 | C17: 20867.14 | D17: =Table9[[#This Row],[المبلغ]]-Table9[[#This Row],[المدفوع]] -> 999.9957 | E17: نوفمبر | I17: بنك البركة مصر | J17: 10101 | K17: 10101 | L17: 0 | M17: 1274
A18: عمولات رايه | B18: 12113.926 | C18: 12113.926 | D18: =Table9[[#This Row],[المبلغ]]-Table9[[#This Row],[المدفوع]] -> 0 | E18: أكتوبر | F18: =Table9[[#This Row],[الباقي ]]+D19+D20+D21+D22+D23+D24+D26+D27+D28+D30+D29 -> 0 | H18: May-25 Total | J18: 1621617.5 | K18: 1585219.3 | L18: -30604.714 | M18: 204528.33
A19: عمولات شركه فورى | D19: =Table9[[#This Row],[المبلغ]]-Table9[[#This Row],[المدفوع]] -> 0 | E19: أكتوبر | H19: 45809 | I19: بنك الإسكندرية | J19: 120472.42 | K19: 120472.42 | L19: 0 | M19: 15194.719
A20: عمولات حالا | B20: 35825.236 | C20: 35825.236 | D20: =Table9[[#This Row],[المبلغ]]-Table9[[#This Row],[المدفوع]] -> 0 | E20: أكتوبر | I20: شركه رايه للالكترونيات | J20: 52425.154 | K20: 51480.56 | L20: 0.0034210526 | M20: 6612.1816
A21: عمولات سفن | B21: 7406.2184 | C21: 7406.2184 | D21: =Table9[[#This Row],[المبلغ]]-Table9[[#This Row],[المدفوع]] -> 0 | E21: أكتوبر | I21: شركه رايه قانونى | J21: 291930 | K21: 291930 | L21: 0 | M21: 36820
A22: عمولات الاسكندريه | B22: 34783.25 | C22: 34783.25 | D22: =Table9[[#This Row],[المبلغ]]-Table9[[#This Row],[المدفوع]] -> 0 | E22: أكتوبر | I22: بنك كريدي اجريكول مصر | J22: 195920.11 | K22: 192390.02 | L22: 0.0029785965 | M22: 24710.644
A23: عمولات كريدي | B23: 70521.155 | C23: 70521.155 | D23: =Table9[[#This Row],[المبلغ]]-Table9[[#This Row],[المدفوع]] -> 0 | E23: أكتوبر | I23: ميد للتقسيط | J23: 112611.54 | K23: 112611.54 | L23: 0 | M23: 14203.257
A24: عمولات ماني | B24: 18624.189 | C24: 18624.189 | D24: =Table9[[#This Row],[المبلغ]]-Table9[[#This Row],[المدفوع]] -> 0 | E24: أكتوبر | I24: مانى فيللوز لتكنولوجيا المعلومات وادارة المشروعات | J24: 119537.75 | K24: 119537.75 | L24: 0 | M24: 15076.833
A25: عمولات وسيلة | B25: 10422.292 | C25: 10422.292 | D25: =Table9[[#This Row],[المبلغ]]-Table9[[#This Row],[المدفوع]] -> 0 | E25: أكتوبر | I25: تنميه لخدمات المشروعات متناهيه الصغر | J25: 98151.253 | K25: 98151.253 | L25: 0 | M25: 12379.437
A26: عمولات وسيلة | B26: 11280.84 | C26: 11280.84 | D26: =Table9[[#This Row],[المبلغ]]-Table9[[#This Row],[المدفوع]] -> 0 | E26: سبتمبر | I26: سفن | J26: 33249.505 | K26: 33249.505 | L26: 0 | M26: 4193.6312
A27: عمولات تنمية | B27: 32242.355 | C27: 32242.355 | D27: =Table9[[#This Row],[المبلغ]]-Table9[[#This Row],[المدفوع]] -> 0 | E27: أكتوبر | I27: اور للتمويل الاستهلاكى -وسيلة | J27: 57414.331 | K27: 57414.331 | L27: 0 | M27: 7241.4472
A28: عمولات ميد بنك | B28: 24864.531 | C28: 24864.531 | D28: =Table9[[#This Row],[المبلغ]]-Table9[[#This Row],[المدفوع]] -> 0 | E28: أكتوبر | I28: سهولة قانونى | J28: 135975 | K28: 135975 | L28: 0 | M28: 17150
A29: عمولات ميد تقسيط | B29: 0 | C29: 0 | D29: =Table9[[#This Row],[المبلغ]]-Table9[[#This Row],[المدفوع]] -> 0 | E29: أكتوبر | I29: امان لتمويل المشروعات | J29: 2220 | L29: -2220 | M29: 280
A30: عمولات إرادة | B30: 7794.4746 | C30: 7794.4746 | D30: =Table9[[#This Row],[المبلغ]]-Table9[[#This Row],[المدفوع]] -> 0 | E30: أكتوبر | I30: فورى لتكنولوجيا المعلومات التجارية | J30: 62180.662 | K30: 62180.662 | L30: 0 | M30: 7842.606
A31: الإيجارات القاهرة 1 | B31: 14800 | D31: =Table9[[#This Row],[المبلغ]]-Table9[[#This Row],[المدفوع]] -> 14800 | E31: نوفمبر | F31: =+Table9[[#This Row],[الباقي ]]+D32+D33+D34 -> 45000 | I31: بنك البركة مصر | J31: 22546.32 | K31: 22546.32 | L31: 0 | M31: 2843.68
A32: الإيجارات القاهرة 2 | B32: =13225+215 -> 13440 | C32: 2440 | D32: =Table9[[#This Row],[المبلغ]]-Table9[[#This Row],[المدفوع]] -> 11000 | E32: نوفمبر | I32: شركه تساهيل للتمويل | J32: 86933.292 | K32: 86933.292 | L32: 0 | M32: 10964.559
A33: الإيجارات القاهرة 3 | B33: 19200 | D33: =Table9[[#This Row],[المبلغ]]-Table9[[#This Row],[المدفوع]] -> 19200 | E33: نوفمبر | I33: شركه حالا للتمويل الاستهلاكى | J33: 59808.864 | K33: 59808.864 | L33: 0 | M33: 7543.4604
A34: الإيجارات المنصورة | B34: 5500 | C34: 5500 | D34: =Table9[[#This Row],[المبلغ]]-Table9[[#This Row],[المدفوع]] -> 0 | E34: نوفمبر | I34: شركه مشروعى للتجاره | J34: 39948.696 | K34: 39948 | L34: -0.69552632 | M34: 5038.5742
A35: ضريبة القيمة المضافة | B35: 286904.76 | D35: =Table9[[#This Row],[المبلغ]]-Table9[[#This Row],[المدفوع]] -> 286904.76 | E35: يوليو | F35: =SUM(D35:D40) -> 817446.72 | H35: Jun-25 Total | J35: 1491324.9 | K35: 1484629.5 | L35: -2220.6891 | M35: 188095.03
A36: ضريبة القيمة المضافة | B36: 200120.18 | D36: =Table9[[#This Row],[المبلغ]]-Table9[[#This Row],[المدفوع]] -> 200120.18 | E36: أغسطس | H36: 45839 | I36: بنك الإسكندرية | J36: 110907.17 | K36: 110907.17 | L36: 0 | M36: 13988.292
A37: ضريبة القيمة المضافة | B37: 168663 | D37: =Table9[[#This Row],[المبلغ]]-Table9[[#This Row],[المدفوع]] -> 168663 | E37: سبتمبر | I37: شركه رايه للالكترونيات | J37: 73190.576 | K37: 71871.827 | L37: 4.7521098e-11 | M37: 9231.2439
A38: ضريبة القيمة المضافة | B38: 161758.78 | D38: =Table9[[#This Row],[المبلغ]]-Table9[[#This Row],[المدفوع]] -> 161758.78 | E38: أكتوبر | I38: شركه رايه قانونى | J38: 611610 | K38: 611610 | L38: 0 | M38: 77140
I39: بنك كريدي اجريكول مصر | J39: 218183.9 | K39: 214252.66 | L39: -1.3187673e-11 | M39: 27518.69
I40: ميد للتقسيط | J40: 126950.31 | K40: 126950.31 | L40: 0 | M40: 16011.751
A41: كسب العمل | B41: 2500 | D41: =+Table9[[#This Row],[المبلغ]]-Table9[[#This Row],[المدفوع]] -> 2500 | E41: نوفمبر | F41: =+Table9[[#This Row],[الباقي ]] -> 2500 | I41: مانى فيللوز لتكنولوجيا المعلومات وادارة المشروعات | J41: 183534.56 | K41: 183534.56 | L41: 0 | M41: 23148.503
A42: الخصم والاضافة | B42: 1270 | C42: 1290.69 | D42: =+Table9[[#This Row],[المبلغ]]-Table9[[#This Row],[المدفوع]] -> -20.69 | E42: الربع الثاالث | F42: =+Table9[[#This Row],[الباقي ]] -> -20.69 | I42: ميد قانونى | J42: 182040 | K42: 182040 | L42: 0 | M42: 22960
A43: المساهمة التكافلية | B43: 29741.24 | D43: =+Table9[[#This Row],[المبلغ]]-Table9[[#This Row],[المدفوع]] -> 29741.24 | E43: 2024 | F43: =+Table9[[#This Row],[الباقي ]] -> 29741.24 | I43: تنميه لخدمات المشروعات متناهيه الصغر | J43: 189744 | K43: 189744 | L43: 0 | M43: 23931.676
A44: عقود الإنتاج ميد بنك | B44: 181692 | C44: 181692 | D44: =+Table9[[#This Row],[المبلغ]]-Table9[[#This Row],[المدفوع]] -> 0 | E44: سبتمبر | I44: سفن | J44: 46668.869 | K44: 46668.869 | L44: 0 | M44: 5886.1637
A45: عقود الانتاج تنمية | D45: =+Table9[[#This Row],[المبلغ]]-Table9[[#This Row],[المدفوع]] -> 0 | E45: يوليو | I45: اور للتمويل الاستهلاكى -وسيلة | J45: 77313.34 | K45: 77313.34 | L45: 0 | M45: 9751.2321
A46: عقود الانتاج ميد بنك | B46: 30181 | C46: 30181 | D46: =+Table9[[#This Row],[المبلغ]]-Table9[[#This Row],[المدفوع]] -> 0 | E46: يوليو | I46: امان لتمويل المشروعات | J46: 3330 | L46: -3330 | M46: 420
A47: عهدة فرع المنصورة | B47: 20000 | D47: =+Table9[[#This Row],[المبلغ]]-Table9[[#This Row],[المدفوع]] -> 20000 | E47: نوفمبر | I47: فورى لتكنولوجيا المعلومات التجارية | J47: 103474.26 | K47: 103474.26 | L47: 0 | M47: 13050.807
A48: كهرباء فرع القاهرة | B48: 9600 | D48: =+Table9[[#This Row],[المبلغ]]-Table9[[#This Row],[المدفوع]] -> 9600 | E48: نوفمبر | I48: بنك البركة مصر | J48: 86580 | K48: 86580 | L48: 0 | M48: 10920
A49: أدوات مكتبيه | B49: 8000 | D49: =+Table9[[#This Row],[المبلغ]]-Table9[[#This Row],[المدفوع]] -> 8000 | E49: نوفمبر | I49: شركه تساهيل للتمويل | J49: 74605.671 | K49: 74605.671 | L49: 0 | M49: 9409.7242
A50: بوفيه | B50: 6000 | D50: =+Table9[[#This Row],[المبلغ]]-Table9[[#This Row],[المدفوع]] -> 6000 | E50: نوفمبر | I50: شركه حالا للتمويل الاستهلاكى | J50: 52469.252 | K50: 52469.252 | L50: 0 | M50: 6617.7435
A51: نظافه | B51: 1000 | D51: =+Table9[[#This Row],[المبلغ]]-Table9[[#This Row],[المدفوع]] -> 1000 | E51: نوفمبر | I51: شركه مشروعى للتجاره | J51: 13449.208 | K51: 13449.208 | L51: 0 | M51: 1696.2965
A52: انترنت -اتصلات-فودافون | B52: 20000 | C52: 10596.45 | D52: =+Table9[[#This Row],[المبلغ]]-Table9[[#This Row],[المدفوع]] -> 9403.55 | E52: نوفمبر | I52: تنميه قانوني | J52: 75200.28 | K52: 75200.28 | L52: 0 | M52: 9484.72
A53: ايجار طابعه فرع القاهرة | B53: 8000 | C53: 5665 | D53: =+Table9[[#This Row],[المبلغ]]-Table9[[#This Row],[المدفوع]] -> 2335 | E53: نوفمبر | H53: Jul-25 Total | J53: 2229251.4 | K53: 2220671.4 | L53: -3330 | M53: 281166.84
A54: تامينات اجتماعيه | B54: 84673.3 | D54: =+Table9[[#This Row],[المبلغ]]-Table9[[#This Row],[المدفوع]] -> 84673.3 | E54: نوفمبر | H54: 45870 | I54: بنك الإسكندرية | J54: 317120.34 | K54: 317120.34 | L54: 0 | M54: 39997.16
A55: جمعية شركة قيمة | B55: 40000 | D55: =+Table9[[#This Row],[المبلغ]]-Table9[[#This Row],[المدفوع]] -> 40000 | E55: نوفمبر | I55: شركه رايه للالكترونيات | J55: 65060.829 | K55: 63888.562 | L55: 4.9794835e-11 | M55: 8205.8704
I56: شركه رايه قانونى | J56: 297480 | L56: -297480 | M56: 37520
I57: بنك كريدي اجريكول مصر | J57: 367140.9 | K57: 360525.75 | L57: 2.7284841e-11 | M57: 46306.06
I58: ميد للتقسيط | J58: 99376.61 | K58: 99376 | L58: -0.610025 | M58: 12533.987
I59: مانى فيللوز لتكنولوجيا المعلومات وادارة المشروعات | J59: 177192.88 | K59: 177192.88 | L59: 0 | M59: 22348.652
I60: فاليو قانونى | J60: 236763 | K60: 236763 | L60: 0 | M60: 29862
I61: بلتون للتمويل الاستهلاكى سفن | J61: 73652.697 | L61: -73652.697 | M61: 9289.5293
I62: تنميه لخدمات المشروعات متناهيه الصغر | J62: 120157.44 | K62: 120157.44 | L62: -0.0015789474 | M62: 15154.993
I63: اور للتمويل الاستهلاكى -وسيلة | J63: 75606.559 | K63: 75606.559 | L63: 0 | M63: 9535.9625
I64: اور للتمويل الاستهلاكى -وسيلة قانونى | J64: 55122.6 | K64: 55122.6 | L64: 0 | M64: 6952.4
I65: امان لتمويل المشروعات | J65: 3330 | L65: -3330 | M65: 420
I66: فورى لتكنولوجيا المعلومات التجارية | J66: 12777.648 | K66: 12777.648 | L66: 0 | M66: 1611.5953
I67: شركه تساهيل للتمويل | J67: 126389.18 | K67: 126389.18 | L67: 0 | M67: 15940.977
I68: شركه حالا للتمويل الاستهلاكى | J68: 48093.973 | K68: 48093.973 | L68: 0 | M68: 6065.9065
A69: Total | B69: =SUBTOTAL(109,Table9[المبلغ]) -> 2013908.4 | C69: =SUBTOTAL(109,Table9[المدفوع]) -> 915210.81 | D69: =SUBTOTAL(109,Table9[[الباقي ]]) -> 1098697.6 | I69: شركه مشروعى للتجاره | J69: 15198.607 | K69: 15198.607 | L69: 0 | M69: 1916.9414
I70: ميد بنك | J70: 46078.125 | K70: 46078.125 | L70: 0 | M70: 5811.6554
I71: تنميه قانوني | J71: 20523.9 | K71: 20523.9 | L71: 3.6379788e-12 | M71: 2588.6
H72: Aug-25 Total | J72: 2157065.3 | K72: 1774814.6 | L72: -374463.31 | M72: 272062.29
H73: 45901 | I73: بنك الإسكندرية | J73: 338507.61 | K73: 338507.61 | L73: 0 | M73: 42694.653
I74: شركه رايه للالكترونيات | J74: 92538.636 | L74: -90871.273 | M74: 11671.54
I75: بنك كريدي اجريكول مصر | J75: 150905.35 | K75: 148186.33 | L75: 0 | M75: 19033.107
I76: ميد للتقسيط | J76: 61061.246 | K76: 61061.246 | L76: 0 | M76: 7701.4184
I77: مانى فيللوز لتكنولوجيا المعلومات وادارة المشروعات | J77: 135658.27 | K77: 135658.27 | L77: 8.7311491e-11 | M77: 17110.052
I78: تنميه لخدمات المشروعات متناهيه الصغر | J78: 120106.05 | K78: 120106.05 | L78: 0 | M78: 15148.511
I79: سفن | J79: 106729.88 | L79: -106729.88 | M79: 13461.426
I80: اور للتمويل الاستهلاكى -وسيلة | J80: 70918.333 | L80: -70918.333 | M80: 8944.6546
I81: بنك البركة مصر | J81: 22546.32 | K81: 22546.32 | L81: 0 | M81: 2843.68
I82: شركه تساهيل للتمويل | J82: 52061.132 | K82: 52061.132 | L82: 0 | M82: 6566.2689
I83: شركه حالا للتمويل الاستهلاكى | J83: 46318.635 | K83: 46318.635 | L83: 0 | M83: 5841.99
I84: شركه مشروعى للتجاره | J84: 20274.724 | K84: 20274.724 | L84: 0 | M84: 2557.1725
I85: ميد بنك | J85: 253681.54 | K85: 253681.54 | L85: 0 | M85: 31995.87
I86: شركة إرادة لتمويل المشروعات | J86: 75930.611 | K86: 75930.611 | L86: 0 | M86: 9576.8339
I87: الكان فاينانس للخدمات المالية الحديثة | J87: 4101.45 | K87: 4101.45 | L87: 0 | M87: 517.3
H88: Sep-25 Total | J88: 1551339.8 | K88: 1278433.9 | L88: -268519.48 | M88: 195664.48
H89: 45931 | I89: بنك الإسكندرية | J89: 192322.07 | K89: 192322.07 | L89: 0 | M89: 24256.837
I90: بنك كريدي اجريكول مصر | J90: 473304.82 | K90: 464776.8 | L90: -2.3646862e-11 | M90: 59696.103
I91: مانى فيللوز لتكنولوجيا المعلومات وادارة المشروعات | J91: 100112.18 | L91: -100112.18 | M91: 12626.761
I92: تنميه لخدمات المشروعات متناهيه الصغر | J92: 199816.03 | L92: -199816.03 | M92: 25202.021
I93: سفن | J93: 35002.818 | L93: -35002.818 | M93: 4414.7698
I94: اور للتمويل الاستهلاكى -وسيلة | J94: 61185.011 | L94: -61185.011 | M94: 7717.0284
I95: سهولة قانونى | J95: 66045 | K95: 66045 | L95: 0 | M95: 8330
I96: اور للتمويل الاستهلاكى -وسيلة قانونى | J96: 389671.61 | L96: -389671.61 | M96: 49147.77
I97: بنك البركة مصر | J97: 249750 | K97: 249750 | L97: 0 | M97: 31500
I98: شركه تساهيل للتمويل | J98: 122522.49 | L98: -122522.49 | M98: 15453.287
I99: شركه حالا للتمويل الاستهلاكى | J99: 51640.997 | L99: -51640.997 | M99: 6513.2789
I100: شركه مشروعى للتجاره | J100: 8509.0361 | L100: -8509.0361 | M100: 1073.2118
...

Sheet الايرادات 
A1: مستحقات لدي الغير | S1: =TODAY() -> 46006
D2: =SUBTOTAL(9,D4:D1048576) -> 16938610 | E2: =SUBTOTAL(9,E4:E1048576) -> 14858430 | F2: =SUBTOTAL(9,F4:F1048576) -> 0 | G2: =SUBTOTAL(9,G4:G1048576) -> 0 | H2: =SUBTOTAL(9,H4:H1048576) -> 0 | I2: =SUBTOTAL(9,I4:I1048576) -> 14858430 | J2: =SUBTOTAL(9,J4:J1048576) -> 2080180.2 | K2: =SUBTOTAL(9,K4:K1048576) -> 445752.9 | ... O2: =SUBTOTAL(9,O4:O1048576) -> -761520.46
A3: العميل | B3: الشهر | C3: تاريخ اصدار الفاتورة | D3: الاجمالي بالضريبه 14% | E3: الاجمالي بدون الضريبه14% | F3: القاهرة | G3: المنصورة | H3: القانونيه | I3: اخري | J3: 14% | K3: 3% | L3: المطلوب تحويله | M3: المبلغ المسدد | N3: مصروفات | O3: المستحق | P3: تاريخ الاستحقاق | Q3: payment term | R3: الاستحقاق | S3: التاخير | T3: تاريخ السداد | U3: الايراد الفعلي -14% | V3: لينك الفاتورة الالكترونية
A4: اور للتمويل الاستهلاكى -وسيلة | B4: 45566 | C4: 45635 | D4: 30574.66 | E4: =D4/1.14 -> 26819.877 | I4: =Table8[[#This Row],[الاجمالي بدون الضريبه14%]]-Table8[[#This Row],[القاهرة ]]-Table8[[#This Row],[المنصورة ]]-Table8[[#This Row],[القانونيه ]] -> 26819.877 | J4: =D4-E4 -> 3754.7828 | K4: =E4*$K$3 -> 804.59632 | L4: =D4-K4 -> 29770.064 | M4: 29770.064 | O4: =M4-L4-N4 -> 0 | Q4: =IFERROR((Table8[[#This Row],[تاريخ الاستحقاق]]-Table8[[#This Row],[تاريخ اصدار الفاتورة ]]),0) -> -45635 | R4: =IF(Table8[[#This Row],[تاريخ الاستحقاق]]<$S$1,"مستحق","غير مستحق") -> مستحق | S4: =Table8[[#This Row],[تاريخ الاستحقاق]]-$S$1 -> -46006 | U4: =Table8[[#This Row],[المبلغ المسدد]]/1.14 -> 26114.091
A5: فاليو لخدمات البيع والتقسيط | B5: 45597 | C5: 45641 | D5: 98980.8 | E5: =D5/1.14 -> 86825.263 | I5: =Table8[[#This Row],[الاجمالي بدون الضريبه14%]]-Table8[[#This Row],[القاهرة ]]-Table8[[#This Row],[المنصورة ]]-Table8[[#This Row],[القانونيه ]] -> 86825.263 | J5: =D5-E5 -> 12155.537 | K5: =E5*$K$3 -> 2604.7579 | L5: =D5-K5 -> 96376.042 | M5: 96376.042 | O5: =M5-L5-N5 -> 0 | Q5: =IFERROR((Table8[[#This Row],[تاريخ الاستحقاق]]-Table8[[#This Row],[تاريخ اصدار الفاتورة ]]),0) -> -45641 | R5: =IF(Table8[[#This Row],[تاريخ الاستحقاق]]<$S$1,"مستحق","غير مستحق") -> مستحق | S5: =Table8[[#This Row],[تاريخ الاستحقاق]]-$S$1 -> -46006 | U5: =Table8[[#This Row],[المبلغ المسدد]]/1.14 -> 84540.388
A6: فاليو قانونى | B6: 45627 | C6: 45643 | D6: 122094 | E6: =D6/1.14 -> 107100 | I6: =Table8[[#This Row],[الاجمالي بدون الضريبه14%]]-Table8[[#This Row],[القاهرة ]]-Table8[[#This Row],[المنصورة ]]-Table8[[#This Row],[القانونيه ]] -> 107100 | J6: =D6-E6 -> 14994 | K6: =E6*$K$3 -> 3213 | L6: =D6-K6 -> 118881 | M6: 118881 | O6: =M6-L6-N6 -> 0 | Q6: =IFERROR((Table8[[#This Row],[تاريخ الاستحقاق]]-Table8[[#This Row],[تاريخ اصدار الفاتورة ]]),0) -> -45643 | R6: =IF(Table8[[#This Row],[تاريخ الاستحقاق]]<$S$1,"مستحق","غير مستحق") -> مستحق | S6: =Table8[[#This Row],[تاريخ الاستحقاق]]-$S$1 -> -46006 | U6: =Table8[[#This Row],[المبلغ المسدد]]/1.14 -> 104281.58
A7: فاليو | B7: 45627 | C7: 45648 | D7: 364000.01 | E7: =D7/1.14 -> 319298.25 | I7: =Table8[[#This Row],[الاجمالي بدون الضريبه14%]]-Table8[[#This Row],[القاهرة ]]-Table8[[#This Row],[المنصورة ]]-Table8[[#This Row],[القانونيه ]] -> 319298.25 | J7: =D7-E7 -> 44701.756 | K7: =E7*$K$3 -> 9578.9476 | L7: =D7-K7 -> 354421.06 | O7: =M7-L7-N7 -> -354421.06 | Q7: =IFERROR((Table8[[#This Row],[تاريخ الاستحقاق]]-Table8[[#This Row],[تاريخ اصدار الفاتورة ]]),0) -> -45648 | R7: =IF(Table8[[#This Row],[تاريخ الاستحقاق]]<$S$1,"مستحق","غير مستحق") -> مستحق | S7: =Table8[[#This Row],[تاريخ الاستحقاق]]-$S$1 -> -46006 | U7: =Table8[[#This Row],[المبلغ المسدد]]/1.14 -> 0
A8: فاليو | B8: 45627 | C8: 45648 | D8: 201210 | E8: =D8/1.14 -> 176500 | I8: =Table8[[#This Row],[الاجمالي بدون الضريبه14%]]-Table8[[#This Row],[القاهرة ]]-Table8[[#This Row],[المنصورة ]]-Table8[[#This Row],[القانونيه ]] -> 176500 | J8: =D8-E8 -> 24710 | K8: =E8*$K$3 -> 5295 | L8: =D8-K8 -> 195915 | M8: 195915 | O8: =M8-L8-N8 -> 0 | Q8: =IFERROR((Table8[[#This Row],[تاريخ الاستحقاق]]-Table8[[#This Row],[تاريخ اصدار الفاتورة ]]),0) -> -45648 | R8: =IF(Table8[[#This Row],[تاريخ الاستحقاق]]<$S$1,"مستحق","غير مستحق") -> مستحق | S8: =Table8[[#This Row],[تاريخ الاستحقاق]]-$S$1 -> -46006 | U8: =Table8[[#This Row],[المبلغ المسدد]]/1.14 -> 171855.26
A9: ميد للتقسيط | B9: 45597 | C9: 45649 | D9: 35142.79 | E9: =D9/1.14 -> 30827.009 | I9: =Table8[[#This Row],[الاجمالي بدون الضريبه14%]]-Table8[[#This Row],[القاهرة ]]-Table8[[#This Row],[المنصورة ]]-Table8[[#This Row],[القانونيه ]] -> 30827.009 | J9: =D9-E9 -> 4315.7812 | K9: =E9*$K$3 -> 924.81026 | L9: =D9-K9 -> 34217.98 | M9: 34217.98 | O9: =M9-L9-N9 -> 0 | Q9: =IFERROR((Table8[[#This Row],[تاريخ الاستحقاق]]-Table8[[#This Row],[تاريخ اصدار الفاتورة ]]),0) -> -45649 | R9: =IF(Table8[[#This Row],[تاريخ الاستحقاق]]<$S$1,"مستحق","غير مستحق") -> مستحق | S9: =Table8[[#This Row],[تاريخ الاستحقاق]]-$S$1 -> -46006 | U9: =Table8[[#This Row],[المبلغ المسدد]]/1.14 -> 30015.772
A10: بى ام للتمويل الاستهلاكى | B10: 45597 | C10: 45649 | D10: 358197.59 | E10: =D10/1.14 -> 314208.41 | I10: =Table8[[#This Row],[الاجمالي بدون الضريبه14%]]-Table8[[#This Row],[القاهرة ]]-Table8[[#This Row],[المنصورة ]]-Table8[[#This Row],[القانونيه ]] -> 314208.41 | J10: =D10-E10 -> 43989.178 | K10: =E10*$K$3 -> 9426.2524 | L10: =D10-K10 -> 348771.34 | M10: 348771.34 | O10: =M10-L10-N10 -> 0 | Q10: =IFERROR((Table8[[#This Row],[تاريخ الاستحقاق]]-Table8[[#This Row],[تاريخ اصدار الفاتورة ]]),0) -> -45649 | R10: =IF(Table8[[#This Row],[تاريخ الاستحقاق]]<$S$1,"مستحق","غير مستحق") -> مستحق | S10: =Table8[[#This Row],[تاريخ الاستحقاق]]-$S$1 -> -46006 | U10: =Table8[[#This Row],[المبلغ المسدد]]/1.14 -> 305939.77
A11: سفن | B11: 45566 | C11: 45650 | D11: 16691.91 | E11: =D11/1.14 -> 14642.026 | I11: =Table8[[#This Row],[الاجمالي بدون الضريبه14%]]-Table8[[#This Row],[القاهرة ]]-Table8[[#This Row],[المنصورة ]]-Table8[[#This Row],[القانونيه ]] -> 14642.026 | J11: =D11-E11 -> 2049.8837 | K11: =E11*$K$3 -> 439.26079 | L11: =D11-K11 -> 16252.649 | M11: 16252.649 | O11: =M11-L11-N11 -> 0 | Q11: =IFERROR((Table8[[#This Row],[تاريخ الاستحقاق]]-Table8[[#This Row],[تاريخ اصدار الفاتورة ]]),0) -> -45650 | R11: =IF(Table8[[#This Row],[تاريخ الاستحقاق]]<$S$1,"مستحق","غير مستحق") -> مستحق | S11: =Table8[[#This Row],[تاريخ الاستحقاق]]-$S$1 -> -46006 | U11: =Table8[[#This Row],[المبلغ المسدد]]/1.14 -> 14256.71
A12: ميد قانونى | B12: 45536 | C12: 45652 | D12: 42616.05 | E12: =D12/1.14 -> 37382.5 | I12: =Table8[[#This Row],[الاجمالي بدون الضريبه14%]]-Table8[[#This Row],[القاهرة ]]-Table8[[#This Row],[المنصورة ]]-Table8[[#This Row],[القانونيه ]] -> 37382.5 | J12: =D12-E12 -> 5233.55 | K12: =E12*$K$3 -> 1121.475 | L12: =D12-K12 -> 41494.575 | M12: 41494.575 | O12: =M12-L12-N12 -> 0 | Q12: =IFERROR((Table8[[#This Row],[تاريخ الاستحقاق]]-Table8[[#This Row],[تاريخ اصدار الفاتورة ]]),0) -> -45652 | R12: =IF(Table8[[#This Row],[تاريخ الاستحقاق]]<$S$1,"مستحق","غير مستحق") -> مستحق | S12: =Table8[[#This Row],[تاريخ الاستحقاق]]-$S$1 -> -46006 | U12: =Table8[[#This Row],[المبلغ المسدد]]/1.14 -> 36398.75
A13: مانى فيللوز لتكنولوجيا المعلومات وادارة المشروعات | B13: 45597 | C13: 45656 | D13: 114176.28 | E13: =D13/1.14 -> 100154.63 | I13: =Table8[[#This Row],[الاجمالي بدون الضريبه14%]]-Table8[[#This Row],[القاهرة ]]-Table8[[#This Row],[المنصورة ]]-Table8[[#This Row],[القانونيه ]] -> 100154.63 | J13: =D13-E13 -> 14021.648 | K13: =E13*$K$3 -> 3004.6389 | L13: =D13-K13 -> 111171.64 | M13: 111171.64 | O13: =M13-L13-N13 -> 0 | Q13: =IFERROR((Table8[[#This Row],[تاريخ الاستحقاق]]-Table8[[#This Row],[تاريخ اصدار الفاتورة ]]),0) -> -45656 | R13: =IF(Table8[[#This Row],[تاريخ الاستحقاق]]<$S$1,"مستحق","غير مستحق") -> مستحق | S13: =Table8[[#This Row],[تاريخ الاستحقاق]]-$S$1 -> -46006 | U13: =Table8[[#This Row],[المبلغ المسدد]]/1.14 -> 97518.983
A14: فاليو لخدمات البيع والتقسيط | B14: 45627 | C14: 45658 | D14: 168615.72 | E14: =D14/1.14 -> 147908.53 | I14: =Table8[[#This Row],[الاجمالي بدون الضريبه14%]]-Table8[[#This Row],[القاهرة ]]-Table8[[#This Row],[المنصورة ]]-Table8[[#This Row],[القانونيه ]] -> 147908.53 | J14: =D14-E14 -> 20707.194 | K14: =E14*$K$3 -> 4437.2558 | L14: =D14-K14 -> 164178.46 | M14: 164178.46 | O14: =M14-L14-N14 -> 0 | Q14: =IFERROR((Table8[[#This Row],[تاريخ الاستحقاق]]-Table8[[#This Row],[تاريخ اصدار الفاتورة ]]),0) -> -45658 | R14: =IF(Table8[[#This Row],[تاريخ الاستحقاق]]<$S$1,"مستحق","غير مستحق") -> مستحق | S14: =Table8[[#This Row],[تاريخ الاستحقاق]]-$S$1 -> -46006 | U14: =Table8[[#This Row],[المبلغ المسدد]]/1.14 -> 144016.2
A15: شركه رايه للالكترونيات | B15: 45627 | C15: 45663 | D15: 108900.53 | E15: =D15/1.14 -> 95526.781 | I15: =Table8[[#This Row],[الاجمالي بدون الضريبه14%]]-Table8[[#This Row],[القاهرة ]]-Table8[[#This Row],[المنصورة ]]-Table8[[#This Row],[القانونيه ]] -> 95526.781 | J15: =D15-E15 -> 13373.749 | K15: =E15*$K$3 -> 2865.8034 | L15: =D15-K15 -> 106034.73 | M15: =+Table8[[#This Row],[المطلوب تحويله ]]+Table8[[#This Row],[مصروفات ]] -> 104124.19 | N15: =-Table8[[#This Row],[الاجمالي بدون الضريبه14%]]*0.02 -> -1910.5356 | O15: =M15-L15-N15 -> -4.3200998e-12 | Q15: =IFERROR((Table8[[#This Row],[تاريخ الاستحقاق]]-Table8[[#This Row],[تاريخ اصدار الفاتورة ]]),0) -> -45663 | R15: =IF(Table8[[#This Row],[تاريخ الاستحقاق]]<$S$1,"مستحق","غير مستحق") -> مستحق | S15: =Table8[[#This Row],[تاريخ الاستحقاق]]-$S$1 -> -46006 | U15: =Table8[[#This Row],[المبلغ المسدد]]/1.14 -> 91337.01
A16: سفن | B16: 45597 | C16: 45665 | D16: 32130.6 | E16: =D16/1.14 -> 28184.737 | I16: =Table8[[#This Row],[الاجمالي بدون الضريبه14%]]-Table8[[#This Row],[القاهرة ]]-Table8[[#This Row],[المنصورة ]]-Table8[[#This Row],[القانونيه ]] -> 28184.737 | J16: =D16-E16 -> 3945.8632 | K16: =E16*$K$3 -> 845.54211 | L16: =D16-K16 -> 31285.058 | M16: 31285.058 | O16: =M16-L16-N16 -> 0 | Q16: =IFERROR((Table8[[#This Row],[تاريخ الاستحقاق]]-Table8[[#This Row],[تاريخ اصدار الفاتورة ]]),0) -> -45665 | R16: =IF(Table8[[#This Row],[تاريخ الاستحقاق]]<$S$1,"مستحق","غير مستحق") -> مستحق | S16: =Table8[[#This Row],[تاريخ الاستحقاق]]-$S$1 -> -46006 | U16: =Table8[[#This Row],[المبلغ المسدد]]/1.14 -> 27443.033
A17: بنك كريدي اجريكول مصر | B17: 45627 | C17: 45671 | D17: 355629.84 | E17: =D17/1.14 -> 311956 | I17: =Table8[[#This Row],[الاجمالي بدون الضريبه14%]]-Table8[[#This Row],[القاهرة ]]-Table8[[#This Row],[المنصورة ]]-Table8[[#This Row],[القانونيه ]] -> 311956 | J17: =D17-E17 -> 43673.84 | K17: =E17*$K$3 -> 9358.68 | L17: =D17-K17 -> 346271.16 | M17: 340032.04 | N17: =-Table8[[#This Row],[الاجمالي بدون الضريبه14%]]*0.02 -> -6239.12 | O17: =M17-L17-N17 -> -5.1841198e-11 | Q17: =IFERROR((Table8[[#This Row],[تاريخ الاستحقاق]]-Table8[[#This Row],[تاريخ اصدار الفاتورة ]]),0) -> -45671 | R17: =IF(Table8[[#This Row],[تاريخ الاستحقاق]]<$S$1,"مستحق","غير مستحق") -> مستحق | S17: =Table8[[#This Row],[تاريخ الاستحقاق]]-$S$1 -> -46006 | U17: =Table8[[#This Row],[المبلغ المسدد]]/1.14 -> 298273.72
A18: بنك الإسكندرية | B18: 45627 | C18: 45671 | D18: 83502.13 | E18: =D18/1.14 -> 73247.482 | I18: =Table8[[#This Row],[الاجمالي بدون الضريبه14%]]-Table8[[#This Row],[القاهرة ]]-Table8[[#This Row],[المنصورة ]]-Table8[[#This Row],[القانونيه ]] -> 73247.482 | J18: =D18-E18 -> 10254.648 | K18: =E18*$K$3 -> 2197.4245 | L18: =D18-K18 -> 81304.706 | M18: 81304.706 | O18: =M18-L18-N18 -> 0 | Q18: =IFERROR((Table8[[#This Row],[تاريخ الاستحقاق]]-Table8[[#This Row],[تاريخ اصدار الفاتورة ]]),0) -> -45671 | R18: =IF(Table8[[#This Row],[تاريخ الاستحقاق]]<$S$1,"مستحق","غير مستحق") -> مستحق | S18: =Table8[[#This Row],[تاريخ الاستحقاق]]-$S$1 -> -46006 | U18: =Table8[[#This Row],[المبلغ المسدد]]/1.14 -> 71319.917
A19: مانى فيللوز لتكنولوجيا المعلومات وادارة المشروعات | B19: 45627 | C19: 45671 | D19: 133733.58 | E19: =D19/1.14 -> 117310.16 | I19: =Table8[[#This Row],[الاجمالي بدون الضريبه14%]]-Table8[[#This Row],[القاهرة ]]-Table8[[#This Row],[المنصورة ]]-Table8[[#This Row],[القانونيه ]] -> 117310.16 | J19: =D19-E19 -> 16423.422 | K19: =E19*$K$3 -> 3519.3047 | L19: =D19-K19 -> 130214.28 | M19: 133733.58 | O19: =M19-L19-N19 -> 3519.3047 | Q19: =IFERROR((Table8[[#This Row],[تاريخ الاستحقاق]]-Table8[[#This Row],[تاريخ اصدار الفاتورة ]]),0) -> -45671 | R19: =IF(Table8[[#This Row],[تاريخ الاستحقاق]]<$S$1,"مستحق","غير مستحق") -> مستحق | S19: =Table8[[#This Row],[تاريخ الاستحقاق]]-$S$1 -> -46006 | U19: =Table8[[#This Row],[المبلغ المسدد]]/1.14 -> 117310.16
A20: بى ام للتمويل الاستهلاكى | B20: 45627 | C20: 45672 | D20: 68483.2 | E20: =D20/1.14 -> 60072.982 | I20: =Table8[[#This Row],[الاجمالي بدون الضريبه14%]]-Table8[[#This Row],[القاهرة ]]-Table8[[#This Row],[المنصورة ]]-Table8[[#This Row],[القانونيه ]] -> 60072.982 | J20: =D20-E20 -> 8410.2175 | K20: =E20*$K$3 -> 1802.1895 | L20: =D20-K20 -> 66681.011 | M20: 66681.011 | O20: =M20-L20-N20 -> 0 | Q20: =IFERROR((Table8[[#This Row],[تاريخ الاستحقاق]]-Table8[[#This Row],[تاريخ اصدار الفاتورة ]]),0) -> -45672 | R20: =IF(Table8[[#This Row],[تاريخ الاستحقاق]]<$S$1,"مستحق","غير مستحق") -> مستحق | S20: =Table8[[#This Row],[تاريخ الاستحقاق]]-$S$1 -> -46006 | U20: =Table8[[#This Row],[المبلغ المسدد]]/1.14 -> 58492.114
A21: تنميه لخدمات المشروعات متناهيه الصغر | B21: 45597 | C21: 45677 | D21: 125671.25 | E21: =D21/1.14 -> 110237.94 | I21: =Table8[[#This Row],[الاجمالي بدون الضريبه14%]]-Table8[[#This Row],[القاهرة ]]-Table8[[#This Row],[المنصورة ]]-Table8[[#This Row],[القانونيه ]] -> 110237.94 | J21: =D21-E21 -> 15433.311 | K21: =E21*$K$3 -> 3307.1382 | L21: =D21-K21 -> 122364.11 | M21: 122364.11 | O21: =M21-L21-N21 -> -0.0018421053 | Q21: =IFERROR((Table8[[#This Row],[تاريخ الاستحقاق]]-Table8[[#This Row],[تاريخ اصدار الفاتورة ]]),0) -> -45677 | R21: =IF(Table8[[#This Row],[تاريخ الاستحقاق]]<$S$1,"مستحق","غير مستحق") -> مستحق | S21: =Table8[[#This Row],[تاريخ الاستحقاق]]-$S$1 -> -46006 | U21: =Table8[[#This Row],[المبلغ المسدد]]/1.14 -> 107336.94
A22: سفن | B22: 45627 | C22: 45685 | D22: 21097.95 | E22: =D22/1.14 -> 18506.974 | I22: =Table8[[#This Row],[الاجمالي بدون الضريبه14%]]-Table8[[#This Row],[القاهرة ]]-Table8[[#This Row],[المنصورة ]]-Table8[[#This Row],[القانونيه ]] -> 18506.974 | J22: =D22-E22 -> 2590.9763 | K22: =E22*$K$3 -> 555.20921 | L22: =D22-K22 -> 20542.741 | M22: 20542.741 | O22: =M22-L22-N22 -> 0 | Q22: =IFERROR((Table8[[#This Row],[تاريخ الاستحقاق]]-Table8[[#This Row],[تاريخ اصدار الفاتورة ]]),0) -> -45685 | R22: =IF(Table8[[#This Row],[تاريخ الاستحقاق]]<$S$1,"مستحق","غير مستحق") -> مستحق | S22: =Table8[[#This Row],[تاريخ الاستحقاق]]-$S$1 -> -46006 | U22: =Table8[[#This Row],[المبلغ المسدد]]/1.14 -> 18019.948
A23: اور للتمويل الاستهلاكى -وسيلة | B23: 45597 | C23: 45686 | D23: 35781.37 | E23: =D23/1.14 -> 31387.167 | I23: =Table8[[#This Row],[الاجمالي بدون الضريبه14%]]-Table8[[#This Row],[القاهرة ]]-Table8[[#This Row],[المنصورة ]]-Table8[[#This Row],[القانونيه ]] -> 31387.167 | J23: =D23-E23 -> 4394.2033 | K23: =E23*$K$3 -> 941.615 | L23: =D23-K23 -> 34839.755 | M23: 34839.755 | O23: =M23-L23-N23 -> 0 | Q23: =IFERROR((Table8[[#This Row],[تاريخ الاستحقاق]]-Table8[[#This Row],[تاريخ اصدار الفاتورة ]]),0) -> -45686 | R23: =IF(Table8[[#This Row],[تاريخ الاستحقاق]]<$S$1,"مستحق","غير مستحق") -> مستحق | S23: =Table8[[#This Row],[تاريخ الاستحقاق]]-$S$1 -> -46006 | U23: =Table8[[#This Row],[المبلغ المسدد]]/1.14 -> 30561.189
A24: اور للتمويل الاستهلاكى -وسيلة | B24: 45627 | C24: 45686 | D24: 44975.82 | E24: =D24/1.14 -> 39452.474 | I24: =Table8[[#This Row],[الاجمالي بدون الضريبه14%]]-Table8[[#This Row],[القاهرة ]]-Table8[[#This Row],[المنصورة ]]-Table8[[#This Row],[القانونيه ]] -> 39452.474 | J24: =D24-E24 -> 5523.3463 | K24: =E24*$K$3 -> 1183.5742 | L24: =D24-K24 -> 43792.246 | M24: 43792.246 | O24: =M24-L24-N24 -> 0 | Q24: =IFERROR((Table8[[#This Row],[تاريخ الاستحقاق]]-Table8[[#This Row],[تاريخ اصدار الفاتورة ]]),0) -> -45686 | R24: =IF(Table8[[#This Row],[تاريخ الاستحقاق]]<$S$1,"مستحق","غير مستحق") -> مستحق | S24: =Table8[[#This Row],[تاريخ الاستحقاق]]-$S$1 -> -46006 | U24: =Table8[[#This Row],[المبلغ المسدد]]/1.14 -> 38414.251
A25: ميد للتقسيط | B25: 45627 | C25: 45696 | D25: 31430.58 | E25: =D25/1.14 -> 27570.684 | I25: =Table8[[#This Row],[الاجمالي بدون الضريبه14%]]-Table8[[#This Row],[القاهرة ]]-Table8[[#This Row],[المنصورة ]]-Table8[[#This Row],[القانونيه ]] -> 27570.684 | J25: =D25-E25 -> 3859.8958 | K25: =E25*$K$3 -> 827.12053 | L25: =D25-K25 -> 30603.459 | M25: 30603.47 | O25: =M25-L25-N25 -> 0.010526316 | Q25: =IFERROR((Table8[[#This Row],[تاريخ الاستحقاق]]-Table8[[#This Row],[تاريخ اصدار الفاتورة ]]),0) -> -45696 | R25: =IF(Table8[[#This Row],[تاريخ الاستحقاق]]<$S$1,"مستحق","غير مستحق") -> مستحق | S25: =Table8[[#This Row],[تاريخ الاستحقاق]]-$S$1 -> -46006 | U25: =Table8[[#This Row],[المبلغ المسدد]]/1.14 -> 26845.149
A26: تنميه لخدمات المشروعات متناهيه الصغر | B26: 45627 | C26: 45697 | D26: 168413.43 | E26: =D26/1.14 -> 147731.08 | I26: =Table8[[#This Row],[الاجمالي بدون الضريبه14%]]-Table8[[#This Row],[القاهرة ]]-Table8[[#This Row],[المنصورة ]]-Table8[[#This Row],[القانونيه ]] -> 147731.08 | J26: =D26-E26 -> 20682.351 | K26: =E26*$K$3 -> 4431.9324 | L26: =D26-K26 -> 163981.5 | M26: 163981.5 | O26: =M26-L26-N26 -> 0 | Q26: =IFERROR((Table8[[#This Row],[تاريخ الاستحقاق]]-Table8[[#This Row],[تاريخ اصدار الفاتورة ]]),0) -> -45697 | R26: =IF(Table8[[#This Row],[تاريخ الاستحقاق]]<$S$1,"مستحق","غير مستحق") -> مستحق | S26: =Table8[[#This Row],[تاريخ الاستحقاق]]-$S$1 -> -46006 | U26: =Table8[[#This Row],[المبلغ المسدد]]/1.14 -> 143843.42
A27: شركه رايه للالكترونيات | B27: 45658 | C27: 45697 | D27: 76472.11 | E27: =D27/1.14 -> 67080.798 | I27: =Table8[[#This Row],[الاجمالي بدون الضريبه14%]]-Table8[[#This Row],[القاهرة ]]-Table8[[#This Row],[المنصورة ]]-Table8[[#This Row],[القانونيه ]] -> 67080.798 | J27: =D27-E27 -> 9391.3118 | K27: =E27*$K$3 -> 2012.4239 | L27: =D27-K27 -> 74459.686 | M27: 73118.07 | N27: =-Table8[[#This Row],[الاجمالي بدون الضريبه14%]]*0.02 -> -1341.616 | O27: =M27-L27-N27 -> -4.5474735e-12 | Q27: =IFERROR((Table8[[#This Row],[تاريخ الاستحقاق]]-Table8[[#This Row],[تاريخ اصدار الفاتورة ]]),0) -> -45697 | R27: =IF(Table8[[#This Row],[تاريخ الاستحقاق]]<$S$1,"مستحق","غير مستحق") -> مستحق | S27: =Table8[[#This Row],[تاريخ الاستحقاق]]-$S$1 -> -46006 | U27: =Table8[[#This Row],[المبلغ المسدد]]/1.14 -> 64138.658
A28: بنك كريدي اجريكول مصر | B28: 45658 | C28: 45698 | D28: 140469.98 | E28: =D28/1.14 -> 123219.28 | I28: =Table8[[#This Row],[الاجمالي بدون الضريبه14%]]-Table8[[#This Row],[القاهرة ]]-Table8[[#This Row],[المنصورة ]]-Table8[[#This Row],[القانونيه ]] -> 123219.28 | J28: =D28-E28 -> 17250.699 | K28: =E28*$K$3 -> 3696.5784 | L28: =D28-K28 -> 136773.4 | M28: 134309.02 | N28: =-Table8[[#This Row],[الاجمالي بدون الضريبه14%]]*0.02 -> -2464.3856 | O28: =M28-L28-N28 -> -1.0004442e-11 | Q28: =IFERROR((Table8[[#This Row],[تاريخ الاستحقاق]]-Table8[[#This Row],[تاريخ اصدار الفاتورة ]]),0) -> -45698 | R28: =IF(Table8[[#This Row],[تاريخ الاستحقاق]]<$S$1,"مستحق","غير مستحق") -> مستحق | S28: =Table8[[#This Row],[تاريخ الاستحقاق]]-$S$1 -> -46006 | U28: =Table8[[#This Row],[المبلغ المسدد]]/1.14 -> 117814.93
A29: بنك الإسكندرية | B29: 45658 | C29: 45700 | D29: 75749.22 | E29: =D29/1.14 -> 66446.684 | I29: =Table8[[#This Row],[الاجمالي بدون الضريبه14%]]-Table8[[#This Row],[القاهرة ]]-Table8[[#This Row],[المنصورة ]]-Table8[[#This Row],[القانونيه ]] -> 66446.684 | J29: =D29-E29 -> 9302.5358 | K29: =E29*$K$3 -> 1993.4005 | L29: =D29-K29 -> 73755.819 | M29: 73755.819 | O29: =M29-L29-N29 -> 0 | Q29: =IFERROR((Table8[[#This Row],[تاريخ الاستحقاق]]-Table8[[#This Row],[تاريخ اصدار الفاتورة ]]),0) -> -45700 | R29: =IF(Table8[[#This Row],[تاريخ الاستحقاق]]<$S$1,"مستحق","غير مستحق") -> مستحق | S29: =Table8[[#This Row],[تاريخ الاستحقاق]]-$S$1 -> -46006 | U29: =Table8[[#This Row],[المبلغ المسدد]]/1.14 -> 64698.087
A30: بى ام للتمويل الاستهلاكى | B30: 45658 | C30: 45705 | D30: 71142.72 | E30: =D30/1.14 -> 62405.895 | I30: =Table8[[#This Row],[الاجمالي بدون الضريبه14%]]-Table8[[#This Row],[القاهرة ]]-Table8[[#This Row],[المنصورة ]]-Table8[[#This Row],[القانونيه ]] -> 62405.895 | J30: =D30-E30 -> 8736.8253 | K30: =E30*$K$3 -> 1872.1768 | L30: =D30-K30 -> 69270.543 | M30: 69270.543 | O30: =M30-L30-N30 -> 0 | Q30: =IFERROR((Table8[[#This Row],[تاريخ الاستحقاق]]-Table8[[#This Row],[تاريخ اصدار الفاتورة ]]),0) -> -45705 | R30: =IF(Table8[[#This Row],[تاريخ الاستحقاق]]<$S$1,"مستحق","غير مستحق") -> مستحق | S30: =Table8[[#This Row],[تاريخ الاستحقاق]]-$S$1 -> -46006 | U30: =Table8[[#This Row],[المبلغ المسدد]]/1.14 -> 60763.634
A31: مانى فيللوز لتكنولوجيا المعلومات وادارة المشروعات | B31: 45658 | C31: 45708 | D31: 156782.6 | E31: =D31/1.14 -> 137528.6 | I31: =Table8[[#This Row],[الاجمالي بدون الضريبه14%]]-Table8[[#This Row],[القاهرة ]]-Table8[[#This Row],[المنصورة ]]-Table8[[#This Row],[القانونيه ]] -> 137528.6 | J31: =D31-E31 -> 19254.004 | K31: =E31*$K$3 -> 4125.8579 | L31: =D31-K31 -> 152656.74 | M31: 152656.75 | O31: =M31-L31-N31 -> 0.0078947368 | Q31: =IFERROR((Table8[[#This Row],[تاريخ الاستحقاق]]-Table8[[#This Row],[تاريخ اصدار الفاتورة ]]),0) -> -45708 | R31: =IF(Table8[[#This Row],[تاريخ الاستحقاق]]<$S$1,"مستحق","غير مستحق") -> مستحق | S31: =Table8[[#This Row],[تاريخ الاستحقاق]]-$S$1 -> -46006 | U31: =Table8[[#This Row],[المبلغ المسدد]]/1.14 -> 133909.43
A32: شركه رايه قانونى | B32: 45658 | C32: 45708 | D32: 197277 | E32: =D32/1.14 -> 173050 | I32: =Table8[[#This Row],[الاجمالي بدون الضريبه14%]]-Table8[[#This Row],[القاهرة ]]-Table8[[#This Row],[المنصورة ]]-Table8[[#This Row],[القانونيه ]] -> 173050 | J32: =D32-E32 -> 24227 | K32: =E32*$K$3 -> 5191.5 | L32: =D32-K32 -> 192085.5 | M32: 192085.5 | O32: =M32-L32-N32 -> 0 | Q32: =IFERROR((Table8[[#This Row],[تاريخ الاستحقاق]]-Table8[[#This Row],[تاريخ اصدار الفاتورة ]]),0) -> -45708 | R32: =IF(Table8[[#This Row],[تاريخ الاستحقاق]]<$S$1,"مستحق","غير مستحق") -> مستحق | S32: =Table8[[#This Row],[تاريخ الاستحقاق]]-$S$1 -> -46006 | U32: =Table8[[#This Row],[المبلغ المسدد]]/1.14 -> 168496.05
A33: ميد للتقسيط | B33: 45658 | C33: 45711 | D33: 31904.686 | E33: =D33/1.14 -> 27986.567 | I33: =Table8[[#This Row],[الاجمالي بدون الضريبه14%]]-Table8[[#This Row],[القاهرة ]]-Table8[[#This Row],[المنصورة ]]-Table8[[#This Row],[القانونيه ]] -> 27986.567 | J33: =D33-E33 -> 3918.1193 | K33: =E33*$K$3 -> 839.597 | L33: =D33-K33 -> 31065.089 | M33: 31065.089 | O33: =M33-L33-N33 -> 0 | Q33: =IFERROR((Table8[[#This Row],[تاريخ الاستحقاق]]-Table8[[#This Row],[تاريخ اصدار الفاتورة ]]),0) -> -45711 | R33: =IF(Table8[[#This Row],[تاريخ الاستحقاق]]<$S$1,"مستحق","غير مستحق") -> مستحق | S33: =Table8[[#This Row],[تاريخ الاستحقاق]]-$S$1 -> -46006 | U33: =Table8[[#This Row],[المبلغ المسدد]]/1.14 -> 27250.078
A34: فاليو لخدمات البيع والتقسيط | B34: 45658 | C34: 45711 | D34: 156576.52 | E34: =D34/1.14 -> 137347.82 | I34: =Table8[[#This Row],[الاجمالي بدون الضريبه14%]]-Table8[[#This Row],[القاهرة ]]-Table8[[#This Row],[المنصورة ]]-Table8[[#This Row],[القانونيه ]] -> 137347.82 | J34: =D34-E34 -> 19228.695 | K34: =E34*$K$3 -> 4120.4347 | L34: =D34-K34 -> 152456.09 | M34: 152456.09 | O34: =M34-L34-N34 -> 0 | Q34: =IFERROR((Table8[[#This Row],[تاريخ الاستحقاق]]-Table8[[#This Row],[تاريخ اصدار الفاتورة ]]),0) -> -45711 | R34: =IF(Table8[[#This Row],[تاريخ الاستحقاق]]<$S$1,"مستحق","غير مستحق") -> مستحق | S34: =Table8[[#This Row],[تاريخ الاستحقاق]]-$S$1 -> -46006 | U34: =Table8[[#This Row],[المبلغ المسدد]]/1.14 -> 133733.41
A35: فاليو | B35: 45658 | C35: 45712 | D35: 135090 | E35: =D35/1.14 -> 118500 | I35: =Table8[[#This Row],[الاجمالي بدون الضريبه14%]]-Table8[[#This Row],[القاهرة ]]-Table8[[#This Row],[المنصورة ]]-Table8[[#This Row],[القانونيه ]] -> 118500 | J35: =D35-E35 -> 16590 | K35: =E35*$K$3 -> 3555 | L35: =D35-K35 -> 131535 | M35: 131535 | O35: =M35-L35-N35 -> 0 | Q35: =IFERROR((Table8[[#This Row],[تاريخ الاستحقاق]]-Table8[[#This Row],[تاريخ اصدار الفاتورة ]]),0) -> -45712 | R35: =IF(Table8[[#This Row],[تاريخ الاستحقاق]]<$S$1,"مستحق","غير مستحق") -> مستحق | S35: =Table8[[#This Row],[تاريخ الاستحقاق]]-$S$1 -> -46006 | U35: =Table8[[#This Row],[المبلغ المسدد]]/1.14 -> 115381.58
A36: شهرى للتمويل الاستهلاكى | B36: 45658 | C36: 45712 | D36: 22800 | E36: =D36/1.14 -> 20000 | I36: =Table8[[#This Row],[الاجمالي بدون الضريبه14%]]-Table8[[#This Row],[القاهرة ]]-Table8[[#This Row],[المنصورة ]]-Table8[[#This Row],[القانونيه ]] -> 20000 | J36: =D36-E36 -> 2800 | K36: =E36*$K$3 -> 600 | L36: =D36-K36 -> 22200 | M36: 22200 | O36: =M36-L36-N36 -> 0 | Q36: =IFERROR((Table8[[#This Row],[تاريخ الاستحقاق]]-Table8[[#This Row],[تاريخ اصدار الفاتورة ]]),0) -> -45712 | R36: =IF(Table8[[#This Row],[تاريخ الاستحقاق]]<$S$1,"مستحق","غير مستحق") -> مستحق | S36: =Table8[[#This Row],[تاريخ الاستحقاق]]-$S$1 -> -46006 | U36: =Table8[[#This Row],[المبلغ المسدد]]/1.14 -> 19473.684
A37: اور للتمويل الاستهلاكى -وسيلة | B37: 45658 | C37: 45720 | D37: 41256.02 | E37: =D37/1.14 -> 36189.491 | I37: =Table8[[#This Row],[الاجمالي بدون الضريبه14%]]-Table8[[#This Row],[القاهرة ]]-Table8[[#This Row],[المنصورة ]]-Table8[[#This Row],[القانونيه ]] -> 36189.491 | J37: =D37-E37 -> 5066.5288 | K37: =E37*$K$3 -> 1085.6847 | L37: =D37-K37 -> 40170.335 | M37: 40170.335 | O37: =M37-L37-N37 -> 0 | Q37: =IFERROR((Table8[[#This Row],[تاريخ الاستحقاق]]-Table8[[#This Row],[تاريخ اصدار الفاتورة ]]),0) -> -45720 | R37: =IF(Table8[[#This Row],[تاريخ الاستحقاق]]<$S$1,"مستحق","غير مستحق") -> مستحق | S37: =Table8[[#This Row],[تاريخ الاستحقاق]]-$S$1 -> -46006 | U37: =Table8[[#This Row],[المبلغ المسدد]]/1.14 -> 35237.136
A38: تنميه لخدمات المشروعات متناهيه الصغر | B38: 45658 | C38: 45720 | D38: 167226.57 | E38: =D38/1.14 -> 146689.97 | I38: =Table8[[#This Row],[الاجمالي بدون الضريبه14%]]-Table8[[#This Row],[القاهرة ]]-Table8[[#This Row],[المنصورة ]]-Table8[[#This Row],[القانونيه ]] -> 146689.97 | J38: =D38-E38 -> 20536.596 | K38: =E38*$K$3 -> 4400.6992 | L38: =D38-K38 -> 162825.87 | M38: 162825.87 | O38: =M38-L38-N38 -> 0 | Q38: =IFERROR((Table8[[#This Row],[تاريخ الاستحقاق]]-Table8[[#This Row],[تاريخ اصدار الفاتورة ]]),0) -> -45720 | R38: =IF(Table8[[#This Row],[تاريخ الاستحقاق]]<$S$1,"مستحق","غير مستحق") -> مستحق | S38: =Table8[[#This Row],[تاريخ الاستحقاق]]-$S$1 -> -46006 | U38: =Table8[[#This Row],[المبلغ المسدد]]/1.14 -> 142829.71
A39: بلتون للتمويل الاستهلاكى سفن | B39: 45658 | C39: 45722 | D39: 7296 | E39: =D39/1.14 -> 6400 | I39: =Table8[[#This Row],[الاجمالي بدون الضريبه14%]]-Table8[[#This Row],[القاهرة ]]-Table8[[#This Row],[المنصورة ]]-Table8[[#This Row],[القانونيه ]] -> 6400 | J39: =D39-E39 -> 896 | K39: =E39*$K$3 -> 192 | L39: =D39-K39 -> 7104 | M39: 7104 | O39: =M39-L39-N39 -> 0 | Q39: =IFERROR((Table8[[#This Row],[تاريخ الاستحقاق]]-Table8[[#This Row],[تاريخ اصدار الفاتورة ]]),0) -> -45722 | R39: =IF(Table8[[#This Row],[تاريخ الاستحقاق]]<$S$1,"مستحق","غير مستحق") -> مستحق | S39: =Table8[[#This Row],[تاريخ الاستحقاق]]-$S$1 -> -46006 | U39: =Table8[[#This Row],[المبلغ المسدد]]/1.14 -> 6231.5789
A40: فاليو قانونى | B40: 45658 | C40: 45722 | D40: 31806 | E40: =D40/1.14 -> 27900 | I40: =Table8[[#This Row],[الاجمالي بدون الضريبه14%]]-Table8[[#This Row],[القاهرة ]]-Table8[[#This Row],[المنصورة ]]-Table8[[#This Row],[القانونيه ]] -> 27900 | J40: =D40-E40 -> 3906 | K40: =E40*$K$3 -> 837 | L40: =D40-K40 -> 30969 | M40: 30969 | O40: =M40-L40-N40 -> 0 | Q40: =IFERROR((Table8[[#This Row],[تاريخ الاستحقاق]]-Table8[[#This Row],[تاريخ اصدار الفاتورة ]]),0) -> -45722 | R40: =IF(Table8[[#This Row],[تاريخ الاستحقاق]]<$S$1,"مستحق","غير مستحق") -> مستحق | S40: =Table8[[#This Row],[تاريخ الاستحقاق]]-$S$1 -> -46006 | U40: =Table8[[#This Row],[المبلغ المسدد]]/1.14 -> 27165.789
A41: شركه رايه للالكترونيات | B41: 45689 | C41: 45724 | D41: 73420.25 | E41: =D41/1.14 -> 64403.728 | I41: =Table8[[#This Row],[الاجمالي بدون الضريبه14%]]-Table8[[#This Row],[القاهرة ]]-Table8[[#This Row],[المنصورة ]]-Table8[[#This Row],[القانونيه ]] -> 64403.728 | J41: =D41-E41 -> 9016.5219 | K41: =E41*$K$3 -> 1932.1118 | L41: =D41-K41 -> 71488.138 | M41: 70200.064 | N41: =-Table8[[#This Row],[الاجمالي بدون الضريبه14%]]*0.02 -> -1288.0746 | O41: =M41-L41-N41 -> -2.5011104e-12 | Q41: =IFERROR((Table8[[#This Row],[تاريخ الاستحقاق]]-Table8[[#This Row],[تاريخ اصدار الفاتورة ]]),0) -> -45724 | R41: =IF(Table8[[#This Row],[تاريخ الاستحقاق]]<$S$1,"مستحق","غير مستحق") -> مستحق | S41: =Table8[[#This Row],[تاريخ الاستحقاق]]-$S$1 -> -46006 | U41: =Table8[[#This Row],[المبلغ المسدد]]/1.14 -> 61579.003
A42: شركه رايه قانونى | B42: 45689 | C42: 45725 | D42: 156180 | E42: =D42/1.14 -> 137000 | I42: =Table8[[#This Row],[الاجمالي بدون الضريبه14%]]-Table8[[#This Row],[القاهرة ]]-Table8[[#This Row],[المنصورة ]]-Table8[[#This Row],[القانونيه ]] -> 137000 | J42: =D42-E42 -> 19180 | K42: =E42*$K$3 -> 4110 | L42: =D42-K42 -> 152070 | M42: 152070 | O42: =M42-L42-N42 -> 0 | Q42: =IFERROR((Table8[[#This Row],[تاريخ الاستحقاق]]-Table8[[#This Row],[تاريخ اصدار الفاتورة ]]),0) -> -45725 | R42: =IF(Table8[[#This Row],[تاريخ الاستحقاق]]<$S$1,"مستحق","غير مستحق") -> مستحق | S42: =Table8[[#This Row],[تاريخ الاستحقاق]]-$S$1 -> -46006 | U42: =Table8[[#This Row],[المبلغ المسدد]]/1.14 -> 133394.74
A43: سهولة قانونى | B43: 45689 | C43: 45727 | D43: 76608 | E43: =D43/1.14 -> 67200 | I43: =Table8[[#This Row],[الاجمالي بدون الضريبه14%]]-Table8[[#This Row],[القاهرة ]]-Table8[[#This Row],[المنصورة ]]-Table8[[#This Row],[القانونيه ]] -> 67200 | J43: =D43-E43 -> 9408 | K43: =E43*$K$3 -> 2016 | L43: =D43-K43 -> 74592 | M43: 74592 | O43: =M43-L43-N43 -> 0 | Q43: =IFERROR((Table8[[#This Row],[تاريخ الاستحقاق]]-Table8[[#This Row],[تاريخ اصدار الفاتورة ]]),0) -> -45727 | R43: =IF(Table8[[#This Row],[تاريخ الاستحقاق]]<$S$1,"مستحق","غير مستحق") -> مستحق | S43: =Table8[[#This Row],[تاريخ الاستحقاق]]-$S$1 -> -46006 | U43: =Table8[[#This Row],[المبلغ المسدد]]/1.14 -> 65431.579
A44: بنك كريدي اجريكول مصر | B44: 45689 | C44: 45728 | D44: 188091.23 | E44: =D44/1.14 -> 164992.31 | I44: =Table8[[#This Row],[الاجمالي بدون الضريبه14%]]-Table8[[#This Row],[القاهرة ]]-Table8[[#This Row],[المنصورة ]]-Table8[[#This Row],[القانونيه ]] -> 164992.31 | J44: =D44-E44 -> 23098.923 | K44: =E44*$K$3 -> 4949.7692 | L44: =D44-K44 -> 183141.46 | M44: 179841.61 | N44: =-Table8[[#This Row],[الاجمالي بدون الضريبه14%]]*0.02 -> -3299.8461 | O44: =M44-L44-N44 -> -6.8212103e-12 | Q44: =IFERROR((Table8[[#This Row],[تاريخ الاستحقاق]]-Table8[[#This Row],[تاريخ اصدار الفاتورة ]]),0) -> -45728 | R44: =IF(Table8[[#This Row],[تاريخ الاستحقاق]]<$S$1,"مستحق","غير مستحق") -> مستحق | S44: =Table8[[#This Row],[تاريخ الاستحقاق]]-$S$1 -> -46006 | U44: =Table8[[#This Row],[المبلغ المسدد]]/1.14 -> 157755.8
A45: بنك الإسكندرية | B45: 45689 | C45: 45728 | D45: 79411.2 | E45: =D45/1.14 -> 69658.947 | I45: =Table8[[#This Row],[الاجمالي بدون الضريبه14%]]-Table8[[#This Row],[القاهرة ]]-Table8[[#This Row],[المنصورة ]]-Table8[[#This Row],[القانونيه ]] -> 69658.947 | J45: =D45-E45 -> 9752.2526 | K45: =E45*$K$3 -> 2089.7684 | L45: =D45-K45 -> 77321.432 | M45: 77321.44 | O45: =M45-L45-N45 -> 0.0084210526 | Q45: =IFERROR((Table8[[#This Row],[تاريخ الاستحقاق]]-Table8[[#This Row],[تاريخ اصدار الفاتورة ]]),0) -> -45728 | R45: =IF(Table8[[#This Row],[تاريخ الاستحقاق]]<$S$1,"مستحق","غير مستحق") -> مستحق | S45: =Table8[[#This Row],[تاريخ الاستحقاق]]-$S$1 -> -46006 | U45: =Table8[[#This Row],[المبلغ المسدد]]/1.14 -> 67825.825
A46: بى ام للتمويل الاستهلاكى | B46: 45689 | C46: 45729 | D46: 170779.76 | E46: =D46/1.14 -> 149806.81 | I46: =Table8[[#This Row],[الاجمالي بدون الضريبه14%]]-Table8[[#This Row],[القاهرة ]]-Table8[[#This Row],[المنصورة ]]-Table8[[#This Row],[القانونيه ]] -> 149806.81 | J46: =D46-E46 -> 20972.953 | K46: =E46*$K$3 -> 4494.2042 | L46: =D46-K46 -> 166285.56 | M46: 166285.56 | O46: =M46-L46-N46 -> 0 | Q46: =IFERROR((Table8[[#This Row],[تاريخ الاستحقاق]]-Table8[[#This Row],[تاريخ اصدار الفاتورة ]]),0) -> -45729 | R46: =IF(Table8[[#This Row],[تاريخ الاستحقاق]]<$S$1,"مستحق","غير مستحق") -> مستحق | S46: =Table8[[#This Row],[تاريخ الاستحقاق]]-$S$1 -> -46006 | U46: =Table8[[#This Row],[المبلغ المسدد]]/1.14 -> 145864.52
A47: مانى فيللوز لتكنولوجيا المعلومات وادارة المشروعات | B47: 45689 | C47: 45732 | D47: 120423.43 | E47: =D47/1.14 -> 105634.59 | I47: =Table8[[#This Row],[الاجمالي بدون الضريبه14%]]-Table8[[#This Row],[القاهرة ]]-Table8[[#This Row],[المنصورة ]]-Table8[[#This Row],[القانونيه ]] -> 105634.59 | J47: =D47-E47 -> 14788.842 | K47: =E47*$K$3 -> 3169.0376 | L47: =D47-K47 -> 117254.39 | M47: 117254.39 | O47: =M47-L47-N47 -> 0 | Q47: =IFERROR((Table8[[#This Row],[تاريخ الاستحقاق]]-Table8[[#This Row],[تاريخ اصدار الفاتورة ]]),0) -> -45732 | R47: =IF(Table8[[#This Row],[تاريخ الاستحقاق]]<$S$1,"مستحق","غير مستحق") -> مستحق | S47: =Table8[[#This Row],[تاريخ الاستحقاق]]-$S$1 -> -46006 | U47: =Table8[[#This Row],[المبلغ المسدد]]/1.14 -> 102854.73
A48: ميد للتقسيط | B48: 45689 | C48: 45739 | D48: 18374.82 | E48: =D48/1.14 -> 16118.263 | I48: =Table8[[#This Row],[الاجمالي بدون الضريبه14%]]-Table8[[#This Row],[القاهرة ]]-Table8[[#This Row],[المنصورة ]]-Table8[[#This Row],[القانونيه ]] -> 16118.263 | J48: =D48-E48 -> 2256.5568 | K48: =E48*$K$3 -> 483.54789 | L48: =D48-K48 -> 17891.272 | M48: 17891.272 | O48: =M48-L48-N48 -> 0 | Q48: =IFERROR((Table8[[#This Row],[تاريخ الاستحقاق]]-Table8[[#This Row],[تاريخ اصدار الفاتورة ]]),0) -> -45739 | R48: =IF(Table8[[#This Row],[تاريخ الاستحقاق]]<$S$1,"مستحق","غير مستحق") -> مستحق | S48: =Table8[[#This Row],[تاريخ الاستحقاق]]-$S$1 -> -46006 | U48: =Table8[[#This Row],[المبلغ المسدد]]/1.14 -> 15694.098
A49: فاليو لخدمات البيع والتقسيط | B49: 45689 | C49: 45741 | D49: 171901.58 | E49: =D49/1.14 -> 150790.86 | I49: =Table8[[#This Row],[الاجمالي بدون الضريبه14%]]-Table8[[#This Row],[القاهرة ]]-Table8[[#This Row],[المنصورة ]]-Table8[[#This Row],[القانونيه ]] -> 150790.86 | J49: =D49-E49 -> 21110.72 | K49: =E49*$K$3 -> 4523.7258 | L49: =D49-K49 -> 167377.85 | M49: 167377.85 | O49: =M49-L49-N49 -> -0.0042105263 | Q49: =IFERROR((Table8[[#This Row],[تاريخ الاستحقاق]]-Table8[[#This Row],[تاريخ اصدار الفاتورة ]]),0) -> -45741 | R49: =IF(Table8[[#This Row],[تاريخ الاستحقاق]]<$S$1,"مستحق","غير مستحق") -> مستحق | S49: =Table8[[#This Row],[تاريخ الاستحقاق]]-$S$1 -> -46006 | U49: =Table8[[#This Row],[المبلغ المسدد]]/1.14 -> 146822.68
A50: اور للتمويل الاستهلاكى -وسيلة قانونى | B50: 45717 | C50: 45755 | D50: 26470.8 | E50: =D50/1.14 -> 23220 | I50: =Table8[[#This Row],[الاجمالي بدون الضريبه14%]]-Table8[[#This Row],[القاهرة ]]-Table8[[#This Row],[المنصورة ]]-Table8[[#This Row],[القانونيه ]] -> 23220 | J50: =D50-E50 -> 3250.8 | K50: =E50*$K$3 -> 696.6 | L50: =D50-K50 -> 25774.2 | M50: 25774.2 | O50: =M50-L50-N50 -> 0 | Q50: =IFERROR((Table8[[#This Row],[تاريخ الاستحقاق]]-Table8[[#This Row],[تاريخ اصدار الفاتورة ]]),0) -> -45755 | R50: =IF(Table8[[#This Row],[تاريخ الاستحقاق]]<$S$1,"مستحق","غير مستحق") -> مستحق | S50: =Table8[[#This Row],[تاريخ الاستحقاق]]-$S$1 -> -46006 | U50: =Table8[[#This Row],[المبلغ المسدد]]/1.14 -> 22608.947
A51: بنك كريدي اجريكول مصر | B51: 45717 | C51: 45757 | D51: 175554.45 | E51: =D51/1.14 -> 153995.13 | I51: =Table8[[#This Row],[الاجمالي بدون الضريبه14%]]-Table8[[#This Row],[القاهرة ]]-Table8[[#This Row],[المنصورة ]]-Table8[[#This Row],[القانونيه ]] -> 153995.13 | J51: =D51-E51 -> 21559.318 | K51: =E51*$K$3 -> 4619.8539 | L51: =D51-K51 -> 170934.6 | M51: 167854.69 | N51: =-Table8[[#This Row],[الاجمالي بدون الضريبه14%]]*0.02 -> -3079.9026 | O51: =M51-L51-N51 -> -0.003008 | Q51: =IFERROR((Table8[[#This Row],[تاريخ الاستحقاق]]-Table8[[#This Row],[تاريخ اصدار الفاتورة ]]),0) -> -45757 | R51: =IF(Table8[[#This Row],[تاريخ الاستحقاق]]<$S$1,"مستحق","غير مستحق") -> مستحق | S51: =Table8[[#This Row],[تاريخ الاستحقاق]]-$S$1 -> -46006 | U51: =Table8[[#This Row],[المبلغ المسدد]]/1.14 -> 147240.96
A52: شركه رايه للالكترونيات | B52: 45717 | C52: 45760 | D52: 75528.6 | E52: =D52/1.14 -> 66253.158 | I52: =Table8[[#This Row],[الاجمالي بدون الضريبه14%]]-Table8[[#This Row],[القاهرة ]]-Table8[[#This Row],[المنصورة ]]-Table8[[#This Row],[القانونيه ]] -> 66253.158 | J52: =D52-E52 -> 9275.4421 | K52: =E52*$K$3 -> 1987.5947 | L52: =D52-K52 -> 73541.005 | M52: 72215.942 | N52: =-Table8[[#This Row],[الاجمالي بدون الضريبه14%]]*0.02 -> -1325.0632 | O52: =M52-L52-N52 -> 0 | Q52: =IFERROR((Table8[[#This Row],[تاريخ الاستحقاق]]-Table8[[#This Row],[تاريخ اصدار الفاتورة ]]),0) -> -45760 | R52: =IF(Table8[[#This Row],[تاريخ الاستحقاق]]<$S$1,"مستحق","غير مستحق") -> مستحق | S52: =Table8[[#This Row],[تاريخ الاستحقاق]]-$S$1 -> -46006 | U52: =Table8[[#This Row],[المبلغ المسدد]]/1.14 -> 63347.318
A53: بنك الإسكندرية | B53: 45717 | C53: 45761 | D53: 121545.91 | E53: =D53/1.14 -> 106619.22 | I53: =Table8[[#This Row],[الاجمالي بدون الضريبه14%]]-Table8[[#This Row],[القاهرة ]]-Table8[[#This Row],[المنصورة ]]-Table8[[#This Row],[القانونيه ]] -> 106619.22 | J53: =D53-E53 -> 14926.691 | K53: =E53*$K$3 -> 3198.5766 | L53: =D53-K53 -> 118347.33 | M53: 118347.33 | O53: =M53-L53-N53 -> 0 | Q53: =IFERROR((Table8[[#This Row],[تاريخ الاستحقاق]]-Table8[[#This Row],[تاريخ اصدار الفاتورة ]]),0) -> -45761 | R53: =IF(Table8[[#This Row],[تاريخ الاستحقاق]]<$S$1,"مستحق","غير مستحق") -> مستحق | S53: =Table8[[#This Row],[تاريخ الاستحقاق]]-$S$1 -> -46006 | U53: =Table8[[#This Row],[المبلغ المسدد]]/1.14 -> 103813.45
A54: تنميه لخدمات المشروعات متناهيه الصغر | B54: 45689 | C54: 45763 | D54: 126873.12 | E54: =D54/1.14 -> 111292.21 | I54: =Table8[[#This Row],[الاجمالي بدون الضريبه14%]]-Table8[[#This Row],[القاهرة ]]-Table8[[#This Row],[المنصورة ]]-Table8[[#This Row],[القانونيه ]] -> 111292.21 | J54: =D54-E54 -> 15580.909 | K54: =E54*$K$3 -> 3338.7663 | L54: =D54-K54 -> 123534.35 | M54: 123534.35 | O54: =M54-L54-N54 -> 0 | Q54: =IFERROR((Table8[[#This Row],[تاريخ الاستحقاق]]-Table8[[#This Row],[تاريخ اصدار الفاتورة ]]),0) -> -45763 | R54: =IF(Table8[[#This Row],[تاريخ الاستحقاق]]<$S$1,"مستحق","غير مستحق") -> مستحق | S54: =Table8[[#This Row],[تاريخ الاستحقاق]]-$S$1 -> -46006 | U54: =Table8[[#This Row],[المبلغ المسدد]]/1.14 -> 108363.47
A55: شركه رايه قانونى | B55: 45717 | C55: 45763 | D55: 295260 | E55: =D55/1.14 -> 259000 | I55: =Table8[[#This Row],[الاجمالي بدون الضريبه14%]]-Table8[[#This Row],[القاهرة ]]-Table8[[#This Row],[المنصورة ]]-Table8[[#This Row],[القانونيه ]] -> 259000 | J55: =D55-E55 -> 36260 | K55: =E55*$K$3 -> 7770 | L55: =D55-K55 -> 287490 | M55: 287490 | O55: =M55-L55-N55 -> 0 | Q55: =IFERROR((Table8[[#This Row],[تاريخ الاستحقاق]]-Table8[[#This Row],[تاريخ اصدار الفاتورة ]]),0) -> -45763 | R55: =IF(Table8[[#This Row],[تاريخ الاستحقاق]]<$S$1,"مستحق","غير مستحق") -> مستحق | S55: =Table8[[#This Row],[تاريخ الاستحقاق]]-$S$1 -> -46006 | U55: =Table8[[#This Row],[المبلغ المسدد]]/1.14 -> 252184.21
A56: امان لتمويل المشروعات | B56: 45689 | C56: 45764 | D56: 7410 | E56: =D56/1.14 -> 6500 | I56: =Table8[[#This Row],[الاجمالي بدون الضريبه14%]]-Table8[[#This Row],[القاهرة ]]-Table8[[#This Row],[المنصورة ]]-Table8[[#This Row],[القانونيه ]] -> 6500 | J56: =D56-E56 -> 910 | K56: =E56*$K$3 -> 195 | L56: =D56-K56 -> 7215 | M56: 7215 | O56: =M56-L56-N56 -> 0 | Q56: =IFERROR((Table8[[#This Row],[تاريخ الاستحقاق]]-Table8[[#This Row],[تاريخ اصدار الفاتورة ]]),0) -> -45764 | R56: =IF(Table8[[#This Row],[تاريخ الاستحقاق]]<$S$1,"مستحق","غير مستحق") -> مستحق | S56: =Table8[[#This Row],[تاريخ الاستحقاق]]-$S$1 -> -46006 | U56: =Table8[[#This Row],[المبلغ المسدد]]/1.14 -> 6328.9474
A57: فورى لتكنولوجيا المعلومات التجارية | B57: 45717 | C57: 45774 | D57: 132060.31 | E57: =D57/1.14 -> 115842.38 | I57: =Table8[[#This Row],[الاجمالي بدون الضريبه14%]]-Table8[[#This Row],[القاهرة ]]-Table8[[#This Row],[المنصورة ]]-Table8[[#This Row],[القانونيه ]] -> 115842.38 | J57: =D57-E57 -> 16217.933 | K57: =E57*$K$3 -> 3475.2713 | L57: =D57-K57 -> 128585.04 | M57: 128585.04 | O57: =M57-L57-N57 -> 0 | Q57: =IFERROR((Table8[[#This Row],[تاريخ الاستحقاق]]-Table8[[#This Row],[تاريخ اصدار الفاتورة ]]),0) -> -45774 | R57: =IF(Table8[[#This Row],[تاريخ الاستحقاق]]<$S$1,"مستحق","غير مستحق") -> مستحق | S57: =Table8[[#This Row],[تاريخ الاستحقاق]]-$S$1 -> -46006 | U57: =Table8[[#This Row],[المبلغ المسدد]]/1.14 -> 112793.89
A58: مانى فيللوز لتكنولوجيا المعلومات وادارة المشروعات | B58: 45717 | C58: 45773 | D58: 99415.98 | E58: =D58/1.14 -> 87207 | I58: =Table8[[#This Row],[الاجمالي بدون الضريبه14%]]-Table8[[#This Row],[القاهرة ]]-Table8[[#This Row],[المنصورة ]]-Table8[[#This Row],[القانونيه ]] -> 87207 | J58: =D58-E58 -> 12208.98 | K58: =E58*$K$3 -> 2616.21 | L58: =D58-K58 -> 96799.77 | M58: 96799.77 | O58: =M58-L58-N58 -> 1.4551915e-11 | Q58: =IFERROR((Table8[[#This Row],[تاريخ الاستحقاق]]-Table8[[#This Row],[تاريخ اصدار الفاتورة ]]),0) -> -45773 | R58: =IF(Table8[[#This Row],[تاريخ الاستحقاق]]<$S$1,"مستحق","غير مستحق") -> مستحق | S58: =Table8[[#This Row],[تاريخ الاستحقاق]]-$S$1 -> -46006 | U58: =Table8[[#This Row],[المبلغ المسدد]]/1.14 -> 84912.079
A59: سفن | B59: 45717 | C59: 45773 | D59: 76254.76 | E59: =D59/1.14 -> 66890.14 | I59: =Table8[[#This Row],[الاجمالي بدون الضريبه14%]]-Table8[[#This Row],[القاهرة ]]-Table8[[#This Row],[المنصورة ]]-Table8[[#This Row],[القانونيه ]] -> 66890.14 | J59: =D59-E59 -> 9364.6196 | K59: =E59*$K$3 -> 2006.7042 | L59: =D59-K59 -> 74248.056 | M59: 74248.056 | O59: =M59-L59-N59 -> 0 | Q59: =IFERROR((Table8[[#This Row],[تاريخ الاستحقاق]]-Table8[[#This Row],[تاريخ اصدار الفاتورة ]]),0) -> -45773 | R59: =IF(Table8[[#This Row],[تاريخ الاستحقاق]]<$S$1,"مستحق","غير مستحق") -> مستحق | S59: =Table8[[#This Row],[تاريخ الاستحقاق]]-$S$1 -> -46006 | U59: =Table8[[#This Row],[المبلغ المسدد]]/1.14 -> 65129.873
A60: ميد للتقسيط | B60: 45717 | C60: 45774 | D60: 72793.45 | E60: =D60/1.14 -> 63853.904 | I60: =Table8[[#This Row],[الاجمالي بدون الضريبه14%]]-Table8[[#This Row],[القاهرة ]]-Table8[[#This Row],[المنصورة ]]-Table8[[#This Row],[القانونيه ]] -> 63853.904 | J60: =D60-E60 -> 8939.5465 | K60: =E60*$K$3 -> 1915.6171 | L60: =D60-K60 -> 70877.833 | M60: 70877.833 | O60: =M60-L60-N60 -> 0 | Q60: =IFERROR((Table8[[#This Row],[تاريخ الاستحقاق]]-Table8[[#This Row],[تاريخ اصدار الفاتورة ]]),0) -> -45774 | R60: =IF(Table8[[#This Row],[تاريخ الاستحقاق]]<$S$1,"مستحق","غير مستحق") -> مستحق | S60: =Table8[[#This Row],[تاريخ الاستحقاق]]-$S$1 -> -46006 | U60: =Table8[[#This Row],[المبلغ المسدد]]/1.14 -> 62173.538
A61: اور للتمويل الاستهلاكى -وسيلة | B61: 45689 | C61: 45774 | D61: 43146.53 | E61: =D61/1.14 -> 37847.833 | I61: =Table8[[#This Row],[الاجمالي بدون الضريبه14%]]-Table8[[#This Row],[القاهرة ]]-Table8[[#This Row],[المنصورة ]]-Table8[[#This Row],[القانونيه ]] -> 37847.833 | J61: =D61-E61 -> 5298.6967 | K61: =E61*$K$3 -> 1135.435 | L61: =D61-K61 -> 42011.095 | M61: 42011.095 | O61: =M61-L61-N61 -> 0 | Q61: =IFERROR((Table8[[#This Row],[تاريخ الاستحقاق]]-Table8[[#This Row],[تاريخ اصدار الفاتورة ]]),0) -> -45774 | R61: =IF(Table8[[#This Row],[تاريخ الاستحقاق]]<$S$1,"مستحق","غير مستحق") -> مستحق | S61: =Table8[[#This Row],[تاريخ الاستحقاق]]-$S$1 -> -46006 | U61: =Table8[[#This Row],[المبلغ المسدد]]/1.14 -> 36851.838
A62: تنميه لخدمات المشروعات متناهيه الصغر | B62: 45717 | C62: 45784 | D62: 133607.44 | E62: =D62/1.14 -> 117199.51 | I62: =Table8[[#This Row],[الاجمالي بدون الضريبه14%]]-Table8[[#This Row],[القاهرة ]]-Table8[[#This Row],[المنصورة ]]-Table8[[#This Row],[القانونيه ]] -> 117199.51 | J62: =D62-E62 -> 16407.931 | K62: =E62*$K$3 -> 3515.9853 | L62: =D62-K62 -> 130091.45 | M62: 130091.45 | O62: =M62-L62-N62 -> 0 | Q62: =IFERROR((Table8[[#This Row],[تاريخ الاستحقاق]]-Table8[[#This Row],[تاريخ اصدار الفاتورة ]]),0) -> -45784 | R62: =IF(Table8[[#This Row],[تاريخ الاستحقاق]]<$S$1,"مستحق","غير مستحق") -> مستحق | S62: =Table8[[#This Row],[تاريخ الاستحقاق]]-$S$1 -> -46006 | U62: =Table8[[#This Row],[المبلغ المسدد]]/1.14 -> 114115.31
A63: شركه رايه للالكترونيات | B63: 45748 | C63: 45784 | D63: 41356.74 | E63: =D63/1.14 -> 36277.842 | I63: =Table8[[#This Row],[الاجمالي بدون الضريبه14%]]-Table8[[#This Row],[القاهرة ]]-Table8[[#This Row],[المنصورة ]]-Table8[[#This Row],[القانونيه ]] -> 36277.842 | J63: =D63-E63 -> 5078.8979 | K63: =E63*$K$3 -> 1088.3353 | L63: =D63-K63 -> 40268.405 | M63: 39542.848 | N63: =-Table8[[#This Row],[الاجمالي بدون الضريبه14%]]*0.02 -> -725.55684 | O63: =M63-L63-N63 -> -3.990408e-11 | Q63: =IFERROR((Table8[[#This Row],[تاريخ الاستحقاق]]-Table8[[#This Row],[تاريخ اصدار الفاتورة ]]),0) -> -45784 | R63: =IF(Table8[[#This Row],[تاريخ الاستحقاق]]<$S$1,"مستحق","غير مستحق") -> مستحق | S63: =Table8[[#This Row],[تاريخ الاستحقاق]]-$S$1 -> -46006 | U63: =Table8[[#This Row],[المبلغ المسدد]]/1.14 -> 34686.709
A64: بنك كريدي اجريكول مصر | B64: 45748 | C64: 45785 | D64: 249942.93 | E64: =D64/1.14 -> 219248.18 | I64: =Table8[[#This Row],[الاجمالي بدون الضريبه14%]]-Table8[[#This Row],[القاهرة ]]-Table8[[#This Row],[المنصورة ]]-Table8[[#This Row],[القانونيه ]] -> 219248.18 | J64: =D64-E64 -> 30694.746 | K64: =E64*$K$3 -> 6577.4455 | L64: =D64-K64 -> 243365.48 | M64: =+Table8[[#This Row],[المطلوب تحويله ]]+Table8[[#This Row],[مصروفات ]] -> 238980.52 | N64: =-Table8[[#This Row],[الاجمالي بدون الضريبه14%]]*0.02 -> -4384.9637 | O64: =M64-L64-N64 -> 0 | Q64: =IFERROR((Table8[[#This Row],[تاريخ الاستحقاق]]-Table8[[#This Row],[تاريخ اصدار الفاتورة ]]),0) -> -45785 | R64: =IF(Table8[[#This Row],[تاريخ الاستحقاق]]<$S$1,"مستحق","غير مستحق") -> مستحق | S64: =Table8[[#This Row],[تاريخ الاستحقاق]]-$S$1 -> -46006 | U64: =Table8[[#This Row],[المبلغ المسدد]]/1.14 -> 209632.04
A65: بنك الإسكندرية | B65: 45748 | C65: 45791 | D65: 76548.77 | E65: =D65/1.14 -> 67148.044 | I65: =Table8[[#This Row],[الاجمالي بدون الضريبه14%]]-Table8[[#This Row],[القاهرة ]]-Table8[[#This Row],[المنصورة ]]-Table8[[#This Row],[القانونيه ]] -> 67148.044 | J65: =D65-E65 -> 9400.7261 | K65: =E65*$K$3 -> 2014.4413 | L65: =D65-K65 -> 74534.329 | M65: 74534.329 | O65: =M65-L65-N65 -> 0 | Q65: =IFERROR((Table8[[#This Row],[تاريخ الاستحقاق]]-Table8[[#This Row],[تاريخ اصدار الفاتورة ]]),0) -> -45791 | R65: =IF(Table8[[#This Row],[تاريخ الاستحقاق]]<$S$1,"مستحق","غير مستحق") -> مستحق | S65: =Table8[[#This Row],[تاريخ الاستحقاق]]-$S$1 -> -46006 | U65: =Table8[[#This Row],[المبلغ المسدد]]/1.14 -> 65380.99
A66: فورى لتكنولوجيا المعلومات التجارية | B66: 45748 | C66: 45795 | D66: 96602.79 | E66: =D66/1.14 -> 84739.289 | I66: =Table8[[#This Row],[الاجمالي بدون الضريبه14%]]-Table8[[#This Row],[القاهرة ]]-Table8[[#This Row],[المنصورة ]]-Table8[[#This Row],[القانونيه ]] -> 84739.289 | J66: =D66-E66 -> 11863.501 | K66: =E66*$K$3 -> 2542.1787 | L66: =D66-K66 -> 94060.611 | M66: 94060.61 | O66: =M66-L66-N66 -> -0.0013157895 | Q66: =IFERROR((Table8[[#This Row],[تاريخ الاستحقاق]]-Table8[[#This Row],[تاريخ اصدار الفاتورة ]]),0) -> -45795 | R66: =IF(Table8[[#This Row],[تاريخ الاستحقاق]]<$S$1,"مستحق","غير مستحق") -> مستحق | S66: =Table8[[#This Row],[تاريخ الاستحقاق]]-$S$1 -> -46006 | U66: =Table8[[#This Row],[المبلغ المسدد]]/1.14 -> 82509.307
A67: بنك البركة مصر | B67: 45748 | C67: 45795 | D67: 185250 | E67: =D67/1.14 -> 162500 | I67: =Table8[[#This Row],[الاجمالي بدون الضريبه14%]]-Table8[[#This Row],[القاهرة ]]-Table8[[#This Row],[المنصورة ]]-Table8[[#This Row],[القانونيه ]] -> 162500 | J67: =D67-E67 -> 22750 | K67: =E67*$K$3 -> 4875 | L67: =D67-K67 -> 180375 | M67: 180375 | O67: =M67-L67-N67 -> 0 | Q67: =IFERROR((Table8[[#This Row],[تاريخ الاستحقاق]]-Table8[[#This Row],[تاريخ اصدار الفاتورة ]]),0) -> -45795 | R67: =IF(Table8[[#This Row],[تاريخ الاستحقاق]]<$S$1,"مستحق","غير مستحق") -> مستحق | S67: =Table8[[#This Row],[تاريخ الاستحقاق]]-$S$1 -> -46006 | U67: =Table8[[#This Row],[المبلغ المسدد]]/1.14 -> 158223.68
A68: فاليو قانونى | B68: 45717 | C68: 45796 | D68: 14820 | E68: =D68/1.14 -> 13000 | I68: =Table8[[#This Row],[الاجمالي بدون الضريبه14%]]-Table8[[#This Row],[القاهرة ]]-Table8[[#This Row],[المنصورة ]]-Table8[[#This Row],[القانونيه ]] -> 13000 | J68: =D68-E68 -> 1820 | K68: =E68*$K$3 -> 390 | L68: =D68-K68 -> 14430 | M68: 14430 | O68: =M68-L68-N68 -> 0 | Q68: =IFERROR((Table8[[#This Row],[تاريخ الاستحقاق]]-Table8[[#This Row],[تاريخ اصدار الفاتورة ]]),0) -> -45796 | R68: =IF(Table8[[#This Row],[تاريخ الاستحقاق]]<$S$1,"مستحق","غير مستحق") -> مستحق | S68: =Table8[[#This Row],[تاريخ الاستحقاق]]-$S$1 -> -46006 | U68: =Table8[[#This Row],[المبلغ المسدد]]/1.14 -> 12657.895
A69: فاليو | B69: 45748 | C69: 45796 | D69: 102970.5 | E69: =D69/1.14 -> 90325 | I69: =Table8[[#This Row],[الاجمالي بدون الضريبه14%]]-Table8[[#This Row],[القاهرة ]]-Table8[[#This Row],[المنصورة ]]-Table8[[#This Row],[القانونيه ]] -> 90325 | J69: =D69-E69 -> 12645.5 | K69: =E69*$K$3 -> 2709.75 | L69: =D69-K69 -> 100260.75 | M69: 100260.75 | O69: =M69-L69-N69 -> 0 | Q69: =IFERROR((Table8[[#This Row],[تاريخ الاستحقاق]]-Table8[[#This Row],[تاريخ اصدار الفاتورة ]]),0) -> -45796 | R69: =IF(Table8[[#This Row],[تاريخ الاستحقاق]]<$S$1,"مستحق","غير مستحق") -> مستحق | S69: =Table8[[#This Row],[تاريخ الاستحقاق]]-$S$1 -> -46006 | U69: =Table8[[#This Row],[المبلغ المسدد]]/1.14 -> 87948.026
A70: ميد للتقسيط | B70: 45748 | C70: 45804 | D70: 133458.86 | E70: =D70/1.14 -> 117069.18 | I70: =Table8[[#This Row],[الاجمالي بدون الضريبه14%]]-Table8[[#This Row],[القاهرة ]]-Table8[[#This Row],[المنصورة ]]-Table8[[#This Row],[القانونيه ]] -> 117069.18 | J70: =D70-E70 -> 16389.685 | K70: =E70*$K$3 -> 3512.0753 | L70: =D70-K70 -> 129946.78 | M70: 129946.78 | O70: =M70-L70-N70 -> 0 | Q70: =IFERROR((Table8[[#This Row],[تاريخ الاستحقاق]]-Table8[[#This Row],[تاريخ اصدار الفاتورة ]]),0) -> -45804 | R70: =IF(Table8[[#This Row],[تاريخ الاستحقاق]]<$S$1,"مستحق","غير مستحق") -> مستحق | S70: =Table8[[#This Row],[تاريخ الاستحقاق]]-$S$1 -> -46006 | U70: =Table8[[#This Row],[المبلغ المسدد]]/1.14 -> 113988.41
A71: سفن | B71: 45748 | C71: 45806 | D71: 88117.56 | E71: =D71/1.14 -> 77296.105 | I71: =Table8[[#This Row],[الاجمالي بدون الضريبه14%]]-Table8[[#This Row],[القاهرة ]]-Table8[[#This Row],[المنصورة ]]-Table8[[#This Row],[القانونيه ]] -> 77296.105 | J71: =D71-E71 -> 10821.455 | K71: =E71*$K$3 -> 2318.8832 | L71: =D71-K71 -> 85798.677 | M71: 85798.677 | O71: =M71-L71-N71 -> 0 | Q71: =IFERROR((Table8[[#This Row],[تاريخ الاستحقاق]]-Table8[[#This Row],[تاريخ اصدار الفاتورة ]]),0) -> -45806 | R71: =IF(Table8[[#This Row],[تاريخ الاستحقاق]]<$S$1,"مستحق","غير مستحق") -> مستحق | S71: =Table8[[#This Row],[تاريخ الاستحقاق]]-$S$1 -> -46006 | U71: =Table8[[#This Row],[المبلغ المسدد]]/1.14 -> 75261.997
A72: شركه رايه قانونى | B72: 45778 | C72: 45809 | D72: 249660 | E72: =D72/1.14 -> 219000 | I72: =Table8[[#This Row],[الاجمالي بدون الضريبه14%]]-Table8[[#This Row],[القاهرة ]]-Table8[[#This Row],[المنصورة ]]-Table8[[#This Row],[القانونيه ]] -> 219000 | J72: =D72-E72 -> 30660 | K72: =E72*$K$3 -> 6570 | L72: =D72-K72 -> 243090 | M72: 243090 | O72: =M72-L72-N72 -> 0 | Q72: =IFERROR((Table8[[#This Row],[تاريخ الاستحقاق]]-Table8[[#This Row],[تاريخ اصدار الفاتورة ]]),0) -> -45809 | R72: =IF(Table8[[#This Row],[تاريخ الاستحقاق]]<$S$1,"مستحق","غير مستحق") -> مستحق | S72: =Table8[[#This Row],[تاريخ الاستحقاق]]-$S$1 -> -46006 | U72: =Table8[[#This Row],[المبلغ المسدد]]/1.14 -> 213236.84
A73: اور للتمويل الاستهلاكى -وسيلة قانونى | B73: 45778 | C73: 45812 | D73: 215460 | E73: =D73/1.14 -> 189000 | I73: =Table8[[#This Row],[الاجمالي بدون الضريبه14%]]-Table8[[#This Row],[القاهرة ]]-Table8[[#This Row],[المنصورة ]]-Table8[[#This Row],[القانونيه ]] -> 189000 | J73: =D73-E73 -> 26460 | K73: =E73*$K$3 -> 5670 | L73: =D73-K73 -> 209790 | M73: 209790 | O73: =M73-L73-N73 -> 0 | Q73: =IFERROR((Table8[[#This Row],[تاريخ الاستحقاق]]-Table8[[#This Row],[تاريخ اصدار الفاتورة ]]),0) -> -45812 | R73: =IF(Table8[[#This Row],[تاريخ الاستحقاق]]<$S$1,"مستحق","غير مستحق") -> مستحق | S73: =Table8[[#This Row],[تاريخ الاستحقاق]]-$S$1 -> -46006 | U73: =Table8[[#This Row],[المبلغ المسدد]]/1.14 -> 184026.32
A74: اور للتمويل الاستهلاكى -وسيلة قانونى | B74: 45778 | C74: 45812 | D74: 18733.56 | E74: =D74/1.14 -> 16432.947 | I74: =Table8[[#This Row],[الاجمالي بدون الضريبه14%]]-Table8[[#This Row],[القاهرة ]]-Table8[[#This Row],[المنصورة ]]-Table8[[#This Row],[القانونيه ]] -> 16432.947 | J74: =D74-E74 -> 2300.6126 | K74: =E74*$K$3 -> 492.98842 | L74: =D74-K74 -> 18240.572 | M74: 18240.57 | O74: =M74-L74-N74 -> -0.0015789474 | Q74: =IFERROR((Table8[[#This Row],[تاريخ الاستحقاق]]-Table8[[#This Row],[تاريخ اصدار الفاتورة ]]),0) -> -45812 | R74: =IF(Table8[[#This Row],[تاريخ الاستحقاق]]<$S$1,"مستحق","غير مستحق") -> مستحق | S74: =Table8[[#This Row],[تاريخ الاستحقاق]]-$S$1 -> -46006 | U74: =Table8[[#This Row],[المبلغ المسدد]]/1.14 -> 16000.5
A75: بنك الإسكندرية | B75: 45778 | C75: 45818 | D75: 191095.34 | E75: =D75/1.14 -> 167627.49 | I75: =Table8[[#This Row],[الاجمالي بدون الضريبه14%]]-Table8[[#This Row],[القاهرة ]]-Table8[[#This Row],[المنصورة ]]-Table8[[#This Row],[القانونيه ]] -> 167627.49 | J75: =D75-E75 -> 23467.849 | K75: =E75*$K$3 -> 5028.8247 | L75: =D75-K75 -> 186066.52 | M75: 186066.52 | O75: =M75-L75-N75 -> 0 | Q75: =IFERROR((Table8[[#This Row],[تاريخ الاستحقاق]]-Table8[[#This Row],[تاريخ اصدار الفاتورة ]]),0) -> -45818 | R75: =IF(Table8[[#This Row],[تاريخ الاستحقاق]]<$S$1,"مستحق","غير مستحق") -> مستحق | S75: =Table8[[#This Row],[تاريخ الاستحقاق]]-$S$1 -> -46006 | U75: =Table8[[#This Row],[المبلغ المسدد]]/1.14 -> 163216.24
A76: شركه رايه للالكترونيات | B76: 45778 | C76: 45818 | D76: 73402.21 | E76: =D76/1.14 -> 64387.904 | I76: =Table8[[#This Row],[الاجمالي بدون الضريبه14%]]-Table8[[#This Row],[القاهرة ]]-Table8[[#This Row],[المنصورة ]]-Table8[[#This Row],[القانونيه ]] -> 64387.904 | J76: =D76-E76 -> 9014.3065 | K76: =E76*$K$3 -> 1931.6371 | L76: =D76-K76 -> 71470.573 | M76: 70182.815 | N76: =-Table8[[#This Row],[الاجمالي بدون الضريبه14%]]*0.02 -> -1287.7581 | O76: =M76-L76-N76 -> 4.7748472e-12 | Q76: =IFERROR((Table8[[#This Row],[تاريخ الاستحقاق]]-Table8[[#This Row],[تاريخ اصدار الفاتورة ]]),0) -> -45818 | R76: =IF(Table8[[#This Row],[تاريخ الاستحقاق]]<$S$1,"مستحق","غير مستحق") -> مستحق | S76: =Table8[[#This Row],[تاريخ الاستحقاق]]-$S$1 -> -46006 | U76: =Table8[[#This Row],[المبلغ المسدد]]/1.14 -> 61563.873
A77: بنك البركة مصر | B77: 45778 | C77: 45820 | D77: 10374 | E77: =D77/1.14 -> 9100 | I77: =Table8[[#This Row],[الاجمالي بدون الضريبه14%]]-Table8[[#This Row],[القاهرة ]]-Table8[[#This Row],[المنصورة ]]-Table8[[#This Row],[القانونيه ]] -> 9100 | J77: =D77-E77 -> 1274 | K77: =E77*$K$3 -> 273 | L77: =D77-K77 -> 10101 | M77: 10101 | O77: =M77-L77-N77 -> 0 | Q77: =IFERROR((Table8[[#This Row],[تاريخ الاستحقاق]]-Table8[[#This Row],[تاريخ اصدار الفاتورة ]]),0) -> -45820 | R77: =IF(Table8[[#This Row],[تاريخ الاستحقاق]]<$S$1,"مستحق","غير مستحق") -> مستحق | S77: =Table8[[#This Row],[تاريخ الاستحقاق]]-$S$1 -> -46006 | U77: =Table8[[#This Row],[المبلغ المسدد]]/1.14 -> 8860.5263
A78: مانى فيللوز لتكنولوجيا المعلومات وادارة المشروعات | B78: 45748 | C78: 45820 | D78: 135784.26 | E78: =D78/1.14 -> 119109 | I78: =Table8[[#This Row],[الاجمالي بدون الضريبه14%]]-Table8[[#This Row],[القاهرة ]]-Table8[[#This Row],[المنصورة ]]-Table8[[#This Row],[القانونيه ]] -> 119109 | J78: =D78-E78 -> 16675.26 | K78: =E78*$K$3 -> 3573.27 | L78: =D78-K78 -> 132210.99 | M78: 132210.99 | O78: =M78-L78-N78 -> 0 | Q78: =IFERROR((Table8[[#This Row],[تاريخ الاستحقاق]]-Table8[[#This Row],[تاريخ اصدار الفاتورة ]]),0) -> -45820 | R78: =IF(Table8[[#This Row],[تاريخ الاستحقاق]]<$S$1,"مستحق","غير مستحق") -> مستحق | S78: =Table8[[#This Row],[تاريخ الاستحقاق]]-$S$1 -> -46006 | U78: =Table8[[#This Row],[المبلغ المسدد]]/1.14 -> 115974.55
A79: تنميه لخدمات المشروعات متناهيه الصغر | B79: 45748 | C79: 45822 | D79: 85364.42 | E79: =D79/1.14 -> 74881.07 | I79: =Table8[[#This Row],[الاجمالي بدون الضريبه14%]]-Table8[[#This Row],[القاهرة ]]-Table8[[#This Row],[المنصورة ]]-Table8[[#This Row],[القانونيه ]] -> 74881.07 | J79: =D79-E79 -> 10483.35 | K79: =E79*$K$3 -> 2246.4321 | L79: =D79-K79 -> 83117.988 | M79: 83117.98 | O79: =M79-L79-N79 -> -0.0078947368 | Q79: =IFERROR((Table8[[#This Row],[تاريخ الاستحقاق]]-Table8[[#This Row],[تاريخ اصدار الفاتورة ]]),0) -> -45822 | R79: =IF(Table8[[#This Row],[تاريخ الاستحقاق]]<$S$1,"مستحق","غير مستحق") -> مستحق | S79: =Table8[[#This Row],[تاريخ الاستحقاق]]-$S$1 -> -46006 | U79: =Table8[[#This Row],[المبلغ المسدد]]/1.14 -> 72910.509
A80: بنك كريدي اجريكول مصر | B80: 45778 | C80: 45823 | D80: 256826.46 | E80: =D80/1.14 -> 225286.37 | I80: =Table8[[#This Row],[الاجمالي بدون الضريبه14%]]-Table8[[#This Row],[القاهرة ]]-Table8[[#This Row],[المنصورة ]]-Table8[[#This Row],[القانونيه ]] -> 225286.37 | J80: =D80-E80 -> 31540.092 | K80: =E80*$K$3 -> 6758.5911 | L80: =D80-K80 -> 250067.87 | M80: 245562.14 | N80: =-Table8[[#This Row],[الاجمالي بدون الضريبه14%]]*0.02 -> -4505.7274 | O80: =M80-L80-N80 -> -1.3642421e-11 | Q80: =IFERROR((Table8[[#This Row],[تاريخ الاستحقاق]]-Table8[[#This Row],[تاريخ اصدار الفاتورة ]]),0) -> -45823 | R80: =IF(Table8[[#This Row],[تاريخ الاستحقاق]]<$S$1,"مستحق","غير مستحق") -> مستحق | S80: =Table8[[#This Row],[تاريخ الاستحقاق]]-$S$1 -> -46006 | U80: =Table8[[#This Row],[المبلغ المسدد]]/1.14 -> 215405.39
A81: اور للتمويل الاستهلاكى -وسيلة | B81: 45717 | C81: 45825 | D81: 73349.87 | E81: =D81/1.14 -> 64341.991 | I81: =Table8[[#This Row],[الاجمالي بدون الضريبه14%]]-Table8[[#This Row],[القاهرة ]]-Table8[[#This Row],[المنصورة ]]-Table8[[#This Row],[القانونيه ]] -> 64341.991 | J81: =D81-E81 -> 9007.8788 | K81: =E81*$K$3 -> 1930.2597 | L81: =D81-K81 -> 71419.61 | M81: 71419.61 | O81: =M81-L81-N81 -> 0 | Q81: =IFERROR((Table8[[#This Row],[تاريخ الاستحقاق]]-Table8[[#This Row],[تاريخ اصدار الفاتورة ]]),0) -> -45825 | R81: =IF(Table8[[#This Row],[تاريخ الاستحقاق]]<$S$1,"مستحق","غير مستحق") -> مستحق | S81: =Table8[[#This Row],[تاريخ الاستحقاق]]-$S$1 -> -46006 | U81: =Table8[[#This Row],[المبلغ المسدد]]/1.14 -> 62648.781
A82: فورى لتكنولوجيا المعلومات التجارية | B82: 45778 | C82: 45834 | D82: 79050.7 | E82: =D82/1.14 -> 69342.719 | I82: =Table8[[#This Row],[الاجمالي بدون الضريبه14%]]-Table8[[#This Row],[القاهرة ]]-Table8[[#This Row],[المنصورة ]]-Table8[[#This Row],[القانونيه ]] -> 69342.719 | J82: =D82-E82 -> 9707.9807 | K82: =E82*$K$3 -> 2080.2816 | L82: =D82-K82 -> 76970.418 | M82: 76970.418 | O82: =M82-L82-N82 -> 0 | Q82: =IFERROR((Table8[[#This Row],[تاريخ الاستحقاق]]-Table8[[#This Row],[تاريخ اصدار الفاتورة ]]),0) -> -45834 | R82: =IF(Table8[[#This Row],[تاريخ الاستحقاق]]<$S$1,"مستحق","غير مستحق") -> مستحق | S82: =Table8[[#This Row],[تاريخ الاستحقاق]]-$S$1 -> -46006 | U82: =Table8[[#This Row],[المبلغ المسدد]]/1.14 -> 67517.911
A83: فاليو قانونى | B83: 45748 | C83: 45836 | D83: 227259 | E83: =D83/1.14 -> 199350 | I83: =Table8[[#This Row],[الاجمالي بدون الضريبه14%]]-Table8[[#This Row],[القاهرة ]]-Table8[[#This Row],[المنصورة ]]-Table8[[#This Row],[القانونيه ]] -> 199350 | J83: =D83-E83 -> 27909 | K83: =E83*$K$3 -> 5980.5 | L83: =D83-K83 -> 221278.5 | M83: 221278.5 | O83: =M83-L83-N83 -> 0 | Q83: =IFERROR((Table8[[#This Row],[تاريخ الاستحقاق]]-Table8[[#This Row],[تاريخ اصدار الفاتورة ]]),0) -> -45836 | R83: =IF(Table8[[#This Row],[تاريخ الاستحقاق]]<$S$1,"مستحق","غير مستحق") -> مستحق | S83: =Table8[[#This Row],[تاريخ الاستحقاق]]-$S$1 -> -46006 | U83: =Table8[[#This Row],[المبلغ المسدد]]/1.14 -> 194103.95
A84: شركه رايه قانونى | B84: 45809 | C84: 45836 | D84: 299820 | E84: =D84/1.14 -> 263000 | I84: =Table8[[#This Row],[الاجمالي بدون الضريبه14%]]-Table8[[#This Row],[القاهرة ]]-Table8[[#This Row],[المنصورة ]]-Table8[[#This Row],[القانونيه ]] -> 263000 | J84: =D84-E84 -> 36820 | K84: =E84*$K$3 -> 7890 | L84: =D84-K84 -> 291930 | M84: 291930 | O84: =M84-L84-N84 -> 0 | Q84: =IFERROR((Table8[[#This Row],[تاريخ الاستحقاق]]-Table8[[#This Row],[تاريخ اصدار الفاتورة ]]),0) -> -45836 | R84: =IF(Table8[[#This Row],[تاريخ الاستحقاق]]<$S$1,"مستحق","غير مستحق") -> مستحق | S84: =Table8[[#This Row],[تاريخ الاستحقاق]]-$S$1 -> -46006 | U84: =Table8[[#This Row],[المبلغ المسدد]]/1.14 -> 256078.95
A85: امان لتمويل المشروعات | B85: 45778 | C85: 45844 | D85: 3093.96 | E85: =D85/1.14 -> 2714 | I85: =Table8[[#This Row],[الاجمالي بدون الضريبه14%]]-Table8[[#This Row],[القاهرة ]]-Table8[[#This Row],[المنصورة ]]-Table8[[#This Row],[القانونيه ]] -> 2714 | J85: =D85-E85 -> 379.96 | K85: =E85*$K$3 -> 81.42 | L85: =D85-K85 -> 3012.54 | M85: 3012.54 | O85: =M85-L85-N85 -> 0 | Q85: =IFERROR((Table8[[#This Row],[تاريخ الاستحقاق]]-Table8[[#This Row],[تاريخ اصدار الفاتورة ]]),0) -> -45844 | R85: =IF(Table8[[#This Row],[تاريخ الاستحقاق]]<$S$1,"مستحق","غير مستحق") -> مستحق | S85: =Table8[[#This Row],[تاريخ الاستحقاق]]-$S$1 -> -46006 | U85: =Table8[[#This Row],[المبلغ المسدد]]/1.14 -> 2642.5789
A86: اور للتمويل الاستهلاكى -وسيلة | B86: 45748 | C86: 45844 | D86: 220441.45 | E86: =D86/1.14 -> 193369.69 | I86: =Table8[[#This Row],[الاجمالي بدون الضريبه14%]]-Table8[[#This Row],[القاهرة ]]-Table8[[#This Row],[المنصورة ]]-Table8[[#This Row],[القانونيه ]] -> 193369.69 | J86: =D86-E86 -> 27071.757 | K86: =E86*$K$3 -> 5801.0908 | L86: =D86-K86 -> 214640.36 | M86: 214640.36 | O86: =M86-L86-N86 -> 0.00078947365 | Q86: =IFERROR((Table8[[#This Row],[تاريخ الاستحقاق]]-Table8[[#This Row],[تاريخ اصدار الفاتورة ]]),0) -> -45844 | R86: =IF(Table8[[#This Row],[تاريخ الاستحقاق]]<$S$1,"مستحق","غير مستحق") -> مستحق | S86: =Table8[[#This Row],[تاريخ الاستحقاق]]-$S$1 -> -46006 | U86: =Table8[[#This Row],[المبلغ المسدد]]/1.14 -> 188281.02
A87: تنميه لخدمات المشروعات متناهيه الصغر | B87: 45778 | C87: 45845 | D87: 141737.11 | E87: =D87/1.14 -> 124330.8 | I87: =Table8[[#This Row],[الاجمالي بدون الضريبه14%]]-Table8[[#This Row],[القاهرة ]]-Table8[[#This Row],[المنصورة ]]-Table8[[#This Row],[القانونيه ]] -> 124330.8 | J87: =D87-E87 -> 17406.312 | K87: =E87*$K$3 -> 3729.9239 | L87: =D87-K87 -> 138007.19 | M87: 138007.19 | O87: =M87-L87-N87 -> 0 | Q87: =IFERROR((Table8[[#This Row],[تاريخ الاستحقاق]]-Table8[[#This Row],[تاريخ اصدار الفاتورة ]]),0) -> -45845 | R87: =IF(Table8[[#This Row],[تاريخ الاستحقاق]]<$S$1,"مستحق","غير مستحق") -> مستحق | S87: =Table8[[#This Row],[تاريخ الاستحقاق]]-$S$1 -> -46006 | U87: =Table8[[#This Row],[المبلغ المسدد]]/1.14 -> 121058.94
A88: شركه رايه قانونى | B88: 45839 | C88: 45847 | D88: 628140 | E88: =D88/1.14 -> 551000 | I88: =Table8[[#This Row],[الاجمالي بدون الضريبه14%]]-Table8[[#This Row],[القاهرة ]]-Table8[[#This Row],[المنصورة ]]-Table8[[#This Row],[القانونيه ]] -> 551000 | J88: =D88-E88 -> 77140 | K88: =E88*$K$3 -> 16530 | L88: =D88-K88 -> 611610 | M88: 611610 | O88: =M88-L88-N88 -> 0 | Q88: =IFERROR((Table8[[#This Row],[تاريخ الاستحقاق]]-Table8[[#This Row],[تاريخ اصدار الفاتورة ]]),0) -> -45847 | R88: =IF(Table8[[#This Row],[تاريخ الاستحقاق]]<$S$1,"مستحق","غير مستحق") -> مستحق | S88: =Table8[[#This Row],[تاريخ الاستحقاق]]-$S$1 -> -46006 | U88: =Table8[[#This Row],[المبلغ المسدد]]/1.14 -> 536500
A89: ميد للتقسيط | B89: 45778 | C89: 45847 | D89: 149327.38 | E89: =D89/1.14 -> 130988.93 | I89: =Table8[[#This Row],[الاجمالي بدون الضريبه14%]]-Table8[[#This Row],[القاهرة ]]-Table8[[#This Row],[المنصورة ]]-Table8[[#This Row],[القانونيه ]] -> 130988.93 | J89: =D89-E89 -> 18338.45 | K89: =E89*$K$3 -> 3929.6679 | L89: =D89-K89 -> 145397.71 | M89: 114793 | O89: =M89-L89-N89 -> -30604.712 | Q89: =IFERROR((Table8[[#This Row],[تاريخ الاستحقاق]]-Table8[[#This Row],[تاريخ اصدار الفاتورة ]]),0) -> -45847 | R89: =IF(Table8[[#This Row],[تاريخ الاستحقاق]]<$S$1,"مستحق","غير مستحق") -> مستحق | S89: =Table8[[#This Row],[تاريخ الاستحقاق]]-$S$1 -> -46006 | U89: =Table8[[#This Row],[المبلغ المسدد]]/1.14 -> 100695.61
A90: بنك البركة مصر | B90: 45809 | C90: 45847 | D90: 23155.68 | E90: =D90/1.14 -> 20312 | I90: =Table8[[#This Row],[الاجمالي بدون الضريبه14%]]-Table8[[#This Row],[القاهرة ]]-Table8[[#This Row],[المنصورة ]]-Table8[[#This Row],[القانونيه ]] -> 20312 | J90: =D90-E90 -> 2843.68 | K90: =E90*$K$3 -> 609.36 | L90: =D90-K90 -> 22546.32 | M90: 22546.32 | O90: =M90-L90-N90 -> 0 | Q90: =IFERROR((Table8[[#This Row],[تاريخ الاستحقاق]]-Table8[[#This Row],[تاريخ اصدار الفاتورة ]]),0) -> -45847 | R90: =IF(Table8[[#This Row],[تاريخ الاستحقاق]]<$S$1,"مستحق","غير مستحق") -> مستحق | S90: =Table8[[#This Row],[تاريخ الاستحقاق]]-$S$1 -> -46006 | U90: =Table8[[#This Row],[المبلغ المسدد]]/1.14 -> 19777.474
A91: شركه رايه للالكترونيات | B91: 45809 | C91: 45847 | D91: 53842.05 | E91: =D91/1.14 -> 47229.868 | I91: =Table8[[#This Row],[الاجمالي بدون الضريبه14%]]-Table8[[#This Row],[القاهرة ]]-Table8[[#This Row],[المنصورة ]]-Table8[[#This Row],[القانونيه ]] -> 47229.868 | J91: =D91-E91 -> 6612.1816 | K91: =E91*$K$3 -> 1416.8961 | L91: =D91-K91 -> 52425.154 | M91: 51480.56 | N91: =-Table8[[#This Row],[الاجمالي بدون الضريبه14%]]*0.02 -> -944.59737 | O91: =M91-L91-N91 -> 0.0034210526 | Q91: =IFERROR((Table8[[#This Row],[تاريخ الاستحقاق]]-Table8[[#This Row],[تاريخ اصدار الفاتورة ]]),0) -> -45847 | R91: =IF(Table8[[#This Row],[تاريخ الاستحقاق]]<$S$1,"مستحق","غير مستحق") -> مستحق | S91: =Table8[[#This Row],[تاريخ الاستحقاق]]-$S$1 -> -46006 | U91: =Table8[[#This Row],[المبلغ المسدد]]/1.14 -> 45158.386
A92: بنك الإسكندرية | B92: 45809 | C92: 45851 | D92: 123728.43 | E92: =D92/1.14 -> 108533.71 | I92: =Table8[[#This Row],[الاجمالي بدون الضريبه14%]]-Table8[[#This Row],[القاهرة ]]-Table8[[#This Row],[المنصورة ]]-Table8[[#This Row],[القانونيه ]] -> 108533.71 | J92: =D92-E92 -> 15194.719 | K92: =E92*$K$3 -> 3256.0113 | L92: =D92-K92 -> 120472.42 | M92: 120472.42 | O92: =M92-L92-N92 -> 0 | Q92: =IFERROR((Table8[[#This Row],[تاريخ الاستحقاق]]-Table8[[#This Row],[تاريخ اصدار الفاتورة ]]),0) -> -45851 | R92: =IF(Table8[[#This Row],[تاريخ الاستحقاق]]<$S$1,"مستحق","غير مستحق") -> مستحق | S92: =Table8[[#This Row],[تاريخ الاستحقاق]]-$S$1 -> -46006 | U92: =Table8[[#This Row],[المبلغ المسدد]]/1.14 -> 105677.56
A93: مانى فيللوز لتكنولوجيا المعلومات وادارة المشروعات | B93: 45778 | C93: 45851 | D93: 137409.68 | E93: =D93/1.14 -> 120534.81 | I93: =Table8[[#This Row],[الاجمالي بدون الضريبه14%]]-Table8[[#This Row],[القاهرة ]]-Table8[[#This Row],[المنصورة ]]-Table8[[#This Row],[القانونيه ]] -> 120534.81 | J93: =D93-E93 -> 16874.873 | K93: =E93*$K$3 -> 3616.0442 | L93: =D93-K93 -> 133793.64 | M93: 133793.64 | O93: =M93-L93-N93 -> 0 | Q93: =IFERROR((Table8[[#This Row],[تاريخ الاستحقاق]]-Table8[[#This Row],[تاريخ اصدار الفاتورة ]]),0) -> -45851 | R93: =IF(Table8[[#This Row],[تاريخ الاستحقاق]]<$S$1,"مستحق","غير مستحق") -> مستحق | S93: =Table8[[#This Row],[تاريخ الاستحقاق]]-$S$1 -> -46006 | U93: =Table8[[#This Row],[المبلغ المسدد]]/1.14 -> 117362.84
A94: بنك كريدي اجريكول مصر | B94: 45809 | C94: 45852 | D94: 201215.25 | E94: =D94/1.14 -> 176504.6 | I94: =Table8[[#This Row],[الاجمالي بدون الضريبه14%]]-Table8[[#This Row],[القاهرة ]]-Table8[[#This Row],[المنصورة ]]-Table8[[#This Row],[القانونيه ]] -> 176504.6 | J94: =D94-E94 -> 24710.644 | K94: =E94*$K$3 -> 5295.1381 | L94: =D94-K94 -> 195920.11 | M94: 192390.02 | N94: =-Table8[[#This Row],[الاجمالي بدون الضريبه14%]]*0.02 -> -3530.0921 | O94: =M94-L94-N94 -> 0.0029785965 | Q94: =IFERROR((Table8[[#This Row],[تاريخ الاستحقاق]]-Table8[[#This Row],[تاريخ اصدار الفاتورة ]]),0) -> -45852 | R94: =IF(Table8[[#This Row],[تاريخ الاستحقاق]]<$S$1,"مستحق","غير مستحق") -> مستحق | S94: =Table8[[#This Row],[تاريخ الاستحقاق]]-$S$1 -> -46006 | U94: =Table8[[#This Row],[المبلغ المسدد]]/1.14 -> 168763.18
